Workbook

Sheet DETAILS
B5: Member Name | C5: Phone number | D5: Date | E5: Amount 1 | F5: Type | G5: Date | H5: Amount 2 | I5: Type | J5: Date | K5: Amount 3 | L5: Type | M5: Date | N5: Amount 4 | O5: Type | P5: Date | Q5: Amount 5 | R5: Type | S5: Date | T5: Amount 6 | U5: Type | V5: Date | W5: Amount 7 | X5: Type | Y5: Date | Z5: Amount 8 | AA5: Type | AB5: Date | AC5: Amount 9 | AD5: Type | AE5: Date | AF5: Amount 10 | AG5: Type | AH5: Date | AI5: Amount 11 | AJ5: Type | AK5: Date | AL5: Amount 12 | AM5: Type | AN5: Date | AO5: Amount 13 | AP5: Type | AQ5: Date | AR5: Amount 14 | AS5: Type | AT5: Date | AU5: Amount 15 | AV5: Type | AW5: Grand Total | AX5: Total Socio | AY5: Total Shares | AZ5: Grand Total
A6: 1 | B6: Felix Daniel | D6: 45348 | E6: 1000 | F6: Opening | G6: 45352 | H6: 10000 | I6: Social | J6: 45352 | K6: 60000 | L6: Shares | M6: 45355 | N6: 70000 | O6: Shares | AW6: =E6+H6+K6+N6+Q6+T6+W6+Z6+AC6+AF6+AI6+AO6+AL6+AR6 -> 141000 | AX6: =E6+H6 -> 11000 | AY6: =K6+N6 -> 130000 | AZ6: =AX6+AY6 -> 141000 | BA6: =AZ6=AW6 -> TRUE
A7: 2 | B7: Norbert Massay | D7: 45351 | E7: 50000 | F7: Shares | G7: 45351 | H7: 120000 | I7: Shares | J7: 45351 | K7: 30000 | L7: Social | M7: 45353 | N7: 360000 | O7: Shares | P7: 45354 | Q7: 140000 | R7: Social | S7: 45492 | T7: 100000 | U7: Shares | V7: 45648 | W7: 200000 | X7: Shares | Y7: 45727 | Z7: 100000 | AA7: NMB | AB7: 45728 | AC7: 100000 | AD7: NMB | AW7: =E7+H7+K7+N7+Q7+T7+W7+Z7+AC7+AF7+AI7+AO7+AL7+AR7 -> 1200000 | AX7: =K7+Q7 -> 170000 | AY7: =E7+H7+N7+T7+W7+Z7+AC7 -> 1030000 | AZ7: =AX7+AY7 -> 1200000 | BA7: =AZ7=AW7 -> TRUE
A8: 3 | B8: Mohamed Mohamed | D8: 45352 | E8: 50000 | F8: Shares | G8: 45362 | H8: 120000 | I8: Shares | J8: 45529 | K8: 630000 | L8: Shares | M8: 45654 | N8: 200000 | O8: Shares | AW8: =E8+H8+K8+N8+Q8+T8+W8+Z8+AC8+AF8+AI8+AO8+AL8+AR8 -> 1000000 | AY8: =E8+H8+K8+W7 -> 1000000 | AZ8: =AX8+AY8 -> 1000000 | BA8: =AZ8=AW8 -> TRUE
A9: 4 | B9: Evarist Francisco | D9: 45352 | E9: 90000 | F9: Shares | G9: 45352 | H9: 10000 | I9: Social | J9: 45353 | K9: 50000 | L9: Shares | M9: 45353 | N9: 30000 | O9: Social | P9: 45529 | Q9: 100000 | R9: Shares | S9: 45530 | T9: 100000 | U9: Shares | V9: 45657 | W9: 450000 | X9: Shares | Y9: 45657 | Z9: 170000 | AA9: Shares | AW9: =E9+H9+K9+N9+Q9+T9+W9+Z9+AC9+AF9+AI9+AO9+AL9+AR9 -> 1000000 | AX9: =H9+N9 -> 40000 | AY9: =E9+K9+Q9+T9+W9+Z9 -> 960000 | AZ9: =AX9+AY9 -> 1000000 | BA9: =AZ9=AW9 -> TRUE
A10: 5 | B10: Emmanuel Matee | D10: 45352 | E10: 10000 | F10: Social | G10: 45353 | H10: 20000 | I10: Social | J10: 45353 | K10: 120000 | L10: Shares | M10: 45353 | N10: 50000 | O10: Shares | P10: 45354 | Q10: 50000 | R10: Social | S10: 45394 | T10: 30000 | U10: Social | V10: 45394 | W10: 120000 | X10: Shares | Y10: 45486 | Z10: 20000 | AA10: Social | AB10: 45486 | AC10: 80000 | AD10: Shares | AE10: 45492 | AF10: 40000 | AG10: Social | AH10: 45492 | AI10: =160000+80000 -> 240000 | AJ10: Shares | AK10: 45496 | AL10: 20000 | AM10: Social | AN10: 45648 | AO10: 200000 | AP10: Shares | AQ10: 45690 | AR10: 200000 | AS10: Shares | AT10: 45703 | AU10: 100000 | AV10: Shares | AW10: =E10+H10+K10+N10+Q10+T10+W10+Z10+AC10+AF10+AI10+AO10+AL10+AR10+AU10 -> 1300000 | AX10: =E10+H10+Q10+T10+Z10+AF10+AL10 -> 190000 | AY10: =K10+N10+W10+AC10+AI10+AO10+AR10+AU10 -> 1110000 | AZ10: =AX10+AY10 -> 1300000 | BA10: =AZ10=AW10 -> TRUE
A11: 6 | B11: Innocent Kweka | D11: 45353 | E11: 40000 | F11: Shares | G11: 45353 | H11: 20000 | I11: Social | J11: 45441 | K11: 100000 | L11: Shares | AW11: =E11+H11+K11+N11+Q11+T11+W11+Z11+AC11+AF11+AI11+AO11+AL11+AR11 -> 160000 | AX11: =H11 -> 20000 | AY11: =E11+K11 -> 140000 | AZ11: =AX11+AY11 -> 160000 | BA11: =AZ11=AW11 -> TRUE
A12: 7 | B12: Kanuti Simba | D12: 45354 | E12: 120000 | F12: Social | G12: 45354 | H12: 500000 | I12: Shares | J12: 45363 | K12: 100000 | L12: Shares | M12: 45529 | N12: 80000 | O12: Shares | P12: 45652 | Q12: 200000 | R12: Shares | AW12: =E12+H12+K12+N12+Q12+T12+W12+Z12+AC12+AF12+AI12+AO12+AL12+AR12 -> 1000000 | AX12: =E12 -> 120000 | AY12: =H12+K12+N12+Q12 -> 880000 | AZ12: =AX12+AY12 -> 1000000 | BA12: =AZ12=AW12 -> TRUE
A13: 8 | B13: Evance Mori | D13: 45354 | E13: 100000 | F13: Shares | G13: 45361 | H13: 100000 | I13: Shares | J13: 45411 | K13: 50000 | L13: Social | M13: 45496 | N13: 100000 | O13: Social | P13: 45521 | Q13: 650000 | R13: Shares | AW13: =E13+H13+K13+N13+Q13+T13+W13+Z13+AC13+AF13+AI13+AO13+AL13+AR13 -> 1000000 | AX13: =K13+N13 -> 150000 | AY13: =E13+H13+Q13 -> 850000 | AZ13: =AX13+AY13 -> 1000000 | BA13: =AZ13=AW13 -> TRUE
A14: 9 | B14: Elianshisaria Munisi | D14: 45354 | E14: 150000 | F14: Shares | G14: 45354 | H14: 70000 | I14: Social | J14: 45521 | K14: 900000 | L14: Shares | M14: 45650 | N14: 100000 | O14: Shares | AW14: =E14+H14+K14+N14+Q14+T14+W14+Z14+AC14+AF14+AI14+AO14+AL14+AR14 -> 1220000 | AX14: =H14 -> 70000 | AY14: =E14+K14+N14 -> 1150000 | AZ14: =AX14+AY14 -> 1220000 | BA14: =AZ14=AW14 -> TRUE
A15: 10 | B15: Stephen Nkurlu | D15: 45355 | E15: 50000 | F15: Social | G15: 45355 | H15: 50000 | I15: Shares | J15: 45358 | K15: 120000 | L15: Shares | M15: 45650 | N15: 800000 | O15: Shares | AW15: =E15+H15+K15+N15+Q15+T15+W15+Z15+AC15+AF15+AI15+AO15+AL15+AR15 -> 1020000 | AX15: =E15 -> 50000 | AY15: =H15+K15+N15 -> 970000 | AZ15: =AX15+AY15 -> 1020000 | BA15: =AZ15=AW15 -> TRUE
A16: 11 | B16: Mosses Makoko | D16: 45355 | E16: 170000 | F16: Social | G16: 45355 | H16: 170000 | I16: Shares | J16: 45530 | K16: 460000 | L16: Shares | M16: 45690 | N16: 200000 | O16: Shares | AW16: =E16+H16+K16+N16+Q16+T16+W16+Z16+AC16+AF16+AI16+AO16+AL16+AR16 -> 1000000 | AX16: =E16 -> 170000 | AY16: =H16+K16+N16 -> 830000 | AZ16: =AX16+AY16 -> 1000000 | BA16: =AZ16=AW16 -> TRUE
A17: 12 | B17: Aaron Mtui | D17: 45355 | E17: 100000 | F17: Shares | AW17: =E17+H17+K17+N17+Q17+T17+W17+Z17+AC17+AF17+AI17+AO17+AL17+AR17 -> 100000 | AY17: =E17 -> 100000 | AZ17: =AX17+AY17 -> 100000 | BA17: =AZ17=AW17 -> TRUE
A18: 13 | B18: Jacob Mangu | D18: 45355 | E18: 100000 | F18: Shares | G18: 45359 | H18: 190000 | I18: Shares | J18: 45359 | K18: 110000 | L18: Social | M18: 45359 | N18: 60000 | O18: Social | P18: 45421 | Q18: 140000 | R18: Shares | S18: 45485 | T18: 140000 | U18: Shares | V18: 45504 | W18: 60000 | X18: Shares | Y18: 45649 | Z18: 200000 | AA18: Shares | AB18: 45702 | AC18: 300000 | AD18: Shares | AE18: 45712 | AF18: 300000 | AG18: Shares | AW18: =E18+H18+K18+N18+Q18+T18+W18+Z18+AC18+AF18+AI18+AO18+AL18+AR18 -> 1600000 | AX18: =K18+N18 -> 170000 | AY18: =E18+H18+Q18+T18+W18+Z18+AC18+AF18 -> 1430000 | AZ18: =AX18+AY18 -> 1600000 | BA18: =AZ18=AW18 -> TRUE
A19: 14 | B19: Nsanyiwa Kiloba | D19: 45355 | E19: 170000 | F19: Shares | G19: 45355 | H19: 80000 | I19: Social | J19: 45361 | K19: 170000 | L19: Shares | M19: 45361 | N19: 90000 | O19: Social | P19: 45370 | Q19: 100000 | R19: Shares | S19: 45655 | T19: 400000 | U19: Shares | AW19: =E19+H19+K19+N19+Q19+T19+W19+Z19+AC19+AF19+AI19+AO19+AL19+AR19 -> 1010000 | AX19: =H19+N19 -> 170000 | AY19: =E19+K19+Q19+T19 -> 840000 | AZ19: =AX19+AY19 -> 1010000 | BA19: =AZ19=AW19 -> TRUE
A20: 15 | B20: Ahmad Yahya | D20: 45356 | E20: 50000 | F20: Shares | G20: 45359 | H20: 40000 | I20: Social | J20: 45373 | K20: 50000 | L20: Social | M20: 45373 | N20: 120000 | O20: Shares | P20: 45663 | Q20: 780000 | R20: Shares | AW20: =E20+H20+K20+N20+Q20+T20+W20+Z20+AC20+AF20+AI20+AO20+AL20+AR20 -> 1040000 | AX20: =H20+K20 -> 90000 | AY20: =E20+N20+Q20 -> 950000 | AZ20: =AX20+AY20 -> 1040000 | BA20: =AZ20=AW20 -> TRUE
A21: 16 | B21: Paul Metili | D21: 45356 | E21: 10000 | F21: Social | G21: 45356 | H21: 50000 | I21: Shares | J21: 45356 | K21: 40000 | L21: Social | AW21: =E21+H21+K21+N21+Q21+T21+W21+Z21+AC21+AF21+AI21+AO21+AL21+AR21 -> 100000 | AX21: =E21+K21 -> 50000 | AY21: =H21 -> 50000 | AZ21: =AX21+AY21 -> 100000 | BA21: =AZ21=AW21 -> TRUE
A22: 17 | B22: Patiens Rweyemamu | D22: 45356 | E22: 50000 | F22: Shares | G22: 45356 | H22: 50000 | I22: Social | AW22: =E22+H22+K22+N22+Q22+T22+W22+Z22+AC22+AF22+AI22+AO22+AL22+AR22 -> 100000 | AX22: =H22 -> 50000 | AY22: =E22 -> 50000 | AZ22: =AX22+AY22 -> 100000 | BA22: =AZ22=AW22 -> TRUE
A23: 18 | B23: Elibariki Mkumbo | D23: 45357 | E23: 250000 | F23: Shares | G23: 45365 | H23: 100000 | I23: Social | J23: 45530 | K23: 230000 | L23: Shares | M23: 45687 | N23: 420000 | O23: Shares | AW23: =E23+H23+K23+N23+Q23+T23+W23+Z23+AC23+AF23+AI23+AO23+AL23+AR23 -> 1000000 | AX23: =H23 -> 100000 | AY23: =E23+K23+N23 -> 900000 | AZ23: =AX23+AY23 -> 1000000 | BA23: =AZ23=AW23 -> TRUE
A24: 19 | B24: David Koillah | D24: 45357 | E24: 50000 | F24: Social | G24: 45357 | H24: 50000 | I24: Shares | AW24: =E24+H24+K24+N24+Q24+T24+W24+Z24+AC24+AF24+AI24+AO24+AL24+AR24 -> 100000 | AX24: =E24 -> 50000 | AY24: =H24 -> 50000 | AZ24: =AX24+AY24 -> 100000 | BA24: =AZ24=AW24 -> TRUE
A25: 20 | B25: Innocent Kasigwa | D25: 45357 | E25: 50000 | F25: Shares | G25: 45381 | H25: 150000 | I25: Shares | J25: 45649 | K25: 300000 | L25: Shares | M25: 45659 | N25: 500000 | O25: Shares | AW25: =E25+H25+K25+N25+Q25+T25+W25+Z25+AC25+AF25+AI25+AO25+AL25+AR25 -> 1000000 | AY25: =E25+H25+K25+N25 -> 1000000 | AZ25: =AX25+AY25 -> 1000000 | BA25: =AZ25=AW25 -> TRUE
A26: 21 | B26: Omary Mwasema | D26: 45357 | E26: 50000 | F26: Shares | AW26: =E26+H26+K26+N26+Q26+T26+W26+Z26+AC26+AF26+AI26+AO26+AL26+AR26 -> 50000 | AY26: =E26 -> 50000 | AZ26: =AX26+AY26 -> 50000 | BA26: =AZ26=AW26 -> TRUE
A27: 22 | B27: Erick Kitali | D27: 45357 | E27: 80000 | F27: Social | G27: 45358 | H27: 170000 | I27: Shares | J27: 45525 | K27: 550000 | L27: Shares | M27: 45648 | N27: 200000 | O27: Shares | P27: 45727 | Q27: 300000 | R27: NMB | AW27: =E27+H27+K27+N27+Q27+T27+W27+Z27+AC27+AF27+AI27+AO27+AL27+AR27 -> 1300000 | AX27: =E27 -> 80000 | AY27: =H27+K27+N27+Q27 -> 1220000 | AZ27: =AX27+AY27 -> 1300000 | BA27: =AZ27=AW27 -> TRUE
A28: 23 | B28: Emmanuel Matechi | D28: 45358 | E28: 50000 | F28: Social | G28: 45382 | H28: 50000 | I28: Shares | J28: 45652 | K28: 400000 | L28: Shares | M28: 45656 | N28: 450000 | O28: Shares | P28: 45657 | Q28: 50000 | R28: Shares | AW28: =E28+H28+K28+N28+Q28+T28+W28+Z28+AC28+AF28+AI28+AO28+AL28+AR28 -> 1000000 | AX28: =E28 -> 50000 | AY28: =H28+K28+N28+Q28 -> 950000 | AZ28: =AX28+AY28 -> 1000000 | BA28: =AZ28=AW28 -> TRUE
A29: 24 | B29: Khalifa Sushy | D29: 45359 | E29: 100000 | F29: Social | G29: 45359 | H29: 130000 | I29: Shares | J29: 45383 | K29: 70000 | L29: Social | M29: 45383 | N29: 120000 | O29: Shares | AW29: =E29+H29+K29+N29+Q29+T29+W29+Z29+AC29+AF29+AI29+AO29+AL29+AR29 -> 420000 | AX29: =E29+K29 -> 170000 | AY29: =H29+N29 -> 250000 | AZ29: =AX29+AY29 -> 420000 | BA29: =AZ29=AW29 -> TRUE
A30: 25 | B30: Liggyle Vumilia | D30: 45359 | E30: 50000 | F30: Shares | G30: 45360 | H30: 90000 | I30: Shares | J30: 45360 | K30: 30000 | L30: Social | M30: 45380 | N30: 150000 | O30: Shares | P30: 45380 | Q30: 30000 | R30: Social | AW30: =E30+H30+K30+N30+Q30+T30+W30+Z30+AC30+AF30+AI30+AO30+AL30+AR30 -> 350000 | AX30: =K30+Q30 -> 60000 | AY30: =E30+H30+N30 -> 290000 | AZ30: =AX30+AY30 -> 350000 | BA30: =AZ30=AW30 -> TRUE
A31: 26 | B31: Ernest Shirima | D31: 45360 | E31: 290000 | F31: Shares | G31: 45360 | H31: 110000 | I31: Social | J31: 45523 | K31: 340000 | L31: Shares | M31: 45523 | N31: 60000 | O31: Social | AW31: =E31+H31+K31+N31+Q31+T31+W31+Z31+AC31+AF31+AI31+AO31+AL31+AR31 -> 800000 | AX31: =H31+N31 -> 170000 | AY31: =E31+K31 -> 630000 | AZ31: =AX31+AY31 -> 800000 | BA31: =AZ31=AW31 -> TRUE
A32: 27 | B32: Walter Salema | D32: 45360 | E32: 60000 | F32: Social | G32: 45360 | H32: 90000 | I32: Shares | J32: 45526 | K32: 650000 | L32: Shares | AW32: =E32+H32+K32+N32+Q32+T32+W32+Z32+AC32+AF32+AI32+AO32+AL32+AR32 -> 800000 | AX32: =E32 -> 60000 | AY32: =H32+K32 -> 740000 | AZ32: =AX32+AY32 -> 800000 | BA32: =AZ32=AW32 -> TRUE
A33: 28 | B33: Stanslaus Nyembea | D33: 45360 | E33: 120000 | F33: Shares | AW33: =E33+H33+K33+N33+Q33+T33+W33+Z33+AC33+AF33+AI33+AO33+AL33+AR33 -> 120000 | AY33: =E33 -> 120000 | AZ33: =AX33+AY33 -> 120000 | BA33: =AZ33=AW33 -> TRUE
A34: 29 | B34: Abraham Assenga | D34: 45360 | E34: 90000 | F34: Shares | G34: 45360 | H34: 60000 | I34: Social | J34: 45530 | K34: 600000 | L34: Shares | M34: 45530 | N34: 200000 | O34: Shares | P34: 45657 | Q34: 50000 | R34: Shares | AW34: =E34+H34+K34+N34+Q34+T34+W34+Z34+AC34+AF34+AI34+AO34+AL34+AR34 -> 1000000 | AX34: =H34 -> 60000 | AY34: =E34+K34+N34+Q34 -> 940000 | AZ34: =AX34+AY34 -> 1000000 | BA34: =AZ34=AW34 -> TRUE
A35: 30 | B35: Abduel Kitururu | D35: 45361 | E35: 280000 | F35: Shares | G35: 45361 | H35: 70000 | I35: Social | J35: 45361 | K35: 280000 | L35: Shares | AW35: =E35+H35+K35+N35+Q35+T35+W35+Z35+AC35+AF35+AI35+AO35+AL35+AR35 -> 630000 | AX35: =H35 -> 70000 | AY35: =E35+K35 -> 560000 | AZ35: =AX35+AY35 -> 630000 | BA35: =AZ35=AW35 -> TRUE
A36: 31 | B36: Masale Masale | D36: 45361 | E36: 100000 | F36: Social | G36: 45361 | H36: 250000 | I36: Shares | J36: 45637 | K36: 450000 | L36: Shares | M36: 45650 | N36: 200000 | O36: Shares | AW36: =E36+H36+K36+N36+Q36+T36+W36+Z36+AC36+AF36+AI36+AO36+AL36+AR36 -> 1000000 | AX36: =E36 -> 100000 | AY36: =H36+K36+N36 -> 900000 | AZ36: =AX36+AY36 -> 1000000 | BA36: =AZ36=AW36 -> TRUE
A37: 32 | B37: Bakari Hemedi | D37: 45361 | E37: 50000 | F37: Shares | G37: 45361 | H37: 50000 | I37: Social | J37: 45669 | K37: 1000000 | L37: Shares | AW37: =E37+H37+K37+N37+Q37+T37+W37+Z37+AC37+AF37+AI37+AO37+AL37+AR37 -> 1100000 | AX37: =H37 -> 50000 | AY37: =E37+K37 -> 1050000 | AZ37: =AX37+AY37 -> 1100000 | BA37: =AZ37=AW37 -> TRUE
A38: 33 | B38: Athumani Mwasha | D38: 45363 | E38: 170000 | F38: Social | G38: 45363 | H38: 130000 | I38: Shares | J38: 45524 | K38: 220000 | L38: Shares | M38: 45530 | N38: 280000 | O38: Shares | P38: 45659 | Q38: 200000 | R38: Shares | AW38: =E38+H38+K38+N38+Q38+T38+W38+Z38+AC38+AF38+AI38+AO38+AL38+AR38 -> 1000000 | AX38: =E38 -> 170000 | AY38: =H38+K38+N38+Q38 -> 830000 | AZ38: =AX38+AY38 -> 1000000 | BA38: =AZ38=AW38 -> TRUE
A39: 34 | B39: Nalogwa Kiula | D39: 45363 | E39: 50000 | F39: Social | AW39: =E39+H39+K39+N39+Q39+T39+W39+Z39+AC39+AF39+AI39+AO39+AL39+AR39 -> 50000 | AX39: =E39 -> 50000 | AZ39: =AX39+AY39 -> 50000 | BA39: =AZ39=AW39 -> TRUE
A40: 35 | B40: Best Magoma | D40: 45363 | E40: 50000 | F40: Social | G40: 45382 | H40: 100000 | I40: Shares | J40: 45487 | K40: 100000 | L40: Shares | M40: 45652 | N40: 200000 | O40: Shares | P40: 45656 | Q40: 550000 | R40: Shares | AW40: =E40+H40+K40+N40+Q40+T40+W40+Z40+AC40+AF40+AI40+AO40+AL40+AR40 -> 1000000 | AX40: =E40 -> 50000 | AY40: =H40+K40+N40+Q40 -> 950000 | AZ40: =AX40+AY40 -> 1000000 | BA40: =AZ40=AW40 -> TRUE
A41: 36 | B41: Gideon Gabriel | D41: 45369 | E41: 80000 | F41: Social | G41: 45369 | H41: 90000 | I41: Shares | J41: 45683 | K41: 200000 | L41: Shares | AW41: =E41+H41+K41+N41+Q41+T41+W41+Z41+AC41+AF41+AI41+AO41+AL41+AR41 -> 370000 | AX41: =E41 -> 80000 | AY41: =H41+K41 -> 290000 | AZ41: =AX41+AY41 -> 370000 | BA41: =AZ41=AW41 -> TRUE
A42: 37 | B42: Amos Nungu | D42: 45369 | E42: 220000 | F42: Shares | G42: 45369 | H42: 80000 | I42: Social | J42: 45524 | K42: 550000 | L42: Shares | M42: 45683 | N42: 150000 | O42: Shares | AW42: =E42+H42+K42+N42+Q42+T42+W42+Z42+AC42+AF42+AI42+AO42+AL42+AR42 -> 1000000 | AX42: =H42 -> 80000 | AY42: =E42+K42+N42 -> 920000 | AZ42: =AX42+AY42 -> 1000000 | BA42: =AZ42=AW42 -> TRUE
A43: 38 | B43: Mlindwa Kashindye | D43: 45369 | E43: 150000 | F43: Social | G43: 45370 | H43: 20000 | I43: Social | J43: 45370 | K43: 200000 | L43: Shares | M43: 45382 | N43: 130000 | O43: Shares | P43: 45525 | Q43: 300000 | R43: Shares | S43: 45635 | T43: 200000 | U43: Shares | V43: 45659 | W43: 250000 | X43: Shares | AW43: =E43+H43+K43+N43+Q43+T43+W43+Z43+AC43+AF43+AI43+AO43+AL43+AR43 -> 1250000 | AX43: =E43+H43 -> 170000 | AY43: =K43+N43+Q43+T43+W43 -> 1080000 | AZ43: =AX43+AY43 -> 1250000 | BA43: =AZ43=AW43 -> TRUE
A44: 39 | B44: Emmanuel Msaki | D44: 45369 | E44: 63000 | F44: Shares | G44: 45392 | H44: 50000 | I44: Shares | J44: 45635 | K44: 100000 | L44: Shares | M44: 45653 | N44: 300000 | O44: Shares | AW44: =E44+H44+K44+N44+Q44+T44+W44+Z44+AC44+AF44+AI44+AO44+AL44+AR44 -> 513000 | AY44: =E44+H44+K44+N44 -> 513000 | AZ44: =AX44+AY44 -> 513000 | BA44: =AZ44=AW44 -> TRUE
A45: 40 | B45: John Massawe | D45: 45370 | E45: 50000 | F45: Social | G45: 45370 | H45: 90000 | I45: Shares | J45: 45527 | K45: 660000 | L45: Shares | M45: 45655 | N45: 200000 | O45: Shares | AW45: =E45+H45+K45+N45+Q45+T45+W45+Z45+AC45+AF45+AI45+AO45+AL45+AR45 -> 1000000 | AX45: =E45 -> 50000 | AY45: =H45+K45+N45 -> 950000 | AZ45: =AX45+AY45 -> 1000000 | BA45: =AZ45=AW45 -> TRUE
A46: 41 | B46: Werema Msongo | D46: 45370 | E46: 530000 | F46: Shares | G46: 45370 | H46: 230000 | I46: Social | J46: 45523 | K46: 40000 | L46: Shares | AW46: =E46+H46+K46+N46+Q46+T46+W46+Z46+AC46+AF46+AI46+AO46+AL46+AR46 -> 800000 | AX46: =H46 -> 230000 | AY46: =E46+K46 -> 570000 | AZ46: =AX46+AY46 -> 800000 | BA46: =AZ46=AW46 -> TRUE
A47: 42 | B47: Nixon Matowo | D47: 45370 | E47: 50000 | F47: Social | G47: 45370 | H47: 50000 | I47: Shares | J47: 45386 | K47: 100000 | L47: Shares | M47: 45386 | N47: 10000 | O47: Social | P47: 45641 | Q47: 150000 | R47: Shares | S47: 45649 | T47: 100000 | U47: Shares | V47: 45658 | W47: 50000 | X47: Shares | Y47: 45661 | Z47: 200000 | AA47: Shares | AB47: 45708 | AC47: 300000 | AD47: Shares | AW47: =E47+H47+K47+N47+Q47+T47+W47+Z47+AC47+AF47+AI47+AO47+AL47+AR47 -> 1010000 | AX47: =E47+N47 -> 60000 | AY47: =H47+K47+Q47+T47+W47+Z47+AC47 -> 950000 | AZ47: =AX47+AY47 -> 1010000 | BA47: =AZ47=AW47 -> TRUE
A48: 43 | B48: Abdillahi Moshi | D48: 45372 | E48: 80000 | F48: Social | G48: 45372 | H48: 100000 | I48: Shares | J48: 45661 | K48: 820000 | L48: Shares | AW48: =E48+H48+K48+N48+Q48+T48+W48+Z48+AC48+AF48+AI48+AO48+AL48+AR48 -> 1000000 | AX48: =E48+K48 -> 900000 | AY48: =H48 -> 100000 | AZ48: =AX48+AY48 -> 1000000 | BA48: =AZ48=AW48 -> TRUE
A49: 44 | B49: Laurian Gidoyi | D49: 45374 | E49: 170000 | F49: Shares | G49: 45374 | H49: 80000 | I49: Social | J49: 45448 | K49: 50000 | L49: Social | M49: 45636 | N49: 300000 | O49: Shares | P49: 45637 | Q49: 200000 | R49: Shares | S49: 45659 | T49: 200000 | U49: Shares | AW49: =E49+H49+K49+N49+Q49+T49+W49+Z49+AC49+AF49+AI49+AO49+AL49+AR49 -> 1000000 | AX49: =H49+K49 -> 130000 | AY49: =E49+N49+Q49+T49 -> 870000 | AZ49: =AX49+AY49 -> 1000000 | BA49: =AZ49=AW49 -> TRUE
A50: 45 | B50: Albani Kimario | D50: 45380 | E50: 170000 | F50: Social | G50: 45380 | H50: 530000 | I50: Shares | J50: 45530 | K50: 100000 | L50: Shares | M50: 45657 | N50: 200000 | O50: Shares | AW50: =E50+H50+K50+N50+Q50+T50+W50+Z50+AC50+AF50+AI50+AO50+AL50+AR50 -> 1000000 | AX50: =E50 -> 170000 | AY50: =H50+K50+N50 -> 830000 | AZ50: =AX50+AY50 -> 1000000 | BA50: =AZ50=AW50 -> TRUE
A51: 46 | B51: Fredrick Ndosi | D51: 45381 | E51: 50000 | F51: Shares | G51: 45383 | H51: 10000 | I51: Social | J51: 45408 | K51: 10000 | L51: Social | M51: 45529 | N51: 150000 | O51: Social | P51: 45631 | Q51: 580000 | R51: Shares | S51: 45652 | T51: 200000 | U51: Shares | AW51: =E51+H51+K51+N51+Q51+T51+W51+Z51+AC51+AF51+AI51+AO51+AL51+AR51 -> 1000000 | AX51: =H51+K51+N51 -> 170000 | AY51: =E51+Q51+T51 -> 830000 | AZ51: =AX51+AY51 -> 1000000 | BA51: =AZ51=AW51 -> TRUE
A52: 47 | B52: Charles Jangu | D52: 45382 | E52: 100000 | F52: Social | G52: 45382 | H52: 100000 | I52: Shares | J52: 45693 | K52: 500000 | L52: Shares | AW52: =E52+H52+K52+N52+Q52+T52+W52+Z52+AC52+AF52+AI52+AO52+AL52+AR52 -> 700000 | AX52: =E52 -> 100000 | AY52: =H52+K52 -> 600000 | AZ52: =AX52+AY52 -> 700000 | BA52: =AZ52=AW52 -> TRUE
A53: 48 | B53: Hassan Matata | D53: 45384 | E53: 30000 | F53: Social | G53: 45384 | H53: 170000 | I53: Social | J53: 45657 | K53: 800000 | L53: Shares | AW53: =E53+H53+K53+N53+Q53+T53+W53+Z53+AC53+AF53+AI53+AO53+AL53+AR53 -> 1000000 | AX53: =E53+H53 -> 200000 | AY53: =K53 -> 800000 | AZ53: =AX53+AY53 -> 1000000 | BA53: =AZ53=AW53 -> TRUE
A54: 49 | B54: Salum Ndolanga | D54: 45384 | E54: 100000 | F54: Shares | AW54: =E54+H54+K54+N54+Q54+T54+W54+Z54+AC54+AF54+AI54+AO54+AL54+AR54 -> 100000 | AY54: =E54 -> 100000 | AZ54: =AX54+AY54 -> 100000 | BA54: =AZ54=AW54 -> TRUE
A55: 50 | B55: Shumbi Mkumbo | D55: 45392 | E55: 90000 | F55: Social | G55: 45392 | H55: 130000 | I55: Shares | J55: 45524 | K55: 80000 | L55: Shares | M55: 45529 | N55: 270000 | O55: Shares | P55: 45530 | Q55: 230000 | R55: Shares | AW55: =E55+H55+K55+N55+Q55+T55+W55+Z55+AC55+AF55+AI55+AO55+AL55+AR55 -> 800000 | AX55: =E55 -> 90000 | AY55: =H55+K55+N55+Q55 -> 710000 | AZ55: =AX55+AY55 -> 800000 | BA55: =AZ55=AW55 -> TRUE
A56: 51 | B56: Adamu Urassa | D56: 45409 | E56: 250000 | F56: Shares | G56: 45393 | H56: 100000 | I56: Social | J56: 45530 | K56: 450000 | L56: Shares | M56: 45657 | N56: 200000 | O56: Shares | AW56: =E56+H56+K56+N56+Q56+T56+W56+Z56+AC56+AF56+AI56+AO56+AL56+AR56 -> 1000000 | AX56: =H56 -> 100000 | AY56: =E56+K56+N56 -> 900000 | AZ56: =AX56+AY56 -> 1000000 | BA56: =AZ56=AW56 -> TRUE
A57: 52 | B57: Robert Masegese | C57: 0754848616 | D57: 45409 | E57: 100000 | F57: Shares | G57: 45409 | H57: 100000 | I57: Social | AW57: =E57+H57+K57+N57+Q57+T57+W57+Z57+AC57+AF57+AI57+AO57+AL57+AR57 -> 200000 | AX57: =H57 -> 100000 | AY57: =E57 -> 100000 | AZ57: =AX57+AY57 -> 200000 | BA57: =AZ57=AW57 -> TRUE
A58: 53 | B58: Emmanuel Mmari | C58: 0754740047 | D58: 45506 | E58: 900000 | F58: Shares | G58: 45685 | H58: 100000 | I58: Shares | AW58: =E58+H58+K58+N58+Q58+T58+W58+Z58+AC58+AF58+AI58+AO58+AL58+AR58 -> 1000000 | AY58: =E58+H58 -> 1000000 | AZ58: =AX58+AY58 -> 1000000 | BA58: =AZ58=AW58 -> TRUE
A59: 54 | B59: Emanuel Moshi | C59: 0754679533 | D59: 45649 | E59: 800000 | F59: Shares | G59: 45655 | H59: 200000 | I59: Shares | J59: 45687 | K59: 200000 | L59: Shares | AW59: =E59+H59+K59+N59+Q59+T59+W59+Z59+AC59+AF59+AI59+AO59+AL59+AR59 -> 1200000 | AY59: =E59+H59+K59 -> 1200000 | AZ59: =AX59+AY59 -> 1200000 | BA59: =AZ59=AW59 -> TRUE
A60: 55 | B60: Innocent Mosha | D60: 45650 | E60: 800000 | F60: Shares | G60: 45653 | H60: 200000 | I60: Shares | AW60: =E60+H60+K60+N60+Q60+T60+W60+Z60+AC60+AF60+AI60+AO60+AL60+AR60 -> 1000000 | AY60: =E60+H60 -> 1000000 | AZ60: =AX60+AY60 -> 1000000 | BA60: =AZ60=AW60 -> TRUE
A61: 56 | B61: Shabani Salim | D61: 45652 | E61: 1000000 | F61: Shares | AW61: =E61+H61+K61+N61+Q61+T61+W61+Z61+AC61+AF61+AI61+AO61+AL61+AR61 -> 1000000 | AY61: =E61 -> 1000000 | AZ61: =AX61+AY61 -> 1000000 | BA61: =AZ61=AW61 -> TRUE
A62: 57 | B62: Adolph Ndyeabura | C62: 0764812183 | D62: 45660 | E62: 1000000 | F62: Shares | AW62: =E62+H62+K62+N62+Q62+T62+W62+Z62+AC62+AF62+AI62+AO62+AL62+AR62 -> 1000000 | AY62: =E62 -> 1000000 | AZ62: =AX62+AY62 -> 1000000 | BA62: =AZ62=AW62 -> TRUE
A63: 58 | B63: Saidi Ramadhani Mdee | D63: 45662 | E63: 1000000 | F63: Shares | AW63: =E63+H63+K63+N63+Q63+T63+W63+Z63+AC63+AF63+AI63+AO63+AL63+AR63 -> 1000000 | AY63: =E63 -> 1000000 | AZ63: =AX63+AY63 -> 1000000 | BA63: =AZ63=AW63 -> TRUE
A64: 59 | B64: Patrick K. Kiani | C64: 0757800235 | D64: 45669 | E64: 1000000 | F64: Shares | G64: 45728 | H64: 200000 | I64: Shares | AW64: =E64+H64+K64+N64+Q64+T64+W64+Z64+AC64+AF64+AI64+AO64+AL64+AR64 -> 1200000 | AY64: =E64+H64 -> 1200000 | AZ64: =AX64+AY64 -> 1200000 | BA64: =AZ64=AW64 -> TRUE
A65: 60 | AW65: =E65+H65+K65+N65+Q65+T65+W65+Z65+AC65+AF65+AI65+AO65+AL65+AR65 -> 0
A66: 61
A67: 62 | B67: Edgar Rwezaura | C67: 0767077952 | AW67: =E67+H67+K67+N67+Q67+T67+W67+Z67+AC67+AF67+AI67+AO67+AL67 -> 0 | AZ67: =AX67+AY67 -> 0 | BA67: =AZ67=AW67 -> TRUE
A68: 63 | B68: Manase Mushi | C68: 0756636044 | D68: 30000 | AW68: =E68+H68+K68+N68+Q68+T68+W68+Z68+AC68+AF68+AI68+AO68+AL68 -> 0 | AZ68: =AX68+AY68 -> 0 | BA68: =AZ68=AW68 -> TRUE
A69: 64 | B69: Paul Mikongoti | C69: 0754674809 | AW69: =E69+H69+K69+N69+Q69+T69+W69+Z69+AC69+AF69+AI69+AO69+AL69 -> 0 | AZ69: =AX69+AY69 -> 0 | BA69: =AZ69=AW69 -> TRUE
A70: 65 | B70: Moses Luguru | C70: 0715573195 | AW70: =E70+H70+K70+N70+Q70+T70+W70+Z70+AC70+AF70+AI70+AO70+AL70 -> 0 | AZ70: =AX70+AY70 -> 0 | BA70: =AZ70=AW70 -> TRUE
A71: 66 | B71: Emili Mkwawi | C71: 0767449265 | AW71: =E71+H71+K71+N71+Q71+T71+W71+Z71+AC71+AF71+AI71+AO71+AL71 -> 0 | AZ71: =AX71+AY71 -> 0 | BA71: =AZ71=AW71 -> TRUE
A72: 67 | B72: Salum Hassani | C72: 0758252442 | AW72: =E72+H72+K72+N72+Q72+T72+W72+Z72+AC72+AF72+AI72+AO72+AL72 -> 0 | AZ72: =AX72+AY72 -> 0 | BA72: =AZ72=AW72 -> TRUE
A73: 68 | B73: Richard Makala | C73: 0754636961 | AW73: =E73+H73+K73+N73+Q73+T73+W73+Z73+AC73+AF73+AI73+AO73+AL73 -> 0 | AZ73: =AX73+AY73 -> 0 | BA73: =AZ73=AW73 -> TRUE
A74: 69 | B74: Shabani Salim | C74: 0754470291 | AW74: =E74+H74+K74+N74+Q74+T74+W74+Z74+AC74+AF74+AI74+AO74+AL74 -> 0 | AZ74: =AX74+AY74 -> 0 | BA74: =AZ74=AW74 -> TRUE
A75: 70 | B75: Fabian Sedoyeka | C75: 0754238113 | AW75: =E75+H75+K75+N75+Q75+T75+W75+Z75+AC75+AF75+AI75+AO75+AL75 -> 0 | AZ75: =AX75+AY75 -> 0 | BA75: =AZ75=AW75 -> TRUE
A76: 71 | B76: Piniel Seth | C76: 0764510328 | AW76: =E76+H76+K76+N76+Q76+T76+W76+Z76+AC76+AF76+AI76+AO76+AL76 -> 0 | AZ76: =AX76+AY76 -> 0 | BA76: =AZ76=AW76 -> TRUE
A77: 72 | B77: Beatus Chikoti | C77: 0752161634 | AW77: =E77+H77+K77+N77+Q77+T77+W77+Z77+AC77+AF77+AI77+AO77+AL77 -> 0 | AZ77: =AX77+AY77 -> 0 | BA77: =AZ77=AW77 -> TRUE
A78: 73 | B78: Nyangusi Laizer | C78: 076763680 | AW78: =E78+H78+K78+N78+Q78+T78+W78+Z78+AC78+AF78+AI78+AO78+AL78 -> 0 | AZ78: =AX78+AY78 -> 0 | BA78: =AZ78=AW78 -> TRUE
A79: 74 | B79: Anase Minja | C79: 0755774236 | AW79: =E79+H79+K79+N79+Q79+T79+W79+Z79+AC79+AF79+AI79+AO79+AL79 -> 0 | AZ79: =AX79+AY79 -> 0 | BA79: =AZ79=AW79 -> TRUE
A80: 75 | B80: Robert Kitundu | C80: 0765520057 | AW80: =E80+H80+K80+N80+Q80+T80+W80+Z80+AC80+AF80+AI80+AO80+AL80 -> 0 | AZ80: =AX80+AY80 -> 0 | BA80: =AZ80=AW80 -> TRUE
A81: 76 | B81: Msafiri Mwapinga | C81: 0654575128 | AW81: =E81+H81+K81+N81+Q81+T81+W81+Z81+AC81+AF81+AI81+AO81+AL81 -> 0 | AZ81: =AX81+AY81 -> 0 | BA81: =AZ81=AW81 -> TRUE
A82: 77 | AW82: =E82+H82+K82+N82+Q82+T82+W82+Z82+AC82+AF82+AI82+AO82+AL82 -> 0 | AZ82: =AX82+AY82 -> 0 | BA82: =AZ82=AW82 -> TRUE
A83: 78 | AW83: =E83+H83+K83+N83+Q83+T83+W83+Z83+AC83+AF83+AI83+AO83+AL83 -> 0 | AZ83: =AX83+AY83 -> 0 | BA83: =AZ83=AW83 -> TRUE
A84: 79 | AW84: =E84+H84+K84+N84+Q84+T84+W84+Z84+AC84+AF84+AI84+AO84+AL84 -> 0 | AZ84: =AX84+AY84 -> 0 | BA84: =AZ84=AW84 -> TRUE
AW85: =E85+H85+K85+N85+Q85+T85+W85+Z85+AC85+AF85+AI85+AO85+AL85 -> 0 | BA85: =AZ85=AW85 -> TRUE
AW86: =E86+H86+K86+N86+Q86+T86+W86+Z86+AC86+AF86+AI86+AO86+AL86 -> 0 | BA86: =AZ86=AW86 -> TRUE
AW87: =E87+H87+K87+N87+Q87+T87+W87+Z87+AC87+AF87+AI87+AO87+AL87 -> 0 | BA87: =AZ87=AW87 -> TRUE
AW88: =SUM(AW5:AW87) -> 47854000 | AX88: =SUM(AX5:AX87) -> 5441000 | AY88: =SUM(AY5:AY87) -> 42413000 | AZ88: =SUM(AZ5:AZ87) -> 47854000 | BA88: =AZ88=AW88 -> TRUE
AZ89: =46324000+830000 -> 47154000
AY90: NMB | AZ90: =AZ88-AZ89 -> 700000

Sheet Sheet1
B2: Amounts in the NMB BANK
B3: Date | C3: Name | D3: Amount
B4: ='DETAILS (sorted)'!AE45 -> 0 | C4: ='DETAILS (sorted)'!B45 -> Abduel Kitururu | D4: ='DETAILS (sorted)'!AF45 -> 0

Sheet Summary
A1: ILBORU ALUMNI SACCOS LIMITED
A3: MICHANGO YA WANACHAMA
A6: S/N | B6: Member Name | C6: MICHANGO | I6: KIWANGO KINACHOHITAJIKA | K6: KIWANGO CHA KUKAMILISHA | M6: STATUS | N6: GAHRAMA ZA MIKUTANO [allocated already]
C7: KIINGILIO | D7: AKIBA | E7: HISA | F7: JUMLA | H7: ACTUAL | Q7: OCTOBER, 2024 | R7: NOV, 2024 | S7: DEC, 2024 | T7: JAN, 2025 | U7: FEB, 2025
D8: ALLOCATED FROM M-KOBA | E8: ALLOCATED FROM M-KOBA | H8: MKOBA | L8: BADO
A9: 1 | B9: Aaron J. Mtui | C9: 100000 | F9: =SUM(C9:E9) -> 100000 | G9: =F9=H9 -> TRUE | H9: =DETAILS!AZ17 -> 100000 | I9: 1200000 | J9: =H9/I9 -> 0.083333333 | K9: =MAX(I9-H9,0) -> 1100000 | L9: =100%-J9 -> 0.91666667 | M9: WAMESHASAINI MAKABRASHA YA USAJILI. LAKINI WENGI HAWAJAMALIZIA MICHANGO YAO | O9: =F9=H9 -> TRUE
A10: =A9+1 -> 2 | B10: Abduel G. Kitururu | C10: 200000 | D10: 100000 | E10: 330000 | F10: =SUM(C10:E10) -> 630000 | G10: =F10=H10 -> TRUE | H10: =DETAILS!AZ35 -> 630000 | I10: 1200000 | J10: =H10/I10 -> 0.525 | K10: =MAX(I10-H10,0) -> 570000 | L10: =100%-J10 -> 0.475 | O10: =F10=H10 -> TRUE
A11: =A10+1 -> 3 | B11: Abraham A. Assenga | C11: 200000 | D11: 100000 | E11: 700000 | F11: =SUM(C11:E11) -> 1000000 | G11: =F11=H11 -> TRUE | H11: =DETAILS!AZ34 -> 1000000 | I11: 1200000 | J11: =H11/I11 -> 0.83333333 | K11: =MAX(I11-H11,0) -> 200000 | L11: =100%-J11 -> 0.16666667 | O11: =F11=H11 -> TRUE | P11: 1
A12: =A11+1 -> 4 | B12: Adam I. Urassa | C12: 200000 | D12: 100000 | E12: 700000 | F12: =SUM(C12:E12) -> 1000000 | G12: =F12=H12 -> TRUE | H12: =DETAILS!AW56 -> 1000000 | I12: 1200000 | J12: =H12/I12 -> 0.83333333 | K12: =MAX(I12-H12,0) -> 200000 | L12: =100%-J12 -> 0.16666667 | O12: =F12=H12 -> TRUE | P12: 1
A13: =A12+1 -> 5 | B13: Amos M. Nungu | C13: 200000 | D13: 100000 | E13: 700000 | F13: =SUM(C13:E13) -> 1000000 | G13: =F13=H13 -> TRUE | H13: =DETAILS!AW42 -> 1000000 | I13: 1200000 | J13: =H13/I13 -> 0.83333333 | K13: =MAX(I13-H13,0) -> 200000 | L13: =100%-J13 -> 0.16666667 | O13: =F13=H13 -> TRUE | P13: 1
A14: =A13+1 -> 6 | B14: Athumani Jerry Mwasha | C14: 200000 | D14: 100000 | E14: 700000 | F14: =SUM(C14:E14) -> 1000000 | G14: =F14=H14 -> TRUE | H14: =DETAILS!AW38 -> 1000000 | I14: 1200000 | J14: =H14/I14 -> 0.83333333 | K14: =MAX(I14-H14,0) -> 200000 | L14: =100%-J14 -> 0.16666667 | O14: =F14=H14 -> TRUE | P14: 1
A15: =A14+1 -> 7 | B15: Elianshisaria Invocavith Munisi | C15: 200000 | D15: 100000 | E15: 920000 | F15: =SUM(C15:E15) -> 1220000 | G15: =F15=H15 -> TRUE | H15: =DETAILS!AW14 -> 1220000 | I15: 1200000 | J15: =H15/I15 -> 1.0166667 | K15: =MAX(I15-H15,0) -> 0 | L15: =100%-J15 -> -0.016666667 | N15: 10000 | O15: =F15=H15 -> TRUE | P15: 1
A16: =A15+1 -> 8 | B16: Elibariki Mkumbo | C16: 200000 | D16: 100000 | E16: 700000 | F16: =SUM(C16:E16) -> 1000000 | G16: =F16=H16 -> TRUE | H16: =DETAILS!AW23 -> 1000000 | I16: 1200000 | J16: =H16/I16 -> 0.83333333 | K16: =MAX(I16-H16,0) -> 200000 | L16: =100%-J16 -> 0.16666667 | O16: =F16=H16 -> TRUE | P16: 1
A17: =A16+1 -> 9 | B17: Emmanuel Matechi | C17: 200000 | D17: 100000 | E17: 700000 | F17: =SUM(C17:E17) -> 1000000 | G17: =F17=H17 -> TRUE | H17: =DETAILS!AW28 -> 1000000 | I17: 1200000 | J17: =H17/I17 -> 0.83333333 | K17: =MAX(I17-H17,0) -> 200000 | L17: =100%-J17 -> 0.16666667 | O17: =F17=H17 -> TRUE | P17: 1
A18: =A17+1 -> 10 | B18: Emmanuel Matee | C18: 200000 | D18: 100000 | E18: 1000000 | F18: =SUM(C18:E18) -> 1300000 | G18: =F18=H18 -> TRUE | H18: =DETAILS!AW10 -> 1300000 | I18: 1200000 | J18: =H18/I18 -> 1.0833333 | K18: =MAX(I18-H18,0) -> 0 | L18: =100%-J18 -> -0.083333333 | O18: =F18=H18 -> TRUE | P18: 1
A19: =A18+1 -> 11 | B19: Emmanuel Mmari | C19: 200000 | D19: 100000 | E19: 700000 | F19: =SUM(C19:E19) -> 1000000 | G19: =F19=H19 -> TRUE | H19: =DETAILS!AW58 -> 1000000 | I19: 1200000 | J19: =H19/I19 -> 0.83333333 | K19: =MAX(I19-H19,0) -> 200000 | L19: =100%-J19 -> 0.16666667 | O19: =F19=H19 -> TRUE | P19: 1
A20: =A19+1 -> 12 | B20: Erick Kitali | C20: 200000 | D20: 100000 | E20: 1000000 | F20: =SUM(C20:E20) -> 1300000 | G20: =F20=H20 -> TRUE | H20: =DETAILS!AW27 -> 1300000 | I20: 1200000 | J20: =H20/I20 -> 1.0833333 | K20: =MAX(I20-H20,0) -> 0 | L20: =100%-J20 -> -0.083333333 | O20: =F20=H20 -> TRUE | P20: 1
A21: =A20+1 -> 13 | B21: Ernest Felician Shirima | C21: 200000 | D21: 100000 | E21: 500000 | F21: =SUM(C21:E21) -> 800000 | G21: =F21=H21 -> TRUE | H21: =DETAILS!AW31 -> 800000 | I21: 1200000 | J21: =H21/I21 -> 0.66666667 | K21: =MAX(I21-H21,0) -> 400000 | L21: =100%-J21 -> 0.33333333 | O21: =F21=H21 -> TRUE
A22: =A21+1 -> 14 | B22: Evarist Exavery Francisco | C22: 200000 | D22: 100000 | E22: 700000 | F22: =SUM(C22:E22) -> 1000000 | G22: =F22=H22 -> TRUE | H22: =DETAILS!AW9 -> 1000000 | I22: 1200000 | J22: =H22/I22 -> 0.83333333 | K22: =MAX(I22-H22,0) -> 200000 | L22: =100%-J22 -> 0.16666667 | O22: =F22=H22 -> TRUE | P22: 1
A23: =A22+1 -> 15 | B23: Fredrick Peter Ndossi | C23: 200000 | D23: 100000 | E23: 700000 | F23: =SUM(C23:E23) -> 1000000 | G23: =F23=H23 -> TRUE | H23: =DETAILS!AW51 -> 1000000 | I23: 1200000 | J23: =H23/I23 -> 0.83333333 | K23: =MAX(I23-H23,0) -> 200000 | L23: =100%-J23 -> 0.16666667 | N23: 10000 | O23: =F23=H23 -> TRUE | P23: 1
A24: =A23+1 -> 16 | B24: Kanuti S. Simba | C24: 200000 | D24: 100000 | E24: 700000 | F24: =SUM(C24:E24) -> 1000000 | G24: =F24=H24 -> TRUE | H24: =DETAILS!AW12 -> 1000000 | I24: 1200000 | J24: =H24/I24 -> 0.83333333 | K24: =MAX(I24-H24,0) -> 200000 | L24: =100%-J24 -> 0.16666667 | O24: =F24=H24 -> TRUE | P24: 1
A25: =A24+1 -> 17 | B25: Mlindwa S. Kashindye | C25: 200000 | D25: 100000 | E25: 950000 | F25: =SUM(C25:E25) -> 1250000 | G25: =F25=H25 -> TRUE | H25: =DETAILS!AW43 -> 1250000 | I25: 1200000 | J25: =H25/I25 -> 1.0416667 | K25: =MAX(I25-H25,0) -> 0 | L25: =100%-J25 -> -0.041666667 | O25: =F25=H25 -> TRUE | P25: 1
A26: =A25+1 -> 18 | B26: Mohamed K. Mohamed | C26: 200000 | D26: 100000 | E26: 700000 | F26: =SUM(C26:E26) -> 1000000 | G26: =F26=H26 -> TRUE | H26: =DETAILS!AW8 -> 1000000 | I26: 1200000 | J26: =H26/I26 -> 0.83333333 | K26: =MAX(I26-H26,0) -> 200000 | L26: =100%-J26 -> 0.16666667 | O26: =F26=H26 -> TRUE | P26: 1
A27: =A26+1 -> 19 | B27: Mosses Makoko | C27: 200000 | D27: 100000 | E27: 700000 | F27: =SUM(C27:E27) -> 1000000 | G27: =F27=H27 -> TRUE | H27: =DETAILS!AW16 -> 1000000 | I27: 1200000 | J27: =H27/I27 -> 0.83333333 | K27: =MAX(I27-H27,0) -> 200000 | L27: =100%-J27 -> 0.16666667 | O27: =F27=H27 -> TRUE | P27: 1
A28: =A27+1 -> 20 | B28: Nsanyiwa Kiloba | C28: 200000 | D28: 100000 | E28: 710000 | F28: =SUM(C28:E28) -> 1010000 | G28: =F28=H28 -> TRUE | H28: =DETAILS!AW19 -> 1010000 | I28: 1200000 | J28: =H28/I28 -> 0.84166667 | K28: =MAX(I28-H28,0) -> 190000 | L28: =100%-J28 -> 0.15833333 | O28: =F28=H28 -> TRUE | P28: 1 | Q28: 235000
A29: =A28+1 -> 21 | B29: Abdillahi Moshi | C29: 200000 | D29: 100000 | E29: 700000 | F29: =SUM(C29:E29) -> 1000000 | G29: =F29=H29 -> TRUE | H29: =DETAILS!AW48 -> 1000000 | I29: 1200000 | J29: =H29/I29 -> 0.83333333 | K29: =MAX(I29-H29,0) -> 200000 | L29: =100%-J29 -> 0.16666667 | M29: WAMELIPA SEHEMU YA MICHANGO ILA HAWAJASAINI MAKABRASHA YA USAJILI | O29: =F29=H29 -> TRUE | P29: 1
A30: =A29+1 -> 22 | B30: Ahmad Yahya | C30: 200000 | D30: 100000 | E30: 740000 | F30: =SUM(C30:E30) -> 1040000 | G30: =F30=H30 -> TRUE | H30: =DETAILS!AW20 -> 1040000 | I30: 1200000 | J30: =H30/I30 -> 0.86666667 | K30: =MAX(I30-H30,0) -> 160000 | L30: =100%-J30 -> 0.13333333 | O30: =F30=H30 -> TRUE | P30: 1
A31: =A30+1 -> 23 | B31: Albani Kimario | C31: 200000 | D31: 100000 | E31: 700000 | F31: =SUM(C31:E31) -> 1000000 | G31: =F31=H31 -> TRUE | H31: =DETAILS!AW50 -> 1000000 | I31: 1200000 | J31: =H31/I31 -> 0.83333333 | K31: =MAX(I31-H31,0) -> 200000 | L31: =100%-J31 -> 0.16666667 | O31: =F31=H31 -> TRUE | P31: 1
A32: =A31+1 -> 24 | B32: Bakari Hemedi | C32: 200000 | D32: 100000 | E32: 800000 | F32: =SUM(C32:E32) -> 1100000 | G32: =F32=H32 -> TRUE | H32: =DETAILS!AW37 -> 1100000 | I32: 1200000 | J32: =H32/I32 -> 0.91666667 | K32: =MAX(I32-H32,0) -> 100000 | L32: =100%-J32 -> 0.083333333 | O32: =F32=H32 -> TRUE | P32: 1
A33: =A32+1 -> 25 | B33: Best Magoma | C33: 200000 | D33: 100000 | E33: 700000 | F33: =SUM(C33:E33) -> 1000000 | G33: =F33=H33 -> TRUE | H33: =DETAILS!AW40 -> 1000000 | I33: 1200000 | J33: =H33/I33 -> 0.83333333 | K33: =MAX(I33-H33,0) -> 200000 | L33: =100%-J33 -> 0.16666667 | O33: =F33=H33 -> TRUE | P33: 1
A34: =A33+1 -> 26 | B34: Charles Jangu | C34: 200000 | D34: 100000 | E34: 400000 | F34: =SUM(C34:E34) -> 700000 | G34: =F34=H34 -> TRUE | H34: =DETAILS!AW52 -> 700000 | I34: 1200000 | J34: =H34/I34 -> 0.58333333 | K34: =MAX(I34-H34,0) -> 500000 | L34: =100%-J34 -> 0.41666667 | O34: =F34=H34 -> TRUE
A35: =A34+1 -> 27 | B35: David Koillah | C35: 100000 | F35: =SUM(C35:E35) -> 100000 | G35: =F35=H35 -> TRUE | H35: =DETAILS!AW24 -> 100000 | I35: 1200000 | J35: =H35/I35 -> 0.083333333 | K35: =MAX(I35-H35,0) -> 1100000 | L35: =100%-J35 -> 0.91666667 | O35: =F35=H35 -> TRUE
A36: =A35+1 -> 28 | B36: Emmanuel Msaki | C36: 200000 | D36: 100000 | E36: 213000 | F36: =SUM(C36:E36) -> 513000 | G36: =F36=H36 -> TRUE | H36: =DETAILS!AW44 -> 513000 | I36: 1200000 | J36: =H36/I36 -> 0.4275 | K36: =MAX(I36-H36,0) -> 687000 | L36: =100%-J36 -> 0.5725 | O36: =F36=H36 -> TRUE
A37: =A36+1 -> 29 | B37: Evance Mori | C37: 200000 | D37: 100000 | E37: 700000 | F37: =SUM(C37:E37) -> 1000000 | G37: =F37=H37 -> TRUE | H37: =DETAILS!AW13 -> 1000000 | I37: 1200000 | J37: =H37/I37 -> 0.83333333 | K37: =MAX(I37-H37,0) -> 200000 | L37: =100%-J37 -> 0.16666667 | O37: =F37=H37 -> TRUE | P37: 1
A38: =A37+1 -> 30 | B38: Felix Daniel | C38: 141000 | F38: =SUM(C38:E38) -> 141000 | G38: =F38=H38 -> TRUE | H38: =DETAILS!AW6 -> 141000 | I38: 1200000 | J38: =H38/I38 -> 0.1175 | K38: =MAX(I38-H38,0) -> 1059000 | L38: =100%-J38 -> 0.8825 | O38: =F38=H38 -> TRUE
A39: =A38+1 -> 31 | B39: Gideon Gabriel | C39: 200000 | D39: 100000 | E39: 70000 | F39: =SUM(C39:E39) -> 370000 | G39: =F39=H39 -> TRUE | H39: =DETAILS!AW41 -> 370000 | I39: 1200000 | J39: =H39/I39 -> 0.30833333 | K39: =MAX(I39-H39,0) -> 830000 | L39: =100%-J39 -> 0.69166667 | O39: =F39=H39 -> TRUE
A40: =A39+1 -> 32 | B40: Hassan Matata | C40: 200000 | D40: 100000 | E40: 700000 | F40: =SUM(C40:E40) -> 1000000 | G40: =F40=H40 -> TRUE | H40: =DETAILS!AW53 -> 1000000 | I40: 1200000 | J40: =H40/I40 -> 0.83333333 | K40: =MAX(I40-H40,0) -> 200000 | L40: =100%-J40 -> 0.16666667 | O40: =F40=H40 -> TRUE | P40: 1
A41: =A40+1 -> 33 | B41: Innocent Kasigwa | C41: 200000 | D41: 100000 | E41: 700000 | F41: =SUM(C41:E41) -> 1000000 | G41: =F41=H41 -> TRUE | H41: =DETAILS!AW25 -> 1000000 | I41: 1200000 | J41: =H41/I41 -> 0.83333333 | K41: =MAX(I41-H41,0) -> 200000 | L41: =100%-J41 -> 0.16666667 | O41: =F41=H41 -> TRUE | P41: 1
A42: =A41+1 -> 34 | B42: Innocent Kweka | C42: 160000 | F42: =SUM(C42:E42) -> 160000 | G42: =F42=H42 -> TRUE | H42: =DETAILS!AW11 -> 160000 | I42: 1200000 | J42: =H42/I42 -> 0.13333333 | K42: =MAX(I42-H42,0) -> 1040000 | L42: =100%-J42 -> 0.86666667 | O42: =F42=H42 -> TRUE
A43: =A42+1 -> 35 | B43: Jacob Mangu | C43: 200000 | D43: 100000 | E43: 1300000 | F43: =SUM(C43:E43) -> 1600000 | G43: =F43=H43 -> TRUE | H43: =DETAILS!AW18 -> 1600000 | I43: 1200000 | J43: =H43/I43 -> 1.3333333 | K43: =MAX(I43-H43,0) -> 0 | L43: =100%-J43 -> -0.33333333 | O43: =F43=H43 -> TRUE | P43: 1
A44: =A43+1 -> 36 | B44: John Massawe | C44: 200000 | D44: 100000 | E44: 700000 | F44: =SUM(C44:E44) -> 1000000 | G44: =F44=H44 -> TRUE | H44: =DETAILS!AW45 -> 1000000 | I44: 1200000 | J44: =H44/I44 -> 0.83333333 | K44: =MAX(I44-H44,0) -> 200000 | L44: =100%-J44 -> 0.16666667 | O44: =F44=H44 -> TRUE | P44: 1
A45: =A44+1 -> 37 | B45: Khalifa Sushy | C45: 200000 | D45: 100000 | E45: 120000 | F45: =SUM(C45:E45) -> 420000 | G45: =F45=H45 -> TRUE | H45: =DETAILS!AW29 -> 420000 | I45: 1200000 | J45: =H45/I45 -> 0.35 | K45: =MAX(I45-H45,0) -> 780000 | L45: =100%-J45 -> 0.65 | O45: =F45=H45 -> TRUE
A46: =A45+1 -> 38 | B46: Laurian Gidoyi | C46: 200000 | D46: 100000 | E46: 700000 | F46: =SUM(C46:E46) -> 1000000 | G46: =F46=H46 -> TRUE | H46: =DETAILS!AW49 -> 1000000 | I46: 1200000 | J46: =H46/I46 -> 0.83333333 | K46: =MAX(I46-H46,0) -> 200000 | L46: =100%-J46 -> 0.16666667 | O46: =F46=H46 -> TRUE | P46: 1
A47: =A46+1 -> 39 | B47: Liggyle Vumilia | C47: 200000 | D47: 100000 | E47: 50000 | F47: =SUM(C47:E47) -> 350000 | G47: =F47=H47 -> TRUE | H47: =DETAILS!AW30 -> 350000 | I47: 1200000 | J47: =H47/I47 -> 0.29166667 | K47: =MAX(I47-H47,0) -> 850000 | L47: =100%-J47 -> 0.70833333 | O47: =F47=H47 -> TRUE
A48: =A47+1 -> 40 | B48: Masale Masale | C48: 200000 | D48: 100000 | E48: 700000 | F48: =SUM(C48:E48) -> 1000000 | G48: =F48=H48 -> TRUE | H48: =DETAILS!AW36 -> 1000000 | I48: 1200000 | J48: =H48/I48 -> 0.83333333 | K48: =MAX(I48-H48,0) -> 200000 | L48: =100%-J48 -> 0.16666667 | O48: =F48=H48 -> TRUE | P48: 1
A49: =A48+1 -> 41 | B49: Nalogwa Kiula | C49: 50000 | F49: =SUM(C49:E49) -> 50000 | G49: =F49=H49 -> TRUE | H49: =DETAILS!AW39 -> 50000 | I49: 1200000 | J49: =H49/I49 -> 0.041666667 | K49: =MAX(I49-H49,0) -> 1150000 | L49: =100%-J49 -> 0.95833333 | O49: =F49=H49 -> TRUE
A50: =A49+1 -> 42 | B50: Nixon Matowo | C50: 200000 | D50: 100000 | E50: 710000 | F50: =SUM(C50:E50) -> 1010000 | G50: =F50=H50 -> TRUE | H50: =DETAILS!AW47 -> 1010000 | I50: 1200000 | J50: =H50/I50 -> 0.84166667 | K50: =MAX(I50-H50,0) -> 190000 | L50: =100%-J50 -> 0.15833333 | N50: 10000 | O50: =F50=H50 -> TRUE | P50: 1
A51: =A50+1 -> 43 | B51: Norbert Massay | C51: 200000 | D51: 100000 | E51: 900000 | F51: =SUM(C51:E51) -> 1200000 | G51: =F51=H51 -> TRUE | H51: =DETAILS!AW7 -> 1200000 | I51: 1200000 | J51: =H51/I51 -> 1 | K51: =MAX(I51-H51,0) -> 0 | L51: =100%-J51 -> 0 | O51: =F51=H51 -> TRUE | P51: 1
A52: =A51+1 -> 44 | B52: Omary Mwasema | C52: 50000 | F52: =SUM(C52:E52) -> 50000 | G52: =F52=H52 -> TRUE | H52: =DETAILS!AW26 -> 50000 | I52: 1200000 | J52: =H52/I52 -> 0.041666667 | K52: =MAX(I52-H52,0) -> 1150000 | L52: =100%-J52 -> 0.95833333 | O52: =F52=H52 -> TRUE
A53: =A52+1 -> 45 | B53: Patiens Rweyemamu | C53: 100000 | F53: =SUM(C53:E53) -> 100000 | G53: =F53=H53 -> TRUE | H53: =DETAILS!AW22 -> 100000 | I53: 1200000 | J53: =H53/I53 -> 0.083333333 | K53: =MAX(I53-H53,0) -> 1100000 | L53: =100%-J53 -> 0.91666667 | O53: =F53=H53 -> TRUE
A54: =A53+1 -> 46 | B54: Paul Metili | C54: 100000 | F54: =SUM(C54:E54) -> 100000 | G54: =F54=H54 -> TRUE | H54: =DETAILS!AW21 -> 100000 | I54: 1200000 | J54: =H54/I54 -> 0.083333333 | K54: =MAX(I54-H54,0) -> 1100000 | L54: =100%-J54 -> 0.91666667 | O54: =F54=H54 -> TRUE
A55: =A54+1 -> 47 | B55: Robert Masegese | C55: 200000 | F55: =SUM(C55:E55) -> 200000 | G55: =F55=H55 -> TRUE | H55: =DETAILS!AW57 -> 200000 | I55: 1200000 | J55: =H55/I55 -> 0.16666667 | K55: =MAX(I55-H55,0) -> 1000000 | L55: =100%-J55 -> 0.83333333 | O55: =F55=H55 -> TRUE
A56: =A55+1 -> 48 | B56: Salum Ndolanga | C56: 100000 | F56: =SUM(C56:E56) -> 100000 | G56: =F56=H56 -> TRUE | H56: =DETAILS!AW54 -> 100000 | I56: 1200000 | J56: =H56/I56 -> 0.083333333 | K56: =MAX(I56-H56,0) -> 1100000 | L56: =100%-J56 -> 0.91666667 | O56: =F56=H56 -> TRUE | Q56: 10000
A57: =A56+1 -> 49 | B57: Shumbi Mkumbo | C57: 200000 | D57: 100000 | E57: 500000 | F57: =SUM(C57:E57) -> 800000 | G57: =F57=H57 -> TRUE | H57: =DETAILS!AW55 -> 800000 | I57: 1200000 | J57: =H57/I57 -> 0.66666667 | K57: =MAX(I57-H57,0) -> 400000 | L57: =100%-J57 -> 0.33333333 | O57: =F57=H57 -> TRUE
A58: =A57+1 -> 50 | B58: Stanslaus Nyembea | C58: 120000 | F58: =SUM(C58:E58) -> 120000 | G58: =F58=H58 -> TRUE | H58: =DETAILS!AW33 -> 120000 | I58: 1200000 | J58: =H58/I58 -> 0.1 | K58: =MAX(I58-H58,0) -> 1080000 | L58: =100%-J58 -> 0.9 | O58: =F58=H58 -> TRUE
A59: =A58+1 -> 51 | B59: Stephen Nkurlu | C59: 200000 | D59: 100000 | E59: 720000 | F59: =SUM(C59:E59) -> 1020000 | G59: =F59=H59 -> TRUE | H59: =DETAILS!AW15 -> 1020000 | I59: 1200000 | J59: =H59/I59 -> 0.85 | K59: =MAX(I59-H59,0) -> 180000 | L59: =100%-J59 -> 0.15 | O59: =F59=H59 -> TRUE | P59: 1
A60: =A59+1 -> 52 | B60: Walter Salema | C60: 200000 | D60: 100000 | E60: 500000 | F60: =SUM(C60:E60) -> 800000 | G60: =F60=H60 -> TRUE | H60: =DETAILS!AW32 -> 800000 | I60: 1200000 | J60: =H60/I60 -> 0.66666667 | K60: =MAX(I60-H60,0) -> 400000 | L60: =100%-J60 -> 0.33333333 | O60: =F60=H60 -> TRUE
A61: =A60+1 -> 53 | B61: Werema Msongo | C61: 200000 | D61: 100000 | E61: 500000 | F61: =SUM(C61:E61) -> 800000 | G61: =F61=H61 -> TRUE | H61: =DETAILS!AW46 -> 800000 | I61: 1200000 | J61: =H61/I61 -> 0.66666667 | K61: =MAX(I61-H61,0) -> 400000 | L61: =100%-J61 -> 0.33333333 | O61: =F61=H61 -> TRUE
A62: =A61+1 -> 54 | B62: Emanuel Moshi | C62: 200000 | D62: 100000 | E62: 900000 | F62: =SUM(C62:E62) -> 1200000 | G62: =F62=H62 -> TRUE | H62: =DETAILS!AW59 -> 1200000 | I62: 1200000 | J62: =H62/I62 -> 1 | K62: =MAX(I62-H62,0) -> 0 | L62: =100%-J62 -> 0 | O62: =F62=H62 -> TRUE | P62: 1
A63: =A62+1 -> 55 | B63: Innocent Mosha | C63: 200000 | D63: 100000 | E63: 700000 | F63: =SUM(C63:E63) -> 1000000 | G63: =F63=H63 -> TRUE | H63: =DETAILS!AW60 -> 1000000 | I63: 1200000 | J63: =H63/I63 -> 0.83333333 | K63: =MAX(I63-H63,0) -> 200000 | L63: =100%-J63 -> 0.16666667 | P63: 1
A64: =A63+1 -> 56 | B64: Shabani Salim | C64: 200000 | D64: 100000 | E64: 700000 | F64: =SUM(C64:E64) -> 1000000 | G64: =F64=H64 -> TRUE | H64: =DETAILS!E61 -> 1000000 | I64: 1200000 | J64: =H64/I64 -> 0.83333333 | K64: =MAX(I64-H64,0) -> 200000 | L64: =100%-J64 -> 0.16666667 | P64: 1
A65: =A64+1 -> 57 | B65: Adolph Ndyeabura | C65: 200000 | D65: 100000 | E65: 700000 | F65: =SUM(C65:E65) -> 1000000 | G65: =F65=H65 -> TRUE | H65: =DETAILS!E62 -> 1000000 | I65: 1200000 | J65: =H65/I65 -> 0.83333333 | K65: =MAX(I65-H65,0) -> 200000 | L65: =100%-J65 -> 0.16666667 | P65: 1
A66: =A65+1 -> 58 | B66: Saidi Ramadhani Mdee | C66: 200000 | D66: 100000 | E66: 700000 | F66: =SUM(C66:E66) -> 1000000 | G66: =F66=H66 -> TRUE | H66: =DETAILS!E63 -> 1000000 | I66: 1200000 | J66: =H66/I66 -> 0.83333333 | K66: =MAX(I66-H66,0) -> 200000 | L66: =100%-J66 -> 0.16666667 | P66: 1
A67: =A66+1 -> 59 | B67: Patrick K. Kiani | C67: 200000 | D67: 100000 | E67: 900000 | F67: =SUM(C67:E67) -> 1200000 | G67: =F67=H67 -> TRUE | H67: =DETAILS!AW64 -> 1200000 | I67: 1200000 | J67: =H67/I67 -> 1 | K67: =MAX(I67-H67,0) -> 0 | L67: =100%-J67 -> 0 | P67: 1
G68: =F68=H68 -> TRUE
G69: =F69=H69 -> TRUE
G70: =F70=H70 -> TRUE
G71: =F71=H71 -> TRUE
A72: =A66+1 -> 59 | B72: Moses Lazaro Molel | F72: =SUM(C72:E72) -> 0 | G72: =F72=H72 -> TRUE | I72: 1000000 | J72: =H72/I72 -> 0 | K72: =MAX(I72-H72,0) -> 1000000 | L72: =100%-J72 -> 1 | O72: =F72=H72 -> TRUE
A73: =A72+1 -> 60 | B73: Edgar Rwezaura | C73: 0 | D73: 0 | F73: =SUM(C73:E73) -> 0 | G73: =F73=H73 -> TRUE | I73: 1000000 | J73: =H73/I73 -> 0 | K73: =MAX(I73-F73,0) -> 1000000 | L73: =100%-J73 -> 1 | M73: WAMEJISAJILI M-KOPA TU. HAWAJALIPA MCHANGO WOWOTE | O73: =F73=H73 -> TRUE
A74: =A73+1 -> 61 | B74: Manase Mushi | C74: 0 | D74: 0 | F74: =SUM(C74:E74) -> 0 | G74: =F74=H74 -> TRUE | I74: 1000000 | J74: =H74/I74 -> 0 | K74: =MAX(I74-F74,0) -> 1000000 | L74: =100%-J74 -> 1 | O74: =F74=H74 -> TRUE
A75: =A74+1 -> 62 | B75: Paul Mikongoti | C75: 0 | D75: 0 | F75: =SUM(C75:E75) -> 0 | G75: =F75=H75 -> TRUE | I75: 1000000 | J75: =H75/I75 -> 0 | K75: =MAX(I75-F75,0) -> 1000000 | L75: =100%-J75 -> 1 | O75: =F75=H75 -> TRUE
A76: =A75+1 -> 63 | B76: Moses Luguru | C76: 0 | D76: 0 | F76: =SUM(C76:E76) -> 0 | G76: =F76=H76 -> TRUE | I76: 1000000 | J76: =H76/I76 -> 0 | K76: =MAX(I76-F76,0) -> 1000000 | L76: =100%-J76 -> 1 | O76: =F76=H76 -> TRUE
A77: =A76+1 -> 64 | B77: Emili Mkwawi | C77: 0 | D77: 0 | F77: =SUM(C77:E77) -> 0 | G77: =F77=H77 -> TRUE | I77: 1000000 | J77: =H77/I77 -> 0 | K77: =MAX(I77-F77,0) -> 1000000 | L77: =100%-J77 -> 1 | O77: =F77=H77 -> TRUE
A78: =A77+1 -> 65 | B78: Salum Hassani | C78: 0 | D78: 0 | F78: =SUM(C78:E78) -> 0 | G78: =F78=H78 -> TRUE | I78: 1000000 | J78: =H78/I78 -> 0 | K78: =MAX(I78-F78,0) -> 1000000 | L78: =100%-J78 -> 1 | O78: =F78=H78 -> TRUE
A79: =A78+1 -> 66 | B79: Richard Makala | C79: 0 | D79: 0 | F79: =SUM(C79:E79) -> 0 | G79: =F79=H79 -> TRUE | I79: 1000000 | J79: =H79/I79 -> 0 | K79: =MAX(I79-F79,0) -> 1000000 | L79: =100%-J79 -> 1 | O79: =F79=H79 -> TRUE
A80: =A79+1 -> 67 | B80: Shabani Salim | C80: 0 | D80: 0 | F80: =SUM(C80:E80) -> 0 | G80: =F80=H80 -> TRUE | I80: 1000000 | J80: =H80/I80 -> 0 | K80: =MAX(I80-F80,0) -> 1000000 | L80: =100%-J80 -> 1 | O80: =F80=H80 -> TRUE
A81: =A80+1 -> 68 | B81: Fabian Sedoyeka | C81: 0 | D81: 0 | F81: =SUM(C81:E81) -> 0 | G81: =F81=H81 -> TRUE | I81: 1000000 | J81: =H81/I81 -> 0 | K81: =MAX(I81-F81,0) -> 1000000 | L81: =100%-J81 -> 1 | O81: =F81=H81 -> TRUE
A82: =A81+1 -> 69 | B82: Piniel Seth | C82: 0 | D82: 0 | F82: =SUM(C82:E82) -> 0 | G82: =F82=H82 -> TRUE | I82: 1000000 | J82: =H82/I82 -> 0 | K82: =MAX(I82-F82,0) -> 1000000 | L82: =100%-J82 -> 1 | O82: =F82=H82 -> TRUE
A83: =A82+1 -> 70 | B83: Beatus Chikoti | C83: 0 | D83: 0 | E83: 0 | F83: =SUM(C83:E83) -> 0 | G83: =F83=H83 -> TRUE | I83: 1000000 | J83: =H83/I83 -> 0 | K83: =MAX(I83-F83,0) -> 1000000 | L83: =100%-J83 -> 1 | O83: =F83=H83 -> TRUE
A84: =A83+1 -> 71 | B84: Nyangusi Laizer | C84: 0 | D84: 0 | F84: =SUM(C84:E84) -> 0 | G84: =F84=H84 -> TRUE | I84: 1000000 | J84: =H84/I84 -> 0 | K84: =MAX(I84-F84,0) -> 1000000 | L84: =100%-J84 -> 1 | O84: =F84=H84 -> TRUE
A85: =A84+1 -> 72 | B85: Anase Minja | C85: 0 | D85: 0 | F85: =SUM(C85:E85) -> 0 | G85: =F85=H85 -> TRUE | I85: 1000000 | J85: =H85/I85 -> 0 | K85: =MAX(I85-F85,0) -> 1000000 | L85: =100%-J85 -> 1 | O85: =F85=H85 -> TRUE
A86: =A85+1 -> 73 | B86: Robert Kitundu | C86: 0 | D86: 0 | F86: =SUM(C86:E86) -> 0 | G86: =F86=H86 -> TRUE | I86: 1000000 | J86: =H86/I86 -> 0 | K86: =MAX(I86-F86,0) -> 1000000 | L86: =100%-J86 -> 1 | O86: =F86=H86 -> TRUE
A87: =A86+1 -> 74 | B87: Msafiri Mwapinga | C87: 0 | D87: 0 | F87: =SUM(C87:E87) -> 0 | G87: =F87=H87 -> TRUE | I87: 1000000 | J87: =H87/I87 -> 0 | K87: =MAX(I87-F87,0) -> 1000000 | L87: =100%-J87 -> 1 | O87: =F87=H87 -> TRUE
G88: =F88=H88 -> TRUE | J88: =H88/I88 -> #DIV/0! | O88: =F88=H88 -> TRUE
B89: TOTAL | C89: =SUM(C9:C88) -> 10821000 | D89: =SUM(D9:D88) -> 4800000 | E89: =SUM(E9:E88) -> 32233000 | F89: =SUM(F9:F88) -> 47854000 | G89: =F89=H89 -> TRUE | H89: =SUM(H9:H88) -> 47854000 | I89: =SUM(I9:I88) -> 86800000 | K89: =SUM(K9:K88) -> 39616000 | N89: =SUM(N9:N87) -> 30000 | O89: =F89=H89 -> TRUE
B90: MKOBA MAIN BALANCE | H90: 46524000 | P90: =SUM(P11:P89) -> 38 | Q90: =P90/P91 -> 0.55072464
B91: MKOBA B BALANCE | H91: 830000 | P91: 69
B92: Bank - NMB | H92: =DETAILS!Z7+DETAILS!Q27+DETAILS!AC7 -> 500000
B93: TOTAL BALANCE | H93: =SUM(H90:H92) -> 47854000
H94: =H93-H89 -> 0
B97: Mwenyekiti alitoa ufafanuzi wa gharama zilizochangiwa na wanachama waanzilishi kama ifuatavyo: | D97: Allocated accordingly to contributions
B98: a) Gharama za Ukumbi: TZS 75,000. Gharama hizi zilichangiwa na:
B99: (i) Mwenyekiti Ndugu Donald Nsanyiwa – TZS 75,000 | C99: 75000
B100: b) Gharama ya Usafiri kwa Afisa Ushirika: TZS 50,000. Gharama hizi zilichangiwa na:
B101: (i) Ndugu Donald Nsanyiwa – TZS 10,000 | C101: 10000
B102: (ii) Salum Ndolanga – TZS 10,000 | C102: 10000
B103: (iii) Eliashasaria Munisi – TZS 10,000 | C103: 10000
B104: (iv) Nixon Matowo – TZS 10,000 | C104: 10000
B105: (v) Fredrick Ndossi – TZS 10,000 | C105: 10000
...

Sheet Summary (sorted)
A1: ILBORU ALUMNI SACCOS LIMITED
A3: MICHANGO YA WANACHAMA
A6: S/N | B6: Member Name | C6: MICHANGO | I6: KIWANGO KINACHOHITAJIKA | K6: KIWANGO CHA KUKAMILISHA | M6: STATUS | N6: GAHRAMA ZA MIKUTANO [allocated already]
C7: KIINGILIO | D7: AKIBA | E7: HISA | F7: JUMLA | H7: ACTUAL | Q7: OCTOBER, 2024
D8: ALLOCATED FROM M-KOBA | E8: ALLOCATED FROM M-KOBA | H8: MKOBA | L8: BADO
A9: 1 | B9: Aaron J. Mtui | C9: 100000 | F9: =SUM(C9:E9) -> 100000 | G9: =F9=H9 -> FALSE | H9: ='DETAILS (sorted)'!BI2 -> 2200000 | I9: 1700000 | J9: =H9/I9 -> 1.2941176 | K9: =MAX(I9-H9,0) -> 0 | L9: =100%-J9 -> -0.29411765 | M9: WAMESHASAINI MAKABRASHA YA USAJILI. LAKINI WENGI HAWAJAMALIZIA MICHANGO YAO | O9: =F9=H9 -> FALSE | R9: NOV, 2024 | S9: DEC, 2024 | T9: JAN, 2025 | U9: FEB, 2025
A10: =A9+1 -> 2 | B10: Abdillahi Moshi | C10: 200000 | D10: 100000 | E10: 700000 | F10: =SUM(C10:E10) -> 1000000 | G10: =F10=H10 -> FALSE | H10: ='DETAILS (sorted)'!BI3 -> 3500000 | I10: 1700000 | J10: =H10/I10 -> 2.0588235 | K10: =MAX(I10-H10,0) -> 0 | L10: =100%-J10 -> -1.0588235 | M10: WAMELIPA SEHEMU YA MICHANGO ILA HAWAJASAINI MAKABRASHA YA USAJILI | O10: =F10=H10 -> FALSE | P10: 1
A11: =A10+1 -> 3 | B11: Abduel G. Kitururu | C11: 200000 | D11: 100000 | E11: 330000 | F11: =SUM(C11:E11) -> 630000 | G11: =F11=H11 -> FALSE | H11: ='DETAILS (sorted)'!BI4 -> 1900000 | I11: 1700000 | J11: =H11/I11 -> 1.1176471 | K11: =MAX(I11-H11,0) -> 0 | L11: =100%-J11 -> -0.11764706 | O11: =F11=H11 -> FALSE
A12: =A11+1 -> 4 | B12: Abraham A. Assenga | C12: 200000 | D12: 100000 | E12: 700000 | F12: =SUM(C12:E12) -> 1000000 | G12: =F12=H12 -> TRUE | H12: ='DETAILS (sorted)'!BI5 -> 1000000 | I12: 1700000 | J12: =H12/I12 -> 0.58823529 | K12: =MAX(I12-H12,0) -> 700000 | L12: =100%-J12 -> 0.41176471 | O12: =F12=H12 -> TRUE | P12: 1
A13: =A12+1 -> 5 | B13: Adam I. Urassa | C13: 200000 | D13: 100000 | E13: 700000 | F13: =SUM(C13:E13) -> 1000000 | G13: =F13=H13 -> FALSE | H13: ='DETAILS (sorted)'!BI6 -> 2000000 | I13: 1700000 | J13: =H13/I13 -> 1.1764706 | K13: =MAX(I13-H13,0) -> 0 | L13: =100%-J13 -> -0.17647059 | O13: =F13=H13 -> FALSE | P13: 1
A14: =A13+1 -> 6 | B14: Adolph Ndyeabura | C14: 200000 | D14: 100000 | E14: 700000 | F14: =SUM(C14:E14) -> 1000000 | G14: =F14=H14 -> FALSE | H14: ='DETAILS (sorted)'!BI7 -> 2000000 | I14: 1700000 | J14: =H14/I14 -> 1.1764706 | K14: =MAX(I14-H14,0) -> 0 | L14: =100%-J14 -> -0.17647059 | P14: 1
A15: =A14+1 -> 7 | B15: Ahmad Yahya | C15: 200000 | D15: 100000 | E15: 740000 | F15: =SUM(C15:E15) -> 1040000 | G15: =F15=H15 -> FALSE | H15: ='DETAILS (sorted)'!BI8 -> 2300000 | I15: 1700000 | J15: =H15/I15 -> 1.3529412 | K15: =MAX(I15-H15,0) -> 0 | L15: =100%-J15 -> -0.35294118 | O15: =F15=H15 -> FALSE | P15: 1
A16: =A15+1 -> 8 | B16: Albani Kimario | C16: 200000 | D16: 100000 | E16: 700000 | F16: =SUM(C16:E16) -> 1000000 | G16: =F16=H16 -> FALSE | H16: ='DETAILS (sorted)'!BI9 -> 141000 | I16: 1700000 | J16: =H16/I16 -> 0.082941176 | K16: =MAX(I16-H16,0) -> 1559000 | L16: =100%-J16 -> 0.91705882 | O16: =F16=H16 -> FALSE | P16: 1
A17: =A16+1 -> 9 | B17: Amos M. Nungu | C17: 200000 | D17: 100000 | E17: 700000 | F17: =SUM(C17:E17) -> 1000000 | G17: =F17=H17 -> FALSE | H17: ='DETAILS (sorted)'!BI10 -> 1170000 | I17: 1700000 | J17: =H17/I17 -> 0.68823529 | K17: =MAX(I17-H17,0) -> 530000 | L17: =100%-J17 -> 0.31176471 | O17: =F17=H17 -> FALSE | P17: 1
A18: =A17+1 -> 10 | B18: Athumani Jerry Mwasha | C18: 200000 | D18: 100000 | E18: 700000 | F18: =SUM(C18:E18) -> 1000000 | G18: =F18=H18 -> FALSE | H18: ='DETAILS (sorted)'!BI11 -> 2000000 | I18: 1700000 | J18: =H18/I18 -> 1.1764706 | K18: =MAX(I18-H18,0) -> 0 | L18: =100%-J18 -> -0.17647059 | O18: =F18=H18 -> FALSE | P18: 1
A19: =A18+1 -> 11 | B19: Bakari Hemedi | C19: 200000 | D19: 100000 | E19: 800000 | F19: =SUM(C19:E19) -> 1100000 | G19: =F19=H19 -> FALSE | H19: ='DETAILS (sorted)'!BI12 -> 2400000 | I19: 1700000 | J19: =H19/I19 -> 1.4117647 | K19: =MAX(I19-H19,0) -> 0 | L19: =100%-J19 -> -0.41176471 | O19: =F19=H19 -> FALSE | P19: 1
A20: =A19+1 -> 12 | B20: Best Magoma | C20: 200000 | D20: 100000 | E20: 700000 | F20: =SUM(C20:E20) -> 1000000 | G20: =F20=H20 -> FALSE | H20: ='DETAILS (sorted)'!BI13 -> 1900000 | I20: 1700000 | J20: =H20/I20 -> 1.1176471 | K20: =MAX(I20-H20,0) -> 0 | L20: =100%-J20 -> -0.11764706 | O20: =F20=H20 -> FALSE | P20: 1
A21: =A20+1 -> 13 | B21: Charles Jangu | C21: 200000 | D21: 100000 | E21: 400000 | F21: =SUM(C21:E21) -> 700000 | G21: =F21=H21 -> FALSE | H21: ='DETAILS (sorted)'!BI14 -> 1500000 | I21: 1700000 | J21: =H21/I21 -> 0.88235294 | K21: =MAX(I21-H21,0) -> 200000 | L21: =100%-J21 -> 0.11764706 | O21: =F21=H21 -> FALSE
A22: =A21+1 -> 14 | B22: David Koillah | C22: 100000 | F22: =SUM(C22:E22) -> 100000 | G22: =F22=H22 -> FALSE | H22: ='DETAILS (sorted)'!BI15 -> 2000000 | I22: 1700000 | J22: =H22/I22 -> 1.1764706 | K22: =MAX(I22-H22,0) -> 0 | L22: =100%-J22 -> -0.17647059 | O22: =F22=H22 -> FALSE
A23: =A22+1 -> 15 | B23: Elianshisaria Invocavith Munisi | C23: 200000 | D23: 100000 | E23: 920000 | F23: =SUM(C23:E23) -> 1220000 | G23: =F23=H23 -> FALSE | H23: ='DETAILS (sorted)'!BI16 -> 1600000 | I23: 1700000 | J23: =H23/I23 -> 0.94117647 | K23: =MAX(I23-H23,0) -> 100000 | L23: =100%-J23 -> 0.058823529 | N23: 10000 | O23: =F23=H23 -> FALSE | P23: 1
A24: =A23+1 -> 16 | B24: Elibariki Mkumbo | C24: 200000 | D24: 100000 | E24: 700000 | F24: =SUM(C24:E24) -> 1000000 | G24: =F24=H24 -> TRUE | H24: ='DETAILS (sorted)'!BI17 -> 1000000 | I24: 1700000 | J24: =H24/I24 -> 0.58823529 | K24: =MAX(I24-H24,0) -> 700000 | L24: =100%-J24 -> 0.41176471 | O24: =F24=H24 -> TRUE | P24: 1
A25: =A24+1 -> 17 | B25: Emanuel Moshi | C25: 200000 | D25: 100000 | E25: 900000 | F25: =SUM(C25:E25) -> 1200000 | G25: =F25=H25 -> FALSE | H25: ='DETAILS (sorted)'!BI18 -> 1800000 | I25: 1700000 | J25: =H25/I25 -> 1.0588235 | K25: =MAX(I25-H25,0) -> 0 | L25: =100%-J25 -> -0.058823529 | O25: =F25=H25 -> FALSE | P25: 1
A26: =A25+1 -> 18 | B26: Emmanuel Matechi | C26: 200000 | D26: 100000 | E26: 700000 | F26: =SUM(C26:E26) -> 1000000 | G26: =F26=H26 -> TRUE | H26: ='DETAILS (sorted)'!BI19 -> 1000000 | I26: 1700000 | J26: =H26/I26 -> 0.58823529 | K26: =MAX(I26-H26,0) -> 700000 | L26: =100%-J26 -> 0.41176471 | O26: =F26=H26 -> TRUE | P26: 1
A27: =A26+1 -> 19 | B27: Emmanuel Matee | C27: 200000 | D27: 100000 | E27: 1000000 | F27: =SUM(C27:E27) -> 1300000 | G27: =F27=H27 -> FALSE | H27: ='DETAILS (sorted)'!BI20 -> 1500000 | I27: 1700000 | J27: =H27/I27 -> 0.88235294 | K27: =MAX(I27-H27,0) -> 200000 | L27: =100%-J27 -> 0.11764706 | O27: =F27=H27 -> FALSE | P27: 1
A28: =A27+1 -> 20 | B28: Emmanuel Mmari | C28: 200000 | D28: 100000 | E28: 700000 | F28: =SUM(C28:E28) -> 1000000 | G28: =F28=H28 -> FALSE | H28: ='DETAILS (sorted)'!BI21 -> 1900000 | I28: 1700000 | J28: =H28/I28 -> 1.1176471 | K28: =MAX(I28-H28,0) -> 0 | L28: =100%-J28 -> -0.11764706 | O28: =F28=H28 -> FALSE | P28: 1
A29: =A28+1 -> 21 | B29: Emmanuel Msaki | C29: 200000 | D29: 100000 | E29: 213000 | F29: =SUM(C29:E29) -> 513000 | G29: =F29=H29 -> FALSE | H29: ='DETAILS (sorted)'!BI22 -> 1900000 | I29: 1700000 | J29: =H29/I29 -> 1.1176471 | K29: =MAX(I29-H29,0) -> 0 | L29: =100%-J29 -> -0.11764706 | O29: =F29=H29 -> FALSE
A30: =A29+1 -> 22 | B30: Erick Kitali | C30: 200000 | D30: 100000 | E30: 1000000 | F30: =SUM(C30:E30) -> 1300000 | G30: =F30=H30 -> FALSE | H30: ='DETAILS (sorted)'!BI23 -> 1500000 | I30: 1700000 | J30: =H30/I30 -> 0.88235294 | K30: =MAX(I30-H30,0) -> 200000 | L30: =100%-J30 -> 0.11764706 | O30: =F30=H30 -> FALSE | P30: 1
A31: =A30+1 -> 23 | B31: Ernest Felician Shirima | C31: 200000 | D31: 100000 | E31: 500000 | F31: =SUM(C31:E31) -> 800000 | G31: =F31=H31 -> FALSE | H31: ='DETAILS (sorted)'!BI24 -> 2100000 | I31: 1700000 | J31: =H31/I31 -> 1.2352941 | K31: =MAX(I31-H31,0) -> 0 | L31: =100%-J31 -> -0.23529412 | O31: =F31=H31 -> FALSE
A32: =A31+1 -> 24 | B32: Evance Mori | C32: 200000 | D32: 100000 | E32: 700000 | F32: =SUM(C32:E32) -> 1000000 | G32: =F32=H32 -> FALSE | H32: ='DETAILS (sorted)'!BI25 -> 2000000 | I32: 1700000 | J32: =H32/I32 -> 1.1764706 | K32: =MAX(I32-H32,0) -> 0 | L32: =100%-J32 -> -0.17647059 | O32: =F32=H32 -> FALSE | P32: 1
A33: =A32+1 -> 25 | B33: Evarist Exavery Francisco | C33: 200000 | D33: 100000 | E33: 700000 | F33: =SUM(C33:E33) -> 1000000 | G33: =F33=H33 -> TRUE | H33: ='DETAILS (sorted)'!BI26 -> 1000000 | I33: 1700000 | J33: =H33/I33 -> 0.58823529 | K33: =MAX(I33-H33,0) -> 700000 | L33: =100%-J33 -> 0.41176471 | O33: =F33=H33 -> TRUE | P33: 1
A34: =A33+1 -> 26 | B34: Felix Daniel | C34: 141000 | F34: =SUM(C34:E34) -> 141000 | G34: =F34=H34 -> FALSE | H34: ='DETAILS (sorted)'!BI27 -> 1900000 | I34: 1700000 | J34: =H34/I34 -> 1.1176471 | K34: =MAX(I34-H34,0) -> 0 | L34: =100%-J34 -> -0.11764706 | O34: =F34=H34 -> FALSE
A35: =A34+1 -> 27 | B35: Fredrick Peter Ndossi | C35: 200000 | D35: 100000 | E35: 700000 | F35: =SUM(C35:E35) -> 1000000 | G35: =F35=H35 -> TRUE | H35: ='DETAILS (sorted)'!BI28 -> 1000000 | I35: 1700000 | J35: =H35/I35 -> 0.58823529 | K35: =MAX(I35-H35,0) -> 700000 | L35: =100%-J35 -> 0.41176471 | N35: 10000 | O35: =F35=H35 -> TRUE | P35: 1
A36: =A35+1 -> 28 | B36: Gideon Gabriel | C36: 200000 | D36: 100000 | E36: 70000 | F36: =SUM(C36:E36) -> 370000 | G36: =F36=H36 -> FALSE | H36: ='DETAILS (sorted)'!BI29 -> 1700000 | I36: 1700000 | J36: =H36/I36 -> 1 | K36: =MAX(I36-H36,0) -> 0 | L36: =100%-J36 -> 0 | O36: =F36=H36 -> FALSE
A37: =A36+1 -> 29 | B37: Hassan Matata | C37: 200000 | D37: 100000 | E37: 700000 | F37: =SUM(C37:E37) -> 1000000 | G37: =F37=H37 -> FALSE | H37: ='DETAILS (sorted)'!BI30 -> 1400000 | I37: 1700000 | J37: =H37/I37 -> 0.82352941 | K37: =MAX(I37-H37,0) -> 300000 | L37: =100%-J37 -> 0.17647059 | O37: =F37=H37 -> FALSE | P37: 1
A38: =A37+1 -> 30 | B38: Innocent Kasigwa | C38: 200000 | D38: 100000 | E38: 700000 | F38: =SUM(C38:E38) -> 1000000 | G38: =F38=H38 -> FALSE | H38: ='DETAILS (sorted)'!BI31 -> 1500000 | I38: 1700000 | J38: =H38/I38 -> 0.88235294 | K38: =MAX(I38-H38,0) -> 200000 | L38: =100%-J38 -> 0.11764706 | O38: =F38=H38 -> FALSE | P38: 1
A39: =A38+1 -> 31 | B39: Innocent Kweka | C39: 160000 | F39: =SUM(C39:E39) -> 160000 | G39: =F39=H39 -> FALSE | H39: ='DETAILS (sorted)'!BI32 -> 1020000 | I39: 1700000 | J39: =H39/I39 -> 0.6 | K39: =MAX(I39-H39,0) -> 680000 | L39: =100%-J39 -> 0.4 | O39: =F39=H39 -> FALSE
A40: =A39+1 -> 32 | B40: Innocent Mosha | C40: 200000 | D40: 100000 | E40: 700000 | F40: =SUM(C40:E40) -> 1000000 | G40: =F40=H40 -> FALSE | H40: ='DETAILS (sorted)'!BI33 -> 1200000 | I40: 1700000 | J40: =H40/I40 -> 0.70588235 | K40: =MAX(I40-H40,0) -> 500000 | L40: =100%-J40 -> 0.29411765 | P40: 1
A41: =A40+1 -> 33 | B41: Jacob Mangu | C41: 200000 | D41: 100000 | E41: 1300000 | F41: =SUM(C41:E41) -> 1600000 | G41: =F41=H41 -> FALSE | H41: ='DETAILS (sorted)'!BI34 -> 1000000 | I41: 1700000 | J41: =H41/I41 -> 0.58823529 | K41: =MAX(I41-H41,0) -> 700000 | L41: =100%-J41 -> 0.41176471 | O41: =F41=H41 -> FALSE | P41: 1
A42: =A41+1 -> 34 | B42: John Massawe | C42: 200000 | D42: 100000 | E42: 700000 | F42: =SUM(C42:E42) -> 1000000 | G42: =F42=H42 -> TRUE | H42: ='DETAILS (sorted)'!BI35 -> 1000000 | I42: 1700000 | J42: =H42/I42 -> 0.58823529 | K42: =MAX(I42-H42,0) -> 700000 | L42: =100%-J42 -> 0.41176471 | O42: =F42=H42 -> TRUE | P42: 1
A43: =A42+1 -> 35 | B43: Kanuti S. Simba | C43: 200000 | D43: 100000 | E43: 700000 | F43: =SUM(C43:E43) -> 1000000 | G43: =F43=H43 -> TRUE | H43: ='DETAILS (sorted)'!BI36 -> 1000000 | I43: 1700000 | J43: =H43/I43 -> 0.58823529 | K43: =MAX(I43-H43,0) -> 700000 | L43: =100%-J43 -> 0.41176471 | O43: =F43=H43 -> TRUE | P43: 1
A44: =A43+1 -> 36 | B44: Khalifa Sushy | C44: 200000 | D44: 100000 | E44: 120000 | F44: =SUM(C44:E44) -> 420000 | G44: =F44=H44 -> FALSE | H44: ='DETAILS (sorted)'!BI37 -> 1100000 | I44: 1700000 | J44: =H44/I44 -> 0.64705882 | K44: =MAX(I44-H44,0) -> 600000 | L44: =100%-J44 -> 0.35294118 | O44: =F44=H44 -> FALSE
A45: =A44+1 -> 37 | B45: Laurian Gidoyi | C45: 200000 | D45: 100000 | E45: 700000 | F45: =SUM(C45:E45) -> 1000000 | G45: =F45=H45 -> TRUE | H45: ='DETAILS (sorted)'!BI38 -> 1000000 | I45: 1700000 | J45: =H45/I45 -> 0.58823529 | K45: =MAX(I45-H45,0) -> 700000 | L45: =100%-J45 -> 0.41176471 | O45: =F45=H45 -> TRUE | P45: 1
A46: =A45+1 -> 38 | B46: Liggyle Vumilia | C46: 200000 | D46: 100000 | E46: 50000 | F46: =SUM(C46:E46) -> 350000 | G46: =F46=H46 -> FALSE | H46: ='DETAILS (sorted)'!BI39 -> 1000000 | I46: 1700000 | J46: =H46/I46 -> 0.58823529 | K46: =MAX(I46-H46,0) -> 700000 | L46: =100%-J46 -> 0.41176471 | O46: =F46=H46 -> FALSE
A47: =A46+1 -> 39 | B47: Masale Masale | C47: 200000 | D47: 100000 | E47: 700000 | F47: =SUM(C47:E47) -> 1000000 | G47: =F47=H47 -> TRUE | H47: ='DETAILS (sorted)'!BI40 -> 1000000 | I47: 1700000 | J47: =H47/I47 -> 0.58823529 | K47: =MAX(I47-H47,0) -> 700000 | L47: =100%-J47 -> 0.41176471 | O47: =F47=H47 -> TRUE | P47: 1
A48: =A47+1 -> 40 | B48: Mlindwa S. Kashindye | C48: 200000 | D48: 100000 | E48: 950000 | F48: =SUM(C48:E48) -> 1250000 | G48: =F48=H48 -> FALSE | H48: ='DETAILS (sorted)'!BI41 -> 1040000 | I48: 1700000 | J48: =H48/I48 -> 0.61176471 | K48: =MAX(I48-H48,0) -> 660000 | L48: =100%-J48 -> 0.38823529 | O48: =F48=H48 -> FALSE | P48: 1
A49: =A48+1 -> 41 | B49: Mohamed K. Mohamed | C49: 200000 | D49: 100000 | E49: 700000 | F49: =SUM(C49:E49) -> 1000000 | G49: =F49=H49 -> FALSE | H49: ='DETAILS (sorted)'!BI42 -> 1920000 | I49: 1700000 | J49: =H49/I49 -> 1.1294118 | K49: =MAX(I49-H49,0) -> 0 | L49: =100%-J49 -> -0.12941176 | O49: =F49=H49 -> FALSE | P49: 1
A50: =A49+1 -> 42 | B50: Mosses Makoko | C50: 200000 | D50: 100000 | E50: 700000 | F50: =SUM(C50:E50) -> 1000000 | G50: =F50=H50 -> TRUE | H50: ='DETAILS (sorted)'!BI43 -> 1000000 | I50: 1700000 | J50: =H50/I50 -> 0.58823529 | K50: =MAX(I50-H50,0) -> 700000 | L50: =100%-J50 -> 0.41176471 | O50: =F50=H50 -> TRUE | P50: 1
A51: =A50+1 -> 43 | B51: Nalogwa Kiula | C51: 50000 | F51: =SUM(C51:E51) -> 50000 | G51: =F51=H51 -> FALSE | H51: ='DETAILS (sorted)'!BI44 -> 1000000 | I51: 1700000 | J51: =H51/I51 -> 0.58823529 | K51: =MAX(I51-H51,0) -> 700000 | L51: =100%-J51 -> 0.41176471 | O51: =F51=H51 -> FALSE
A52: =A51+1 -> 44 | B52: Nixon Matowo | C52: 200000 | D52: 100000 | E52: 710000 | F52: =SUM(C52:E52) -> 1010000 | G52: =F52=H52 -> FALSE | H52: ='DETAILS (sorted)'!BI45 -> 630000 | I52: 1700000 | J52: =H52/I52 -> 0.37058824 | K52: =MAX(I52-H52,0) -> 1070000 | L52: =100%-J52 -> 0.62941176 | N52: 10000 | O52: =F52=H52 -> FALSE | P52: 1
A53: =A52+1 -> 45 | B53: Norbert Massay | C53: 200000 | D53: 100000 | E53: 900000 | F53: =SUM(C53:E53) -> 1200000 | G53: =F53=H53 -> FALSE | H53: ='DETAILS (sorted)'!BI46 -> 800000 | I53: 1700000 | J53: =H53/I53 -> 0.47058824 | K53: =MAX(I53-H53,0) -> 900000 | L53: =100%-J53 -> 0.52941176 | O53: =F53=H53 -> FALSE | P53: 1
A54: =A53+1 -> 46 | B54: Nsanyiwa Kiloba | C54: 200000 | D54: 100000 | E54: 710000 | F54: =SUM(C54:E54) -> 1010000 | G54: =F54=H54 -> FALSE | H54: ='DETAILS (sorted)'!BI47 -> 1000000 | I54: 1700000 | J54: =H54/I54 -> 0.58823529 | K54: =MAX(I54-H54,0) -> 700000 | L54: =100%-J54 -> 0.41176471 | O54: =F54=H54 -> FALSE | P54: 1 | Q54: 235000
A55: =A54+1 -> 47 | B55: Omary Mwasema | C55: 50000 | F55: =SUM(C55:E55) -> 50000 | G55: =F55=H55 -> FALSE | H55: ='DETAILS (sorted)'!BI48 -> 713000 | I55: 1700000 | J55: =H55/I55 -> 0.41941176 | K55: =MAX(I55-H55,0) -> 987000 | L55: =100%-J55 -> 0.58058824 | O55: =F55=H55 -> FALSE
A56: =A55+1 -> 48 | B56: Patiens Rweyemamu | C56: 100000 | F56: =SUM(C56:E56) -> 100000 | G56: =F56=H56 -> FALSE | H56: ='DETAILS (sorted)'!BI49 -> 1110000 | I56: 1700000 | J56: =H56/I56 -> 0.65294118 | K56: =MAX(I56-H56,0) -> 590000 | L56: =100%-J56 -> 0.34705882 | O56: =F56=H56 -> FALSE
A57: =A56+1 -> 49 | B57: Patrick S. Kiani | C57: 200000 | D57: 100000 | E57: 900000 | F57: =SUM(C57:E57) -> 1200000 | G57: =F57=H57 -> FALSE | H57: ='DETAILS (sorted)'!BI50 -> 700000 | I57: 1700000 | J57: =H57/I57 -> 0.41176471 | K57: =MAX(I57-H57,0) -> 1000000 | L57: =100%-J57 -> 0.58823529 | P57: 1
A58: =A57+1 -> 50 | B58: Paul Metili | C58: 100000 | F58: =SUM(C58:E58) -> 100000 | G58: =F58=H58 -> FALSE | H58: ='DETAILS (sorted)'!BI51 -> 800000 | I58: 1700000 | J58: =H58/I58 -> 0.47058824 | K58: =MAX(I58-H58,0) -> 900000 | L58: =100%-J58 -> 0.52941176 | O58: =F58=H58 -> FALSE
A59: =A58+1 -> 51 | B59: Robert Masegese | C59: 200000 | F59: =SUM(C59:E59) -> 200000 | G59: =F59=H59 -> FALSE | H59: ='DETAILS (sorted)'!BI52 -> 50000 | I59: 1700000 | J59: =H59/I59 -> 0.029411765 | K59: =MAX(I59-H59,0) -> 1650000 | L59: =100%-J59 -> 0.97058824 | O59: =F59=H59 -> FALSE
A60: =A59+1 -> 52 | B60: Saidi Ramadhani Mdee | C60: 200000 | D60: 100000 | E60: 700000 | F60: =SUM(C60:E60) -> 1000000 | G60: =F60=H60 -> FALSE | H60: ='DETAILS (sorted)'!BI53 -> 50000 | I60: 1700000 | J60: =H60/I60 -> 0.029411765 | K60: =MAX(I60-H60,0) -> 1650000 | L60: =100%-J60 -> 0.97058824 | P60: 1
A61: =A60+1 -> 53 | B61: Salum Ndolanga | C61: 100000 | F61: =SUM(C61:E61) -> 100000 | G61: =F61=H61 -> FALSE | H61: ='DETAILS (sorted)'!BI54 -> 200000 | I61: 1700000 | J61: =H61/I61 -> 0.11764706 | K61: =MAX(I61-H61,0) -> 1500000 | L61: =100%-J61 -> 0.88235294 | O61: =F61=H61 -> FALSE | Q61: 10000
A62: =A61+1 -> 54 | B62: Shabani Salim | C62: 200000 | D62: 100000 | E62: 700000 | F62: =SUM(C62:E62) -> 1000000 | G62: =F62=H62 -> FALSE | H62: ='DETAILS (sorted)'!BI55 -> 120000 | I62: 1700000 | J62: =H62/I62 -> 0.070588235 | K62: =MAX(I62-H62,0) -> 1580000 | L62: =100%-J62 -> 0.92941176 | P62: 1
A63: =A62+1 -> 55 | B63: Shumbi Mkumbo | C63: 200000 | D63: 100000 | E63: 500000 | F63: =SUM(C63:E63) -> 800000 | G63: =F63=H63 -> FALSE | H63: ='DETAILS (sorted)'!BI56 -> 100000 | I63: 1700000 | J63: =H63/I63 -> 0.058823529 | K63: =MAX(I63-H63,0) -> 1600000 | L63: =100%-J63 -> 0.94117647 | O63: =F63=H63 -> FALSE
A64: =A63+1 -> 56 | B64: Stanslaus Nyembea | C64: 120000 | F64: =SUM(C64:E64) -> 120000 | G64: =F64=H64 -> FALSE | H64: ='DETAILS (sorted)'!BI57 -> 100000 | I64: 1700000 | J64: =H64/I64 -> 0.058823529 | K64: =MAX(I64-H64,0) -> 1600000 | L64: =100%-J64 -> 0.94117647 | O64: =F64=H64 -> FALSE
A65: =A64+1 -> 57 | B65: Stephen Nkurlu | C65: 200000 | D65: 100000 | E65: 720000 | F65: =SUM(C65:E65) -> 1020000 | G65: =F65=H65 -> FALSE | H65: ='DETAILS (sorted)'!BI58 -> 100000 | I65: 1700000 | J65: =H65/I65 -> 0.058823529 | K65: =MAX(I65-H65,0) -> 1600000 | L65: =100%-J65 -> 0.94117647 | O65: =F65=H65 -> FALSE | P65: 1
A66: =A65+1 -> 58 | B66: Walter Salema | C66: 200000 | D66: 100000 | E66: 500000 | F66: =SUM(C66:E66) -> 800000 | G66: =F66=H66 -> FALSE | H66: ='DETAILS (sorted)'!BI59 -> 160000 | I66: 1700000 | J66: =H66/I66 -> 0.094117647 | K66: =MAX(I66-H66,0) -> 1540000 | L66: =100%-J66 -> 0.90588235 | O66: =F66=H66 -> FALSE
A67: =A66+1 -> 59 | B67: Werema Msongo | C67: 200000 | D67: 100000 | E67: 500000 | F67: =SUM(C67:E67) -> 800000 | G67: =F67=H67 -> FALSE | H67: ='DETAILS (sorted)'!BI60 -> 100000 | I67: 1700000 | J67: =H67/I67 -> 0.058823529 | K67: =MAX(I67-H67,0) -> 1600000 | L67: =100%-J67 -> 0.94117647 | O67: =F67=H67 -> FALSE
G68: =F68=H68 -> TRUE
G69: =F69=H69 -> TRUE
G70: =F70=H70 -> TRUE
G71: =F71=H71 -> TRUE
A72: =#REF!+1 -> #REF! | B72: Moses Lazaro Molel | F72: =SUM(C72:E72) -> 0 | G72: =F72=H72 -> TRUE | I72: 1000000 | J72: =H72/I72 -> 0 | K72: =MAX(I72-H72,0) -> 1000000 | L72: =100%-J72 -> 1 | O72: =F72=H72 -> TRUE
A73: =A72+1 -> #REF! | B73: Edgar Rwezaura | C73: 0 | D73: 0 | F73: =SUM(C73:E73) -> 0 | G73: =F73=H73 -> TRUE | I73: 1000000 | J73: =H73/I73 -> 0 | K73: =MAX(I73-F73,0) -> 1000000 | L73: =100%-J73 -> 1 | M73: WAMEJISAJILI M-KOPA TU. HAWAJALIPA MCHANGO WOWOTE | O73: =F73=H73 -> TRUE
A74: =A73+1 -> #REF! | B74: Manase Mushi | C74: 0 | D74: 0 | F74: =SUM(C74:E74) -> 0 | G74: =F74=H74 -> TRUE | I74: 1000000 | J74: =H74/I74 -> 0 | K74: =MAX(I74-F74,0) -> 1000000 | L74: =100%-J74 -> 1 | O74: =F74=H74 -> TRUE
A75: =A74+1 -> #REF! | B75: Paul Mikongoti | C75: 0 | D75: 0 | F75: =SUM(C75:E75) -> 0 | G75: =F75=H75 -> TRUE | I75: 1000000 | J75: =H75/I75 -> 0 | K75: =MAX(I75-F75,0) -> 1000000 | L75: =100%-J75 -> 1 | O75: =F75=H75 -> TRUE
A76: =A75+1 -> #REF! | B76: Moses Luguru | C76: 0 | D76: 0 | F76: =SUM(C76:E76) -> 0 | G76: =F76=H76 -> TRUE | I76: 1000000 | J76: =H76/I76 -> 0 | K76: =MAX(I76-F76,0) -> 1000000 | L76: =100%-J76 -> 1 | O76: =F76=H76 -> TRUE
A77: =A76+1 -> #REF! | B77: Emili Mkwawi | C77: 0 | D77: 0 | F77: =SUM(C77:E77) -> 0 | G77: =F77=H77 -> TRUE | I77: 1000000 | J77: =H77/I77 -> 0 | K77: =MAX(I77-F77,0) -> 1000000 | L77: =100%-J77 -> 1 | O77: =F77=H77 -> TRUE
A78: =A77+1 -> #REF! | B78: Salum Hassani | C78: 0 | D78: 0 | F78: =SUM(C78:E78) -> 0 | G78: =F78=H78 -> TRUE | I78: 1000000 | J78: =H78/I78 -> 0 | K78: =MAX(I78-F78,0) -> 1000000 | L78: =100%-J78 -> 1 | O78: =F78=H78 -> TRUE
A79: =A78+1 -> #REF! | B79: Richard Makala | C79: 0 | D79: 0 | F79: =SUM(C79:E79) -> 0 | G79: =F79=H79 -> TRUE | I79: 1000000 | J79: =H79/I79 -> 0 | K79: =MAX(I79-F79,0) -> 1000000 | L79: =100%-J79 -> 1 | O79: =F79=H79 -> TRUE
A80: =A79+1 -> #REF! | B80: Shabani Salim | C80: 0 | D80: 0 | F80: =SUM(C80:E80) -> 0 | G80: =F80=H80 -> TRUE | I80: 1000000 | J80: =H80/I80 -> 0 | K80: =MAX(I80-F80,0) -> 1000000 | L80: =100%-J80 -> 1 | O80: =F80=H80 -> TRUE
A81: =A80+1 -> #REF! | B81: Fabian Sedoyeka | C81: 0 | D81: 0 | F81: =SUM(C81:E81) -> 0 | G81: =F81=H81 -> TRUE | I81: 1000000 | J81: =H81/I81 -> 0 | K81: =MAX(I81-F81,0) -> 1000000 | L81: =100%-J81 -> 1 | O81: =F81=H81 -> TRUE
A82: =A81+1 -> #REF! | B82: Piniel Seth | C82: 0 | D82: 0 | F82: =SUM(C82:E82) -> 0 | G82: =F82=H82 -> TRUE | I82: 1000000 | J82: =H82/I82 -> 0 | K82: =MAX(I82-F82,0) -> 1000000 | L82: =100%-J82 -> 1 | O82: =F82=H82 -> TRUE
A83: =A82+1 -> #REF! | B83: Beatus Chikoti | C83: 0 | D83: 0 | E83: 0 | F83: =SUM(C83:E83) -> 0 | G83: =F83=H83 -> TRUE | I83: 1000000 | J83: =H83/I83 -> 0 | K83: =MAX(I83-F83,0) -> 1000000 | L83: =100%-J83 -> 1 | O83: =F83=H83 -> TRUE
A84: =A83+1 -> #REF! | B84: Nyangusi Laizer | C84: 0 | D84: 0 | F84: =SUM(C84:E84) -> 0 | G84: =F84=H84 -> TRUE | I84: 1000000 | J84: =H84/I84 -> 0 | K84: =MAX(I84-F84,0) -> 1000000 | L84: =100%-J84 -> 1 | O84: =F84=H84 -> TRUE
A85: =A84+1 -> #REF! | B85: Anase Minja | C85: 0 | D85: 0 | F85: =SUM(C85:E85) -> 0 | G85: =F85=H85 -> TRUE | I85: 1000000 | J85: =H85/I85 -> 0 | K85: =MAX(I85-F85,0) -> 1000000 | L85: =100%-J85 -> 1 | O85: =F85=H85 -> TRUE
A86: =A85+1 -> #REF! | B86: Robert Kitundu | C86: 0 | D86: 0 | F86: =SUM(C86:E86) -> 0 | G86: =F86=H86 -> TRUE | I86: 1000000 | J86: =H86/I86 -> 0 | K86: =MAX(I86-F86,0) -> 1000000 | L86: =100%-J86 -> 1 | O86: =F86=H86 -> TRUE
A87: =A86+1 -> #REF! | B87: Msafiri Mwapinga | C87: 0 | D87: 0 | F87: =SUM(C87:E87) -> 0 | G87: =F87=H87 -> TRUE | I87: 1000000 | J87: =H87/I87 -> 0 | K87: =MAX(I87-F87,0) -> 1000000 | L87: =100%-J87 -> 1 | O87: =F87=H87 -> TRUE
G88: =F88=H88 -> TRUE | J88: =H88/I88 -> #DIV/0! | O88: =F88=H88 -> TRUE
B91: TOTAL | C91: =SUM(C12:C88) -> 10321000 | D91: =SUM(D12:D88) -> 4600000 | E91: =SUM(E12:E88) -> 31203000 | F91: =SUM(F12:F88) -> 46124000 | G91: =SUM(G12:G88) -> 0 | H91: =SUM(H12:H88) -> 64224000 | I91: =SUM(I12:I88) -> 111200000 | K91: =SUM(K12:K88) -> 51296000 | N91: =SUM(N12:N87) -> 30000 | O91: =F91=H91 -> FALSE
B92: MKOBA MAIN BALANCE | H92: ='DETAILS (sorted)'!BM155 -> 100000 | P92: =SUM(P14:P91) -> 35 | Q92: =P92/P93 -> 0.50724638
B93: MKOBA B BALANCE | P93: 69
B94: Bank - NMB | H94: ='DETAILS (sorted)'!#REF! -> #REF!
B95: TOTAL BALANCE | H95: =SUM(H92:H94) -> #REF!
H97: =H91 -> 64224000
B99: Mwenyekiti alitoa ufafanuzi wa gharama zilizochangiwa na wanachama waanzilishi kama ifuatavyo: | D99: Allocated accordingly to contributions
B100: a) Gharama za Ukumbi: TZS 75,000. Gharama hizi zilichangiwa na:
B101: (i) Mwenyekiti Ndugu Donald Nsanyiwa – TZS 75,000 | C101: 75000
B102: b) Gharama ya Usafiri kwa Afisa Ushirika: TZS 50,000. Gharama hizi zilichangiwa na:
B103: (i) Ndugu Donald Nsanyiwa – TZS 10,000 | C103: 10000
B104: (ii) Salum Ndolanga – TZS 10,000 | C104: 10000
B105: (iii) Eliashasaria Munisi – TZS 10,000 | C105: 10000
B106: (iv) Nixon Matowo – TZS 10,000 | C106: 10000
B107: (v) Fredrick Ndossi – TZS 10,000 | C107: 10000
...

Sheet Summary2
A1: ILBORU ALUMNI SACCOS LIMITED
A3: MICHANGO YA WANACHAMA
A6: S/N | B6: Member Name | C6: MICHANGO
C7: KIINGILIO | D7: AKIBA | E7: HISA | F7: JUMLA | H7: ACTUAL | I7: KIINGILIO | J7: SHARES (50%) | K7: OCTOBER, 2024 | L7: NOV, 2024 | M7: DEC, 2024 | N7: JAN, 2025 | O7: FEB, 2025 | P7: TOTAL | Q7: STATUS
D8: ALLOCATED FROM M-KOBA | E8: ALLOCATED FROM M-KOBA | H8: MKOBA
A9: 1 | B9: Aaron J. Mtui | C9: 100000 | F9: =SUM(C9:E9) -> 100000 | G9: =F9=H9 -> TRUE | H9: =Summary!H9 -> 100000 | I9: 200000 | J9: 500000 | K9: 100000 | L9: 100000 | M9: 100000 | N9: 100000 | O9: 100000 | P9: =SUM(I9:O9) -> 1200000 | Q9: =H9-P9 -> -1100000
A10: =A9+1 -> 2 | B10: Abduel G. Kitururu | C10: 200000 | D10: 100000 | E10: 330000 | F10: =SUM(C10:E10) -> 630000 | G10: =F10=H10 -> TRUE | H10: =Summary!H10 -> 630000 | I10: 200000 | J10: 500000 | K10: 100000 | L10: 100000 | M10: 100000 | N10: 100000 | O10: 100000 | P10: =SUM(I10:O10) -> 1200000 | Q10: =H10-P10 -> -570000
A11: =A10+1 -> 3 | B11: Abraham A. Assenga | C11: 200000 | D11: 100000 | E11: 700000 | F11: =SUM(C11:E11) -> 1000000 | G11: =F11=H11 -> TRUE | H11: =Summary!H11 -> 1000000 | I11: 200000 | J11: 500000 | K11: 100000 | L11: 100000 | M11: 100000 | N11: 100000 | O11: 100000 | P11: =SUM(I11:O11) -> 1200000 | Q11: =H11-P11 -> -200000
A12: =A11+1 -> 4 | B12: Adam I. Urassa | C12: 200000 | D12: 100000 | E12: 700000 | F12: =SUM(C12:E12) -> 1000000 | G12: =F12=H12 -> TRUE | H12: =Summary!H12 -> 1000000 | I12: 200000 | J12: 500000 | K12: 100000 | L12: 100000 | M12: 100000 | N12: 100000 | O12: 100000 | P12: =SUM(I12:O12) -> 1200000 | Q12: =H12-P12 -> -200000
A13: =A12+1 -> 5 | B13: Amos M. Nungu | C13: 200000 | D13: 100000 | E13: 700000 | F13: =SUM(C13:E13) -> 1000000 | G13: =F13=H13 -> TRUE | H13: =Summary!H13 -> 1000000 | I13: 200000 | J13: 500000 | K13: 100000 | L13: 100000 | M13: 100000 | N13: 100000 | O13: 100000 | P13: =SUM(I13:O13) -> 1200000 | Q13: =H13-P13 -> -200000
A14: =A13+1 -> 6 | B14: Athumani Jerry Mwasha | C14: 200000 | D14: 100000 | E14: 700000 | F14: =SUM(C14:E14) -> 1000000 | G14: =F14=H14 -> TRUE | H14: =Summary!H14 -> 1000000 | I14: 200000 | J14: 500000 | K14: 100000 | L14: 100000 | M14: 100000 | N14: 100000 | O14: 100000 | P14: =SUM(I14:O14) -> 1200000 | Q14: =H14-P14 -> -200000
A15: =A14+1 -> 7 | B15: Elianshisaria Invocavith Munisi | C15: 200000 | D15: 100000 | E15: 920000 | F15: =SUM(C15:E15) -> 1220000 | G15: =F15=H15 -> TRUE | H15: =Summary!H15 -> 1220000 | I15: 200000 | J15: 500000 | K15: 100000 | L15: 100000 | M15: 100000 | N15: 100000 | O15: 100000 | P15: =SUM(I15:O15) -> 1200000 | Q15: =H15-P15 -> 20000
A16: =A15+1 -> 8 | B16: Elibariki Mkumbo | C16: 200000 | D16: 100000 | E16: 700000 | F16: =SUM(C16:E16) -> 1000000 | G16: =F16=H16 -> TRUE | H16: =Summary!H16 -> 1000000 | I16: 200000 | J16: 500000 | K16: 100000 | L16: 100000 | M16: 100000 | N16: 100000 | O16: 100000 | P16: =SUM(I16:O16) -> 1200000 | Q16: =H16-P16 -> -200000
A17: =A16+1 -> 9 | B17: Emmanuel Matechi | C17: 200000 | D17: 100000 | E17: 700000 | F17: =SUM(C17:E17) -> 1000000 | G17: =F17=H17 -> TRUE | H17: =Summary!H17 -> 1000000 | I17: 200000 | J17: 500000 | K17: 100000 | L17: 100000 | M17: 100000 | N17: 100000 | O17: 100000 | P17: =SUM(I17:O17) -> 1200000 | Q17: =H17-P17 -> -200000
A18: =A17+1 -> 10 | B18: Emmanuel Matee | C18: 200000 | D18: 100000 | E18: 1000000 | F18: =SUM(C18:E18) -> 1300000 | G18: =F18=H18 -> TRUE | H18: =Summary!H18 -> 1300000 | I18: 200000 | J18: 500000 | K18: 100000 | L18: 100000 | M18: 100000 | N18: 100000 | O18: 100000 | P18: =SUM(I18:O18) -> 1200000 | Q18: =H18-P18 -> 100000
A19: =A18+1 -> 11 | B19: Emmanuel Mmari | C19: 200000 | D19: 100000 | E19: 700000 | F19: =SUM(C19:E19) -> 1000000 | G19: =F19=H19 -> TRUE | H19: =Summary!H19 -> 1000000 | I19: 200000 | J19: 500000 | K19: 100000 | L19: 100000 | M19: 100000 | N19: 100000 | O19: 100000 | P19: =SUM(I19:O19) -> 1200000 | Q19: =H19-P19 -> -200000
A20: =A19+1 -> 12 | B20: Erick Kitali | C20: 200000 | D20: 100000 | E20: 700000 | F20: =SUM(C20:E20) -> 1000000 | G20: =F20=H20 -> FALSE | H20: =Summary!H20 -> 1300000 | I20: 200000 | J20: 500000 | K20: 100000 | L20: 100000 | M20: 100000 | N20: 100000 | O20: 100000 | P20: =SUM(I20:O20) -> 1200000 | Q20: =H20-P20 -> 100000
A21: =A20+1 -> 13 | B21: Ernest Felician Shirima | C21: 200000 | D21: 100000 | E21: 500000 | F21: =SUM(C21:E21) -> 800000 | G21: =F21=H21 -> TRUE | H21: =Summary!H21 -> 800000 | I21: 200000 | J21: 500000 | K21: 100000 | L21: 100000 | M21: 100000 | N21: 100000 | O21: 100000 | P21: =SUM(I21:O21) -> 1200000 | Q21: =H21-P21 -> -400000
... A34: =A33+1 -> 26 | B34: Charles Jangu | C34: 200000 | D34: 100000 | E34: 400000 | F34: =SUM(C34:E34) -> 700000 | G34: =F34=H34 -> TRUE | H34: =Summary!H34 -> 700000 | I34: 200000 | J34: 500000 | K34: 100000 | L34: 100000 | M34: 100000 | N34: 100000 | O34: 100000 | P34: =SUM(I34:O34) -> 1200000 | Q34: =H34-P34 -> -500000
A35: =A34+1 -> 27 | B35: David Koillah | C35: 100000 | F35: =SUM(C35:E35) -> 100000 | G35: =F35=H35 -> TRUE | H35: =Summary!H35 -> 100000 | I35: 200000 | J35: 500000 | K35: 100000 | L35: 100000 | M35: 100000 | N35: 100000 | O35: 100000 | P35: =SUM(I35:O35) -> 1200000 | Q35: =H35-P35 -> -1100000
A36: =A35+1 -> 28 | B36: Emmanuel Msaki | C36: 200000 | D36: 100000 | E36: 213000 | F36: =SUM(C36:E36) -> 513000 | G36: =F36=H36 -> TRUE | H36: =Summary!H36 -> 513000 | I36: 200000 | J36: 500000 | K36: 100000 | L36: 100000 | M36: 100000 | N36: 100000 | O36: 100000 | P36: =SUM(I36:O36) -> 1200000 | Q36: =H36-P36 -> -687000
A37: =A36+1 -> 29 | B37: Evance Mori | C37: 200000 | D37: 100000 | E37: 700000 | F37: =SUM(C37:E37) -> 1000000 | G37: =F37=H37 -> TRUE | H37: =Summary!H37 -> 1000000 | I37: 200000 | J37: 500000 | K37: 100000 | L37: 100000 | M37: 100000 | N37: 100000 | O37: 100000 | P37: =SUM(I37:O37) -> 1200000 | Q37: =H37-P37 -> -200000
A38: =A37+1 -> 30 | B38: Felix Daniel | C38: 141000 | F38: =SUM(C38:E38) -> 141000 | G38: =F38=H38 -> TRUE | H38: =Summary!H38 -> 141000 | I38: 200000 | J38: 500000 | K38: 100000 | L38: 100000 | M38: 100000 | N38: 100000 | O38: 100000 | P38: =SUM(I38:O38) -> 1200000 | Q38: =H38-P38 -> -1059000
A39: =A38+1 -> 31 | B39: Gideon Gabriel | C39: 200000 | D39: 100000 | E39: 70000 | F39: =SUM(C39:E39) -> 370000 | G39: =F39=H39 -> TRUE | H39: =Summary!H39 -> 370000 | I39: 200000 | J39: 500000 | K39: 100000 | L39: 100000 | M39: 100000 | N39: 100000 | O39: 100000 | P39: =SUM(I39:O39) -> 1200000 | Q39: =H39-P39 -> -830000
A40: =A39+1 -> 32 | B40: Hassan Matata | C40: 200000 | D40: 100000 | E40: 700000 | F40: =SUM(C40:E40) -> 1000000 | G40: =F40=H40 -> TRUE | H40: =Summary!H40 -> 1000000 | I40: 200000 | J40: 500000 | K40: 100000 | L40: 100000 | M40: 100000 | N40: 100000 | O40: 100000 | P40: =SUM(I40:O40) -> 1200000 | Q40: =H40-P40 -> -200000
A41: =A40+1 -> 33 | B41: Innocent Kasigwa | C41: 200000 | D41: 100000 | E41: 700000 | F41: =SUM(C41:E41) -> 1000000 | G41: =F41=H41 -> TRUE | H41: =Summary!H41 -> 1000000 | I41: 200000 | J41: 500000 | K41: 100000 | L41: 100000 | M41: 100000 | N41: 100000 | O41: 100000 | P41: =SUM(I41:O41) -> 1200000 | Q41: =H41-P41 -> -200000
A42: =A41+1 -> 34 | B42: Innocent Kweka | C42: 160000 | F42: =SUM(C42:E42) -> 160000 | G42: =F42=H42 -> TRUE | H42: =Summary!H42 -> 160000 | I42: 200000 | J42: 500000 | K42: 100000 | L42: 100000 | M42: 100000 | N42: 100000 | O42: 100000 | P42: =SUM(I42:O42) -> 1200000 | Q42: =H42-P42 -> -1040000
A43: =A42+1 -> 35 | B43: Jacob Mangu | C43: 200000 | D43: 100000 | E43: 1300000 | F43: =SUM(C43:E43) -> 1600000 | G43: =F43=H43 -> TRUE | H43: =Summary!H43 -> 1600000 | I43: 200000 | J43: 500000 | K43: 100000 | L43: 100000 | M43: 100000 | N43: 100000 | O43: 100000 | P43: =SUM(I43:O43) -> 1200000 | Q43: =H43-P43 -> 400000
A44: =A43+1 -> 36 | B44: John Massawe | C44: 200000 | D44: 100000 | E44: 700000 | F44: =SUM(C44:E44) -> 1000000 | G44: =F44=H44 -> TRUE | H44: =Summary!H44 -> 1000000 | I44: 200000 | J44: 500000 | K44: 100000 | L44: 100000 | M44: 100000 | N44: 100000 | O44: 100000 | P44: =SUM(I44:O44) -> 1200000 | Q44: =H44-P44 -> -200000
A45: =A44+1 -> 37 | B45: Khalifa Sushy | C45: 200000 | D45: 100000 | E45: 120000 | F45: =SUM(C45:E45) -> 420000 | G45: =F45=H45 -> TRUE | H45: =Summary!H45 -> 420000 | I45: 200000 | J45: 500000 | K45: 100000 | L45: 100000 | M45: 100000 | N45: 100000 | O45: 100000 | P45: =SUM(I45:O45) -> 1200000 | Q45: =H45-P45 -> -780000
A46: =A45+1 -> 38 | B46: Laurian Gidoyi | C46: 200000 | D46: 100000 | E46: 700000 | F46: =SUM(C46:E46) -> 1000000 | G46: =F46=H46 -> TRUE | H46: =Summary!H46 -> 1000000 | I46: 200000 | J46: 500000 | K46: 100000 | L46: 100000 | M46: 100000 | N46: 100000 | O46: 100000 | P46: =SUM(I46:O46) -> 1200000 | Q46: =H46-P46 -> -200000
A47: =A46+1 -> 39 | B47: Liggyle Vumilia | C47: 200000 | D47: 100000 | E47: 50000 | F47: =SUM(C47:E47) -> 350000 | G47: =F47=H47 -> TRUE | H47: =Summary!H47 -> 350000 | I47: 200000 | J47: 500000 | K47: 100000 | L47: 100000 | M47: 100000 | N47: 100000 | O47: 100000 | P47: =SUM(I47:O47) -> 1200000 | Q47: =H47-P47 -> -850000
A48: =A47+1 -> 40 | B48: Masale Masale | C48: 200000 | D48: 100000 | E48: 700000 | F48: =SUM(C48:E48) -> 1000000 | G48: =F48=H48 -> TRUE | H48: =Summary!H48 -> 1000000 | I48: 200000 | J48: 500000 | K48: 100000 | L48: 100000 | M48: 100000 | N48: 100000 | O48: 100000 | P48: =SUM(I48:O48) -> 1200000 | Q48: =H48-P48 -> -200000
A49: =A48+1 -> 41 | B49: Nalogwa Kiula | C49: 50000 | F49: =SUM(C49:E49) -> 50000 | G49: =F49=H49 -> TRUE | H49: =Summary!H49 -> 50000 | I49: 200000 | J49: 500000 | K49: 100000 | L49: 100000 | M49: 100000 | N49: 100000 | O49: 100000 | P49: =SUM(I49:O49) -> 1200000 | Q49: =H49-P49 -> -1150000
A50: =A49+1 -> 42 | B50: Nixon Matowo | C50: 200000 | D50: 100000 | E50: 710000 | F50: =SUM(C50:E50) -> 1010000 | G50: =F50=H50 -> TRUE | H50: =Summary!H50 -> 1010000 | I50: 200000 | J50: 500000 | K50: 100000 | L50: 100000 | M50: 100000 | N50: 100000 | O50: 100000 | P50: =SUM(I50:O50) -> 1200000 | Q50: =H50-P50 -> -190000
A51: =A50+1 -> 43 | B51: Norbert Massay | C51: 200000 | D51: 100000 | E51: 700000 | F51: =SUM(C51:E51) -> 1000000 | G51: =F51=H51 -> FALSE | H51: =Summary!H51 -> 1200000 | I51: 200000 | J51: 500000 | K51: 100000 | L51: 100000 | M51: 100000 | N51: 100000 | O51: 100000 | P51: =SUM(I51:O51) -> 1200000 | Q51: =H51-P51 -> 0
A52: =A51+1 -> 44 | B52: Omary Mwasema | C52: 50000 | F52: =SUM(C52:E52) -> 50000 | G52: =F52=H52 -> TRUE | H52: =Summary!H52 -> 50000 | I52: 200000 | J52: 500000 | K52: 100000 | L52: 100000 | M52: 100000 | N52: 100000 | O52: 100000 | P52: =SUM(I52:O52) -> 1200000 | Q52: =H52-P52 -> -1150000
A53: =A52+1 -> 45 | B53: Patiens Rweyemamu | C53: 100000 | F53: =SUM(C53:E53) -> 100000 | G53: =F53=H53 -> TRUE | H53: =Summary!H53 -> 100000 | I53: 200000 | J53: 500000 | K53: 100000 | L53: 100000 | M53: 100000 | N53: 100000 | O53: 100000 | P53: =SUM(I53:O53) -> 1200000 | Q53: =H53-P53 -> -1100000
A54: =A53+1 -> 46 | B54: Paul Metili | C54: 100000 | F54: =SUM(C54:E54) -> 100000 | G54: =F54=H54 -> TRUE | H54: =Summary!H54 -> 100000 | I54: 200000 | J54: 500000 | K54: 100000 | L54: 100000 | M54: 100000 | N54: 100000 | O54: 100000 | P54: =SUM(I54:O54) -> 1200000 | Q54: =H54-P54 -> -1100000
A55: =A54+1 -> 47 | B55: Robert Masegese | C55: 200000 | F55: =SUM(C55:E55) -> 200000 | G55: =F55=H55 -> TRUE | H55: =Summary!H55 -> 200000 | I55: 200000 | J55: 500000 | K55: 100000 | L55: 100000 | M55: 100000 | N55: 100000 | O55: 100000 | P55: =SUM(I55:O55) -> 1200000 | Q55: =H55-P55 -> -1000000
A56: =A55+1 -> 48 | B56: Salum Ndolanga | C56: 100000 | F56: =SUM(C56:E56) -> 100000 | G56: =F56=H56 -> TRUE | H56: =Summary!H56 -> 100000 | I56: 200000 | J56: 500000 | K56: 100000 | L56: 100000 | M56: 100000 | N56: 100000 | O56: 100000 | P56: =SUM(I56:O56) -> 1200000 | Q56: =H56-P56 -> -1100000
A57: =A56+1 -> 49 | B57: Shumbi Mkumbo | C57: 200000 | D57: 100000 | E57: 500000 | F57: =SUM(C57:E57) -> 800000 | G57: =F57=H57 -> TRUE | H57: =Summary!H57 -> 800000 | I57: 200000 | J57: 500000 | K57: 100000 | L57: 100000 | M57: 100000 | N57: 100000 | O57: 100000 | P57: =SUM(I57:O57) -> 1200000 | Q57: =H57-P57 -> -400000
A58: =A57+1 -> 50 | B58: Stanslaus Nyembea | C58: 120000 | F58: =SUM(C58:E58) -> 120000 | G58: =F58=H58 -> TRUE | H58: =Summary!H58 -> 120000 | I58: 200000 | J58: 500000 | K58: 100000 | L58: 100000 | M58: 100000 | N58: 100000 | O58: 100000 | P58: =SUM(I58:O58) -> 1200000 | Q58: =H58-P58 -> -1080000
A59: =A58+1 -> 51 | B59: Stephen Nkurlu | C59: 200000 | D59: 100000 | E59: 720000 | F59: =SUM(C59:E59) -> 1020000 | G59: =F59=H59 -> TRUE | H59: =Summary!H59 -> 1020000 | I59: 200000 | J59: 500000 | K59: 100000 | L59: 100000 | M59: 100000 | N59: 100000 | O59: 100000 | P59: =SUM(I59:O59) -> 1200000 | Q59: =H59-P59 -> -180000
A60: =A59+1 -> 52 | B60: Walter Salema | C60: 200000 | D60: 100000 | E60: 500000 | F60: =SUM(C60:E60) -> 800000 | G60: =F60=H60 -> TRUE | H60: =Summary!H60 -> 800000 | I60: 200000 | J60: 500000 | K60: 100000 | L60: 100000 | M60: 100000 | N60: 100000 | O60: 100000 | P60: =SUM(I60:O60) -> 1200000 | Q60: =H60-P60 -> -400000
A61: =A60+1 -> 53 | B61: Werema Msongo | C61: 200000 | D61: 100000 | E61: 500000 | F61: =SUM(C61:E61) -> 800000 | G61: =F61=H61 -> TRUE | H61: =Summary!H61 -> 800000 | I61: 200000 | J61: 500000 | K61: 100000 | L61: 100000 | M61: 100000 | N61: 100000 | O61: 100000 | P61: =SUM(I61:O61) -> 1200000 | Q61: =H61-P61 -> -400000
A62: =A61+1 -> 54 | B62: Emanuel Moshi | C62: 200000 | D62: 100000 | E62: 900000 | F62: =SUM(C62:E62) -> 1200000 | G62: =F62=H62 -> TRUE | H62: =Summary!H62 -> 1200000 | I62: 200000 | J62: 500000 | K62: 100000 | L62: 100000 | M62: 100000 | N62: 100000 | O62: 100000 | P62: =SUM(I62:O62) -> 1200000 | Q62: =H62-P62 -> 0
A63: =A62+1 -> 55 | B63: Innocent Mosha | C63: 200000 | D63: 100000 | E63: 700000 | F63: =SUM(C63:E63) -> 1000000 | G63: =F63=H63 -> TRUE | H63: =Summary!H63 -> 1000000 | I63: 200000 | J63: 500000 | K63: 100000 | L63: 100000 | M63: 100000 | N63: 100000 | O63: 100000 | P63: =SUM(I63:O63) -> 1200000 | Q63: =H63-P63 -> -200000
A64: =A63+1 -> 56 | B64: Shabani Salim | C64: 200000 | D64: 100000 | E64: 700000 | F64: =SUM(C64:E64) -> 1000000 | G64: =F64=H64 -> TRUE | H64: =Summary!H64 -> 1000000 | I64: 200000 | J64: 500000 | K64: 100000 | L64: 100000 | M64: 100000 | N64: 100000 | O64: 100000 | P64: =SUM(I64:O64) -> 1200000 | Q64: =H64-P64 -> -200000
A65: =A64+1 -> 57 | B65: Adolph Ndyeabura | C65: 200000 | D65: 100000 | E65: 700000 | F65: =SUM(C65:E65) -> 1000000 | G65: =F65=H65 -> TRUE | H65: =Summary!H65 -> 1000000 | I65: 200000 | J65: 500000 | K65: 100000 | L65: 100000 | M65: 100000 | N65: 100000 | O65: 100000 | P65: =SUM(I65:O65) -> 1200000 | Q65: =H65-P65 -> -200000
A66: =A65+1 -> 58 | B66: Saidi Ramadhani Mdee | C66: 200000 | D66: 100000 | E66: 700000 | F66: =SUM(C66:E66) -> 1000000 | G66: =F66=H66 -> TRUE | H66: =Summary!H66 -> 1000000 | I66: 200000 | J66: 500000 | K66: 100000 | L66: 100000 | M66: 100000 | N66: 100000 | O66: 100000 | P66: =SUM(I66:O66) -> 1200000 | Q66: =H66-P66 -> -200000
A67: =A66+1 -> 59 | B67: Patrick K. Kiani | C67: 200000 | D67: 100000 | E67: 700000 | F67: =SUM(C67:E67) -> 1000000 | G67: =F67=H67 -> FALSE | H67: =Summary!H67 -> 1200000 | I67: 200000 | J67: 500000 | K67: 100000 | L67: 100000 | M67: 100000 | N67: 100000 | O67: 100000 | P67: =SUM(I67:O67) -> 1200000 | Q67: =H67-P67 -> 0
G68: =F68=H68 -> TRUE | Q68: =H68-P68 -> 0
G69: =F69=H69 -> TRUE | Q69: =H69-P69 -> 0
G70: =F70=H70 -> TRUE | Q70: =H70-P70 -> 0
G71: =F71=H71 -> TRUE | Q71: =H71-P71 -> 0
A72: =A66+1 -> 59 | B72: Moses Lazaro Molel | F72: =SUM(C72:E72) -> 0 | G72: =F72=H72 -> TRUE | Q72: =H72-P72 -> 0
A73: =A72+1 -> 60 | B73: Edgar Rwezaura | C73: 0 | D73: 0 | F73: =SUM(C73:E73) -> 0 | G73: =F73=H73 -> TRUE | Q73: =H73-P73 -> 0
A74: =A73+1 -> 61 | B74: Manase Mushi | C74: 0 | D74: 0 | F74: =SUM(C74:E74) -> 0 | G74: =F74=H74 -> TRUE | Q74: =H74-P74 -> 0
A75: =A74+1 -> 62 | B75: Paul Mikongoti | C75: 0 | D75: 0 | F75: =SUM(C75:E75) -> 0 | G75: =F75=H75 -> TRUE | Q75: =H75-P75 -> 0
A76: =A75+1 -> 63 | B76: Moses Luguru | C76: 0 | D76: 0 | F76: =SUM(C76:E76) -> 0 | G76: =F76=H76 -> TRUE | Q76: =H76-P76 -> 0
A77: =A76+1 -> 64 | B77: Emili Mkwawi | C77: 0 | D77: 0 | F77: =SUM(C77:E77) -> 0 | G77: =F77=H77 -> TRUE | Q77: =H77-P77 -> 0
A78: =A77+1 -> 65 | B78: Salum Hassani | C78: 0 | D78: 0 | F78: =SUM(C78:E78) -> 0 | G78: =F78=H78 -> TRUE | Q78: =H78-P78 -> 0
A79: =A78+1 -> 66 | B79: Richard Makala | C79: 0 | D79: 0 | F79: =SUM(C79:E79) -> 0 | G79: =F79=H79 -> TRUE | Q79: =H79-P79 -> 0
A80: =A79+1 -> 67 | B80: Shabani Salim | C80: 0 | D80: 0 | F80: =SUM(C80:E80) -> 0 | G80: =F80=H80 -> TRUE | Q80: =H80-P80 -> 0
A81: =A80+1 -> 68 | B81: Fabian Sedoyeka | C81: 0 | D81: 0 | F81: =SUM(C81:E81) -> 0 | G81: =F81=H81 -> TRUE | Q81: =H81-P81 -> 0
A82: =A81+1 -> 69 | B82: Piniel Seth | C82: 0 | D82: 0 | F82: =SUM(C82:E82) -> 0 | G82: =F82=H82 -> TRUE | Q82: =H82-P82 -> 0
A83: =A82+1 -> 70 | B83: Beatus Chikoti | C83: 0 | D83: 0 | E83: 0 | F83: =SUM(C83:E83) -> 0 | G83: =F83=H83 -> TRUE | Q83: =H83-P83 -> 0
A84: =A83+1 -> 71 | B84: Nyangusi Laizer | C84: 0 | D84: 0 | F84: =SUM(C84:E84) -> 0 | G84: =F84=H84 -> TRUE | Q84: =H84-P84 -> 0
A85: =A84+1 -> 72 | B85: Anase Minja | C85: 0 | D85: 0 | F85: =SUM(C85:E85) -> 0 | G85: =F85=H85 -> TRUE | Q85: =H85-P85 -> 0
A86: =A85+1 -> 73 | B86: Robert Kitundu | C86: 0 | D86: 0 | F86: =SUM(C86:E86) -> 0 | G86: =F86=H86 -> TRUE | Q86: =H86-P86 -> 0
A87: =A86+1 -> 74 | B87: Msafiri Mwapinga | C87: 0 | D87: 0 | F87: =SUM(C87:E87) -> 0 | G87: =F87=H87 -> TRUE | Q87: =H87-P87 -> 0
G88: =F88=H88 -> TRUE | Q88: =H88-P88 -> 0
B89: TOTAL | C89: =SUM(C9:C88) -> 10821000 | D89: =SUM(D9:D88) -> 4800000 | E89: =SUM(E9:E88) -> 31533000 | F89: =SUM(F9:F88) -> 47154000 | G89: =F89=H89 -> FALSE | H89: =SUM(H9:H88) -> 47854000 | I89: =SUM(I9:I88) -> 11800000 | J89: =SUM(J9:J88) -> 29500000 | K89: =SUM(K9:K88) -> 5900000 | L89: =SUM(L9:L88) -> 5900000 | M89: =SUM(M9:M88) -> 5900000 | N89: =SUM(N9:N88) -> 5900000 | O89: =SUM(O9:O88) -> 5900000 | ... Q89: =SUM(Q9:Q88) -> -22946000
B90: MKOBA MAIN BALANCE | H90: 46524000
B91: MKOBA B BALANCE | H91: =Summary!H91 -> 830000
B92: BANK - NMB | H92: =Summary!H92 -> 500000
B93: TOTAL BALANCE | H93: =SUM(H90:P92) -> 47854000
B97: Mwenyekiti alitoa ufafanuzi wa gharama zilizochangiwa na wanachama waanzilishi kama ifuatavyo: | D97: Allocated accordingly to contributions
B98: a) Gharama za Ukumbi: TZS 75,000. Gharama hizi zilichangiwa na:
B99: (i) Mwenyekiti Ndugu Donald Nsanyiwa – TZS 75,000 | C99: 75000
B100: b) Gharama ya Usafiri kwa Afisa Ushirika: TZS 50,000. Gharama hizi zilichangiwa na:
B101: (i) Ndugu Donald Nsanyiwa – TZS 10,000 | C101: 10000
B102: (ii) Salum Ndolanga – TZS 10,000 | C102: 10000
B103: (iii) Eliashasaria Munisi – TZS 10,000 | C103: 10000
B104: (iv) Nixon Matowo – TZS 10,000 | C104: 10000
B105: (v) Fredrick Ndossi – TZS 10,000 | C105: 10000
B106: JUMLA | C106: =SUM(C99:C105) -> 125000
B107: Ilipendekezwa gharama hizi zitakuwa sehemu ya michango ya viingilio vya wanachama hawa. Endapo kiwango cha kingilio kitakuwa chini ya gharama walizozilipia basi SACCOS itawarudishia salio lao kutoka kwenye Akaunti Kuu ya VIINGILIO.
B108: 2. Michango kutoka kwa Wanachama
B109: Viwango vya michango ya Akiba, Hisa na Kiingilio vitajulikana baada ya kupendekezwa na Bodi ya Uanzilishi na kupigiwa kura na wanachama waanzilishi.
B111: Baada ya hapo utawekwa utaratibu rasmi wa kukusanya michango hii kutoka kwa wanachama.
B113: EXPENSES OF THE FORMATION MEETING OF 12th JULY 2024
B114: 1. Malipo ya Ukumbi | D114: Allocated accordingly to contributions
B115: (i) Donald Nsanyiwa (Mwenyekiti) | C115: 150000
B116: JUMLA | C116: =C106+C115 -> 275000

Sheet DETAILS (sorted)
A1: ID | B1: Member Name | C1: Phone number | D1: Date | E1: Amount 1 | F1: Type | G1: Date | H1: Amount 2 | I1: Type | J1: Date | K1: Amount 3 | L1: Type | M1: Date | N1: Amount 4 | O1: Type | P1: Date | Q1: Amount 5 | R1: Type | S1: Date | T1: Amount 6 | U1: Type | V1: Date | W1: Amount 7 | X1: Type | Y1: Date | Z1: Amount 8 | AA1: Type | AB1: Date | AC1: Amount 9 | AD1: Type | AE1: Date | AF1: Amount 10 | AG1: Type | AH1: Date | AI1: Amount 11 | AJ1: Type | AK1: Date | AL1: Amount 12 | AM1: Type | AN1: Date | AO1: Amount 13 | AP1: Type | AQ1: Date | AR1: Amount 14 | AS1: Type | AT1: Date | AU1: Amount 15 | AV1: Type | AW1: Date | AX1: Amount 16 | AY1: Type | AZ1: Date | BA1: Amount 17 | BB1: Type | BF1: Date | BG1: Amount 18 | BH1: Type | BI1: Grand Total Y1 | BJ1: Total Socio | BK1: NMB | BL1: Total Shares | BM1: Grand Total Y1 | BO1: OCT, 25 | BP1: Amount | BQ1: NOV, 25 | BR1: Amount | BS1: DEC, 25 | BT1: Amount | BU1: JAN, 26 | BV1: Amount | BW1: FEB, 26 | BX1: Amount | BY1: MAR, 26 | BZ1: 46082 | CA1: APR, 26 | CB1: 46113 | CC1: MAY, 26 | CD1: 46143 | CE1: JUN, 26 | CF1: Amount | CG1: JUL, 26 | CH1: Amount | CI1: AUG, 26 | CJ1: Amount | CK1: SEP, 26 | CL1: Amount | CM1: Grand Total Y2 | CN1: TOTAL contributions only Y1+Y2 | CO1: DIVIDEND 1 UTT (Year 1) | CP1: TOTAL UP TO 30 NOV. 25 | CQ1: DIV 2 UTT (Nov. 25) | CR1: DIV 3 (Loan 1) | CS1: TOTAL UP TO JAN 26 | CT1: DIV 4 UTT (Jan 24) | CU1: TOTAL UP TO FEB 26 | CV1: DIV 5 (Loan 2+3) | CW1: TOTAL UP TO MAR 26 | CX1: DIV 6 UTT (15 Apr 26) | CY1: TOTAL UP TO APR 26 | CZ1: LOAN 6+7 Apr 26 (250+500k) | DA1: DIV. 7 UTT 5th May 26 | DB1: TOTAL UP TO MAY 26 | DC1: DIV (loan 8,10, 11,12,5) 1 June 26 | DD1: DIV UTT 6: 2nd June 26 | DE1: TOTAL UP JUNE 2026 | DF1: DIV (loans June 2026) | DG1: DIV UTT 7 JUNE 2026 | DH1: TOTAL UP TO JULY 2026 | DI1: What is in Portal | DJ1: difference | DK1: DIV (Loans July 2026) | DL1: DIV UTT 8 -31 JULY2026 | DM1: TOTAL UP TO AUG 2026 | DN1: DIV (Loans Aug 2026) | DO1: DIV UTT 9 - 31 AUG 2026 | DP1: TOTAL UP TO SEPT 2026 | DQ1: DIV (Loans Sep 2026) | DR1: DIV UTT 9 - 30 SEP 2026 | DS1: CUMMULATIVE TOTAL | DU1: MEMBER NAME | DV1: TOTAL CONTRIBUTION | DW1: PROFIT TODATE | DZ1: TOTAL AMOUNT
A2: ILS24-F00001 | B2: Nsanyiwa Kiloba | C2: 0655281326 | D2: 45355 | E2: 170000 | F2: Shares | G2: 45355 | H2: 80000 | I2: Social | J2: 45361 | K2: 170000 | L2: Shares | M2: 45361 | N2: 90000 | O2: Social | P2: 45370 | R2: Shares | S2: 45655 | T2: 400000 | U2: Shares | V2: 45739 | W2: 100000 | X2: Shares | Y2: 45884 | Z2: 1000000 | AA2: NMB | AB2: 45912 | AC2: 190000 | AD2: NMB | BI2: =E2+H2+K2+N2+Q2+T2+W2+Z2+AC2+AF2+AI2+AO2+AL2+AR2+AU2+AX2+BA2+BG2 -> 2200000 | BJ2: =H2+N2 -> 170000 | BK2: =Z2+AC2 -> 1190000 | BL2: =E2+K2+Q2+T2+W2 -> 840000 | BM2: =BJ2+BL2+BK2 -> 2200000 | BN2: =BM2=BI2 -> TRUE | BO2: 45941 | BP2: =300000+200000 -> 500000 | BQ2: 45981 | BR2: 1000000 | BS2: 46014 | BT2: =100000+1200000 -> 1300000 | BU2: 46041 | BV2: =2000000+2000000 -> 4000000 | BW2: 46058 | BX2: =1000000+300000+500000 -> 1800000 | BY2: 46087 | BZ2: =125000+1200000+300000+700000+1300000+1000000+925225+1500000 -> 7050225 | CA2: 46113 | CB2: =3500000+1500000+3000000+326589 -> 8326589 | CC2: 46164 | CD2: =500000+355488+2000000 -> 2855488 | CE2: 46174 | CF2: =1000000+1500000+225500+500100+1000000+500000 -> 4725600 | CG2: 46212 | CH2: =2200000+2600000+1500000 -> 6300000 | CM2: =BP2+BR2+BT2+BV2+BX2+BZ2+CB2+CD2+CF2+CH2+CJ2+CL2 -> 37857902 | CN2: =BM2+CM2 -> 40057902 | CO2: =BM2/$BM$153*$BM$166 -> 32705.035 | CP2: =BM2+BP2+BR2 -> 3700000 | CQ2: =CP2/$CP$153*$DS$172 -> 48456.297 | CR2: =CP2/$CP$153*$DS$173 -> 73904.694 | CS2: =BM2+BP2+BR2+BT2+BV2 -> 9000000 | CT2: =CS2/$CS$153*$DS$174 -> 128015.05 | CU2: =CS2+BX2 -> 10800000 | CV2: =CU2/$CU$153*$DS$175 -> 366693.52 | CW2: =CU2+BZ2 -> 17850225 | CX2: =CW2/$CW$153*$DS$176 -> 173411.72 | CY2: =CW2+CB2 -> 26176814 | CZ2: =CY2/$CY$153*750000 -> 40449.761 | DA2: =CY2/$CY$153*$DS$185 -> 104062.18 | DB2: =CY2+CD2 -> 29032302 | DC2: =DB2/$DB$153*$DC$154 -> 163616.32 | DD2: =DB2/$DB$153*$DD$154 -> 110783.79 | DE2: =DB2+CF2 -> 33757902 | DF2: =DE2/$DE$153*$DF$154 -> 90512.651 | DG2: =DE2/$DE$153*$DG$154 -> 302221.05 | DH2: =40192734.0611326+1500000 -> 41692734 | DI2: =DH2 -> 41692734 | DJ2: =DH2-DI2 -> 0 | DK2: =DH2/$DH$153*$DK$154 -> 428090.97 | DL2: =DH2/$DH$153*$DL$154 -> 119243.37 | DS2: =CN2+CO2+CQ2+CR2+CT2+CV2+CX2+CZ2+DA2+DC2+DD2+DF2+DG2+DK2+DL2+DN2+DO2+DQ2+DR2 -> 42240068 | DT2: =DS2=CN2+CO2+CQ2+CR2+CT2+CV2+CX2+CZ2+DA2+DC2+DD2+DF2+DG2+DK2+DL2+DN2+DO2+DQ2+DR2 -> TRUE | DU2: =B2 -> Nsanyiwa Kiloba | DV2: =DS2 -> 42240068 | DW2: =DS2-CN2 -> 2182166.4 | DZ2: =BM2+BP2+BR2+BT2+CO2+CQ2+CR2+CT2 -> 5283081.1 | EB2: =BM2+BP2+BR2+BT2+BV2+BX2+CO2+CQ2+CR2+CT2+CV2 -> 11449775
A3: ILS24-F00002 | B3: Werema Msongo | C3: 0764636000 | D3: 45370 | E3: 530000 | F3: Shares | G3: 45370 | H3: 230000 | I3: Social | J3: 45523 | K3: 40000 | L3: Shares | M3: 45884 | N3: 1000000 | O3: NMB | P3: 45885 | Q3: 500000 | R3: UTT | S3: 45905 | T3: 400000 | U3: NMB | V3: 45911 | W3: 500000 | X3: NMB | Y3: 45915 | Z3: 300000 | AA3: NMB | BI3: =E3+H3+K3+N3+Q3+T3+W3+Z3+AC3+AF3+AI3+AO3+AL3+AR3+AU3+AX3+BA3+BG3 -> 3500000 | BJ3: =H3 -> 230000 | BK3: =N3+Q3+T3+W3+Z3 -> 2700000 | BL3: =E3+K3 -> 570000 | BM3: =BJ3+BL3+BK3 -> 3500000 | BN3: =BM3=BI3 -> TRUE | BO3: 45934 | BP3: =1000000+500000+1000000 -> 2500000 | BQ3: 45980 | BR3: =1500000+100000 -> 1600000 | BS3: 46014 | BT3: =3000000-2000000 -> 1000000 | BU3: 46052 | BV3: 200000 | BY3: 46084 | BZ3: =2500000+3000000+1500000+1500000+1000000+1160000+500000+1000000+1000000 -> 13160000 | CG3: 46228 | CH3: =1500000+2000000 -> 3500000 | CM3: =BP3+BR3+BT3+BV3+BX3+BZ3+CB3+CD3+CF3+CH3+CJ3+CL3 -> 21960000 | CN3: =BM3+CM3 -> 25460000 | CO3: =BM3/$BM$153*$BM$166 -> 52030.738 | CP3: =BM3+BP3+BR3 -> 7600000 | CQ3: =CP3/$CP$153*$DS$172 -> 99531.852 | CR3: =CP3/$CP$153*$DS$173 -> 151804.24 | CS3: =BM3+BP3+BR3+BT3+BV3 -> 8800000 | CT3: =CS3/$CS$153*$DS$174 -> 125170.27 | CU3: =CS3+BX3 -> 8800000 | CV3: =CU3/$CU$153*$DS$175 -> 298787.32 | CW3: =CU3+BZ3 -> 21960000 | CX3: =CW3/$CW$153*$DS$176 -> 213337.44 | CY3: =CW3+CB3 -> 21960000 | CZ3: =CY3/$CY$153*750000 -> 33933.723 | DA3: =CY3/$CY$153*$DS$185 -> 87298.842 | DB3: =CY3+CD3 -> 21960000 | DC3: =DB3/$DB$153*$DC$154 -> 123759.2 | DD3: =DB3/$DB$153*$DD$154 -> 83796.73 | DE3: =DB3+CF3 -> 21960000 | DF3: =DE3/$DE$153*$DF$154 -> 58879.779 | DG3: =DE3/$DE$153*$DG$154 -> 196599.13 | DH3: 26984929 | DI3: =DH3 -> 26984929 | DJ3: =DH3-DI3 -> 0 | DK3: =DH3/$DH$153*$DK$154 -> 277074.77 | DL3: =DH3/$DH$153*$DL$154 -> 77178.289 | DS3: =CN3+CO3+CQ3+CR3+CT3+CV3+CX3+CZ3+DA3+DC3+DD3+DF3+DG3+DK3+DL3+DN3+DO3+DQ3+DR3 -> 27339182 | DT3: =DS3=CN3+CO3+CQ3+CR3+CT3+CV3+CX3+CZ3+DA3+DC3+DD3+DF3+DG3+DK3+DL3+DN3+DO3+DQ3+DR3 -> TRUE | DU3: =B3 -> Werema Msongo | DV3: =DS3 -> 27339182 | DW3: =DS3-CN3 -> 1879182.3 | DZ3: =BM3+BP3+BR3+BT3+CO3+CQ3+CR3+CT3 -> 9028537.1 | EB3: =BM3+BP3+BR3+BT3+BV3+BX3+CO3+CQ3+CR3+CT3+CV3 -> 9527324.4
A4: ILS24-F00003 | B4: Norbert Massay | C4: 0754531611 | D4: 45351 | E4: 50000 | F4: Shares | G4: 45351 | H4: 120000 | I4: Shares | J4: 45351 | K4: 30000 | L4: Social | M4: 45353 | N4: 360000 | O4: Shares | P4: 45354 | Q4: 140000 | R4: Social | S4: 45492 | T4: 100000 | U4: Shares | V4: 45648 | W4: 200000 | X4: Shares | Y4: 45727 | Z4: 100000 | AA4: NMB | AB4: 45728 | AC4: 100000 | AD4: NMB | AE4: 45884 | AF4: 700000 | AG4: NMB | BI4: =E4+H4+K4+N4+Q4+T4+W4+Z4+AC4+AF4+AI4+AO4+AL4+AR4+AU4+AX4+BA4+BG4 -> 1900000 | BJ4: =K4+Q4 -> 170000 | BK4: =Z4+AC4+AF4 -> 900000 | BL4: =E4+H4+N4+T4+W4 -> 830000 | BM4: =BJ4+BL4+BK4 -> 1900000 | BN4: =BM4=BI4 -> TRUE | BO4: 45937 | BP4: =300000+300000 -> 600000 | BQ4: 45966 | BR4: =100000+1000000+1000000+600000 -> 2700000 | BS4: 45998 | BT4: =1200000+100000+1300000+500000 -> 3100000 | BU4: 46026 | BV4: =500000+1000000+100000 -> 1600000 | BW4: 46077 | BX4: =500000+1000000 -> 1500000 | BY4: 46083 | BZ4: =1300000+2000000+125000+750000+2200000+1120000+900000+500000+100000+1500000+400000+60000+300000 -> 11255000 | CA4: 46113 | CB4: =3700000+1000000+2000000+150000+320000+524210+900000+1000000+1000000+1000000+5000000 -> 16594210 | CC4: 46143 | CD4: =500000+85927+4000000+500000+1000000+3500000 -> 9585927 | CE4: 46174 | CF4: =500000+26361+1000000+1000000+1000000+300000+3000000+2712072 -> 9538433 | CG4: 46206 | CH4: =500000+500000+10000000+320892+1500000+5000000+1500000+2000000 -> 21320892 | CM4: =BP4+BR4+BT4+BV4+BX4+BZ4+CB4+CD4+CF4+CH4+CJ4+CL4 -> 77794462 | CN4: =BM4+CM4 -> 79694462 | CO4: =BM4/$BM$153*$BM$166 -> 28245.258 | CP4: =BM4+BP4+BR4 -> 5200000 | CQ4: =CP4/$CP$153*$DS$172 -> 68100.741 | CR4: =CP4/$CP$153*$DS$173 -> 103866.06 | CS4: =BM4+BP4+BR4+BT4+BV4 -> 9900000 | CT4: =CS4/$CS$153*$DS$174 -> 140816.55 | CU4: =CS4+BX4 -> 11400000 | CV4: =CU4/$CU$153*$DS$175 -> 387065.39 | CW4: =CU4+BZ4 -> 22655000 | CX4: =CW4/$CW$153*$DS$176 -> 220089.24 | CY4: =CW4+CB4 -> 39249210 | CZ4: =CY4/$CY$153*750000 -> 60649.9 | DA4: =CY4/$CY$153*$DS$185 -> 156029.63 | DB4: =CY4+CD4 -> 48835137 | DC4: =DB4/$DB$153*$DC$154 -> 275218.46 | DD4: =DB4/$DB$153*$DD$154 -> 186349.03 | DE4: =DB4+CF4 -> 58373570 | DF4: =DE4/$DE$153*$DF$154 -> 156512.88 | DG4: =DE4/$DE$153*$DG$154 -> 522595.31 | DH4: 82000000 | DI4: =DH4 -> 82000000 | DJ4: =DH4-DI4 -> 0 | DK4: =DH4/$DH$153*$DK$154 -> 841956.29 | DL4: =DH4/$DH$153*$DL$154 -> 234524.23 | DS4: =CN4+CO4+CQ4+CR4+CT4+CV4+CX4+CZ4+DA4+DC4+DD4+DF4+DG4+DK4+DL4+DN4+DO4+DQ4+DR4 -> 83076481 | DT4: =DS4=CN4+CO4+CQ4+CR4+CT4+CV4+CX4+CZ4+DA4+DC4+DD4+DF4+DG4+DK4+DL4+DN4+DO4+DQ4+DR4 -> TRUE | DU4: =B4 -> Norbert Massay | DV4: =DS4 -> 83076481 | DW4: =DS4-CN4 -> 3382019 | DZ4: =BM4+BP4+BR4+BT4+CO4+CQ4+CR4+CT4 -> 8641028.6 | EB4: =BM4+BP4+BR4+BT4+BV4+BX4+CO4+CQ4+CR4+CT4+CV4 -> 12128094 | ED4: 320891.55
A5: ILS24-F00004 | B5: Everest Exavery Francisco | C5: 0742997323 | D5: 45352 | E5: 90000 | F5: Shares | G5: 45352 | H5: 10000 | I5: Social | J5: 45353 | K5: 50000 | L5: Shares | M5: 45353 | N5: 30000 | O5: Social | P5: 45529 | Q5: 100000 | R5: Shares | S5: 45530 | T5: 100000 | U5: Shares | V5: 45657 | W5: 450000 | X5: Shares | Y5: 45657 | Z5: 170000 | AA5: Shares | BI5: =E5+H5+K5+N5+Q5+T5+W5+Z5+AC5+AF5+AI5+AO5+AL5+AR5+AU5+AX5+BA5+BG5 -> 1000000 | BJ5: =H5+N5 -> 40000 | BL5: =E5+K5+Q5+T5+W5+Z5 -> 960000 | BM5: =BJ5+BL5+BK5 -> 1000000 | BN5: =BM5=BI5 -> TRUE | BO5: 45951 | BP5: 200000 | BR5: 0 | BU5: 46049 | BV5: =450000+700000+200000+250000 -> 1600000 | BW5: 46059 | BX5: =100000+150000 -> 250000 | BY5: 46082 | BZ5: =200000+150000+150000+100000+160000 -> 760000 | CA5: 46133 | CB5: 150000 | CC5: 46164 | CD5: =500000+300000 -> 800000 | CE5: 46201 | CF5: 120000 | CG5: 46227 | CH5: 1000000 | CM5: =BP5+BR5+BT5+BV5+BX5+BZ5+CB5+CD5+CF5+CH5+CJ5+CL5 -> 4880000 | CN5: =BM5+CM5 -> 5880000 | CO5: =BM5/$BM$153*$BM$166 -> 14865.925 | CP5: =BM5+BP5+BR5 -> 1200000 | CQ5: =CP5/$CP$153*$DS$172 -> 15715.556 | CR5: =CP5/$CP$153*$DS$173 -> 23969.09 | CS5: =BM5+BP5+BR5+BT5+BV5 -> 2800000 | CT5: =CS5/$CS$153*$DS$174 -> 39826.904 | CU5: =CS5+BX5 -> 3050000 | CV5: =CU5/$CU$153*$DS$175 -> 103556.97 | CW5: =CU5+BZ5 -> 3810000 | CX5: =CW5/$CW$153*$DS$176 -> 37013.463 | CY5: =CW5+CB5 -> 3960000 | CZ5: =CY5/$CY$153*750000 -> 6119.1959 | DA5: =CY5/$CY$153*$DS$185 -> 15742.414 | DB5: =CY5+CD5 -> 4760000 | DC5: =DB5/$DB$153*$DC$154 -> 26825.764 | DD5: =DB5/$DB$153*$DD$154 -> 18163.59 | DE5: =DB5+CF5 -> 4880000 | DF5: =DE5/$DE$153*$DF$154 -> 13084.395 | DG5: =DE5/$DE$153*$DG$154 -> 43688.696 | DH5: 6238572 | DI5: =DH5 -> 6238572 | DJ5: =DH5-DI5 -> 0 | DK5: =DH5/$DH$153*$DK$154 -> 64056.157 | DL5: =DH5/$DH$153*$DL$154 -> 17842.638 | DS5: =CN5+CO5+CQ5+CR5+CT5+CV5+CX5+CZ5+DA5+DC5+DD5+DF5+DG5+DK5+DL5+DN5+DO5+DQ5+DR5 -> 6320470.8 | DT5: =DS5=CN5+CO5+CQ5+CR5+CT5+CV5+CX5+CZ5+DA5+DC5+DD5+DF5+DG5+DK5+DL5+DN5+DO5+DQ5+DR5 -> TRUE | DU5: =B5 -> Everest Exavery Francisco | DV5: =DS5 -> 6320470.8 | DW5: =DS5-CN5 -> 440470.75 | DZ5: =BM5+BP5+BR5+BT5+CO5+CQ5+CR5+CT5 -> 1294377.5 | EB5: =BM5+BP5+BR5+BT5+BV5+BX5+CO5+CQ5+CR5+CT5+CV5 -> 3247934.4
A6: ILS24-F00005 | B6: Elianshasaria Munisi | C6: 0784662615 | D6: 45354 | E6: 150000 | F6: Shares | G6: 45354 | H6: 70000 | I6: Social | J6: 45521 | K6: 900000 | L6: Shares | M6: 45650 | N6: 100000 | O6: Shares | P6: 45795 | Q6: 180000 | R6: Shares | S6: 45821 | T6: 200000 | U6: Shares | V6: 45884 | W6: 200000 | X6: NMB | Y6: 45910 | Z6: 100000 | AA6: NMB | AB6: 45930 | AC6: 100000 | AD6: NMB | BI6: =E6+H6+K6+N6+Q6+T6+W6+Z6+AC6+AF6+AI6+AO6+AL6+AR6+AU6+AX6+BA6+BG6 -> 2000000 | BJ6: =H6 -> 70000 | BK6: =W6+Z6+AC6 -> 400000 | BL6: =E6+K6+N6+Q6+T6 -> 1530000 | BM6: =BJ6+BL6+BK6 -> 2000000 | BN6: =BM6=BI6 -> TRUE | BO6: 45936 | BP6: =400000+200000+400000 -> 1000000 | BR6: 0 | BU6: 46053 | BV6: 1000000 | BW6: 46072 | BX6: =1000000+1000000+1000000 -> 3000000 | BY6: 46098 | BZ6: =1000000+1000000+1000000 -> 3000000 | CA6: 46140 | CB6: 100000 | CC6: 46172 | CD6: 100000 | CE6: 46203 | CF6: 200000 | CG6: 46226 | CH6: =1000000+500000+100000 -> 1600000 | CM6: =BP6+BR6+BT6+BV6+BX6+BZ6+CB6+CD6+CF6+CH6+CJ6+CL6 -> 10000000 | CN6: =BM6+CM6 -> 12000000 | CO6: =BM6/$BM$153*$BM$166 -> 29731.85 | CP6: =BM6+BP6+BR6 -> 3000000 | CQ6: =CP6/$CP$153*$DS$172 -> 39288.889 | CR6: =CP6/$CP$153*$DS$173 -> 59922.725 | CS6: =BM6+BP6+BR6+BT6+BV6 -> 4000000 | CT6: =CS6/$CS$153*$DS$174 -> 56895.577 | CU6: =CS6+BX6 -> 7000000 | CV6: =CU6/$CU$153*$DS$175 -> 237671.73 | CW6: =CU6+BZ6 -> 10000000 | CX6: =CW6/$CW$153*$DS$176 -> 97148.196 | CY6: =CW6+CB6 -> 10100000 | CZ6: =CY6/$CY$153*750000 -> 15607.04 | DA6: =CY6/$CY$153*$DS$185 -> 40151.107 | DB6: =CY6+CD6 -> 10200000 | DC6: =DB6/$DB$153*$DC$154 -> 57483.779 | DD6: =DB6/$DB$153*$DD$154 -> 38921.978 | DE6: =DB6+CF6 -> 10400000 | DF6: =DE6/$DE$153*$DF$154 -> 27884.777 | DG6: =DE6/$DE$153*$DG$154 -> 93107.056 | DH6: 12793815 | DI6: =DH6 -> 12793815 | DJ6: =DH6-DI6 -> 0 | DK6: =DH6/$DH$153*$DK$154 -> 131363.81 | DL6: =DH6/$DH$153*$DL$154 -> 36590.97 | DS6: =CN6+CO6+CQ6+CR6+CT6+CV6+CX6+CZ6+DA6+DC6+DD6+DF6+DG6+DK6+DL6+DN6+DO6+DQ6+DR6 -> 12961769 | DT6: =DS6=CN6+CO6+CQ6+CR6+CT6+CV6+CX6+CZ6+DA6+DC6+DD6+DF6+DG6+DK6+DL6+DN6+DO6+DQ6+DR6 -> TRUE | DU6: =B6 -> Elianshasaria Munisi | DV6: =DS6 -> 12961769 | DW6: =DS6-CN6 -> 961769.49 | DZ6: =BM6+BP6+BR6+BT6+CO6+CQ6+CR6+CT6 -> 3185839 | EB6: =BM6+BP6+BR6+BT6+BV6+BX6+CO6+CQ6+CR6+CT6+CV6 -> 7423510.8
A7: ILS24-F00006 | B7: Emmanuel Matee | C7: 0745802050 | D7: 45352 | E7: 10000 | F7: Social | G7: 45353 | H7: 20000 | I7: Social | J7: 45353 | K7: 120000 | L7: Shares | M7: 45353 | N7: 50000 | O7: Shares | P7: 45354 | Q7: 50000 | R7: Social | S7: 45394 | T7: 30000 | U7: Social | V7: 45394 | W7: 120000 | X7: Shares | Y7: 45486 | Z7: 20000 | AA7: Social | AB7: 45486 | AC7: 80000 | AD7: Shares | AE7: 45492 | AF7: 40000 | AG7: Social | AH7: 45492 | AI7: =160000+80000 -> 240000 | AJ7: Shares | AK7: 45496 | AL7: 20000 | AM7: Social | AN7: 45648 | AO7: 200000 | AP7: Shares | AQ7: 45690 | AR7: 200000 | AS7: Shares | AT7: 45703 | AU7: 100000 | AV7: Shares | AW7: 45795 | AX7: 100000 | AY7: Shares | AZ7: 45835 | BA7: 100000 | BB7: Shares | BC7: 45884 | BD7: 200000 | BE7: NMB | BF7: 45911 | BG7: 300000 | BH7: NMB | BI7: =E7+H7+K7+N7+Q7+T7+W7+Z7+AC7+AF7+AI7+AO7+AL7+AR7+AU7+AX7+BA7+BG7+BD7 -> 2000000 | BJ7: =E7+H7+Q7+T7+Z7+AF7+AL7 -> 190000 | BK7: =BD7+BG7 -> 500000 | BL7: =K7+N7+W7+AC7+AI7+AO7+AR7+AU7+AX7+BA7 -> 1310000 | BM7: =BJ7+BL7+BK7 -> 2000000 | BN7: =BM7=BI7 -> TRUE | BO7: 45936 | BP7: =400000+200000 -> 600000 | BQ7: 45967 | BR7: =200000+200000 -> 400000 | BS7: 46001 | BT7: 200000 | BU7: 46026 | BV7: =500000+671957 -> 1171957 | BY7: 46083 | BZ7: =936913+700000+151559+2500000 -> 4288472 | CA7: 46142 | CB7: 200000 | CC7: 46165 | CD7: =900000+966950 -> 1866950 | CE7: 46198 | CF7: =4998610+4999999 -> 9998609 | CG7: 46216 | CH7: =458878+1000000 -> 1458878 | CM7: =BP7+BR7+BT7+BV7+BX7+BZ7+CB7+CD7+CF7+CH7+CJ7+CL7 -> 20184866 | CN7: =BM7+CM7 -> 22184866 | CO7: =BM7/$BM$153*$BM$166 -> 29731.85 | CP7: =BM7+BP7+BR7 -> 3000000 | CQ7: =CP7/$CP$153*$DS$172 -> 39288.889 | CR7: =CP7/$CP$153*$DS$173 -> 59922.725 | CS7: =BM7+BP7+BR7+BT7+BV7 -> 4371957 | CT7: =CS7/$CS$153*$DS$174 -> 62186.255 | CU7: =CS7+BX7 -> 4371957 | CV7: =CU7/$CU$153*$DS$175 -> 148441.51 | CW7: =CU7+BZ7 -> 8660429 | CX7: =CW7/$CW$153*$DS$176 -> 84134.506 | CY7: =CW7+CB7 -> 8860429 | CZ7: =CY7/$CY$153*750000 -> 13691.591 | DA7: =CY7/$CY$153*$DS$185 -> 35223.369 | DB7: =CY7+CD7 -> 10727379 | DC7: =DB7/$DB$153*$DC$154 -> 60455.911 | DD7: =DB7/$DB$153*$DD$154 -> 40934.394 | DE7: =DB7+CF7 -> 20725988 | DF7: =DE7/$DE$153*$DF$154 -> 55571.111 | DG7: =DE7/$DE$153*$DG$154 -> 185551.51 | DH7: 23000000 | DI7: =DH7 -> 23000000 | DJ7: =DH7-DI7 -> 0 | DK7: =DH7/$DH$153*$DK$154 -> 236158.47 | DL7: =DH7/$DH$153*$DL$154 -> 65781.185 | DS7: =CN7+CO7+CQ7+CR7+CT7+CV7+CX7+CZ7+DA7+DC7+DD7+DF7+DG7+DK7+DL7+DN7+DO7+DQ7+DR7 -> 23301939 | DT7: =DS7=CN7+CO7+CQ7+CR7+CT7+CV7+CX7+CZ7+DA7+DC7+DD7+DF7+DG7+DK7+DL7+DN7+DO7+DQ7+DR7 -> TRUE | DU7: =B7 -> Emmanuel Matee | DV7: =DS7 -> 23301939 | DW7: =DS7-CN7 -> 1117073.3 | DZ7: =BM7+BP7+BR7+BT7+CO7+CQ7+CR7+CT7 -> 3391129.7 | EB7: =BM7+BP7+BR7+BT7+BV7+BX7+CO7+CQ7+CR7+CT7+CV7 -> 4711528.2
A8: ILS24-F00007 | B8: Erick Kitali | C8: 0713858844 | D8: 45357 | E8: 80000 | F8: Social | G8: 45358 | H8: 170000 | I8: Shares | J8: 45525 | K8: 550000 | L8: Shares | M8: 45648 | N8: 200000 | O8: Shares | P8: 45727 | Q8: 300000 | R8: NMB | S8: 45909 | T8: 1000000 | U8: NMB | BI8: =E8+H8+K8+N8+Q8+T8+W8+Z8+AC8+AF8+AI8+AO8+AL8+AR8+AU8+AX8+BA8+BG8 -> 2300000 | BJ8: =E8 -> 80000 | BK8: =Q8+T8 -> 1300000 | BL8: =H8+K8+N8 -> 920000 | BM8: =BJ8+BL8+BK8 -> 2300000 | BN8: =BM8=BI8 -> TRUE | BO8: 45937 | BP8: 200000 | BQ8: 45972 | BR8: 270000 | BS8: 45998 | BT8: =1000000+1195808 -> 2195808 | BU8: 46052 | BV8: 408395 | BW8: 46072 | BX8: =423558 -> 423558 | BY8: 46082 | BZ8: =2000000+2000000+4803148+1000000 -> 9803148 | CA8: 46123 | CB8: =3000000+849791 -> 3849791 | CC8: 46143 | CD8: =2998649+1892620 -> 4891269 | CE8: 46174 | CF8: =500000+263914+4000000+2000000 -> 6763914 | CG8: 46217 | CH8: =2644136+1000000+4200000 -> 7844136 | CM8: =BP8+BR8+BT8+BV8+BX8+BZ8+CB8+CD8+CF8+CH8+CJ8+CL8 -> 36650019 | CN8: =BM8+CM8 -> 38950019 | CO8: =BM8/$BM$153*$BM$166 -> 34191.628 | CP8: =BM8+BP8+BR8 -> 2770000 | CQ8: =CP8/$CP$153*$DS$172 -> 36276.741 | CR8: =CP8/$CP$153*$DS$173 -> 55328.649 | CS8: =BM8+BP8+BR8+BT8+BV8 -> 5374203 | CT8: =CS8/$CS$153*$DS$174 -> 76442.096 | CU8: =CS8+BX8 -> 5797761 | CV8: =CU8/$CU$153*$DS$175 -> 196851.98 | CW8: =CU8+BZ8 -> 15600909 | CX8: =CW8/$CW$153*$DS$176 -> 151560.02 | CY8: =CW8+CB8 -> 19450700 | CZ8: =CY8/$CY$153*750000 -> 30056.223 | DA8: =CY8/$CY$153*$DS$185 -> 77323.478 | DB8: =CY8+CD8 -> 24341969 | DC8: =DB8/$DB$153*$DC$154 -> 137183.17 | DD8: =DB8/$DB$153*$DD$154 -> 92886.038 | DE8: =DB8+CF8 -> 31105883 | DF8: =DE8/$DE$153*$DF$154 -> 83401.982 | DG8: =DE8/$DE$153*$DG$154 -> 278478.58 | DH8: 40200000 | DI8: =DH8 -> 40200000 | DJ8: =DH8-DI8 -> 0 | DK8: =DH8/$DH$153*$DK$154 -> 412763.93 | DL8: =DH8/$DH$153*$DL$154 -> 114974.07 | DS8: =CN8+CO8+CQ8+CR8+CT8+CV8+CX8+CZ8+DA8+DC8+DD8+DF8+DG8+DK8+DL8+DN8+DO8+DQ8+DR8 -> 40727738 | DT8: =DS8=CN8+CO8+CQ8+CR8+CT8+CV8+CX8+CZ8+DA8+DC8+DD8+DF8+DG8+DK8+DL8+DN8+DO8+DQ8+DR8 -> TRUE | DU8: =B8 -> Erick Kitali | DV8: =DS8 -> 40727738 | DW8: =DS8-CN8 -> 1777718.6 | DZ8: =BM8+BP8+BR8+BT8+CO8+CQ8+CR8+CT8 -> 5168047.1 | EB8: =BM8+BP8+BR8+BT8+BV8+BX8+CO8+CQ8+CR8+CT8+CV8 -> 6196852.1
A9: ILS24-F00008 | B9: Felix Daniel Kinabo | C9: 0713224716 | D9: 45348 | E9: 1000 | F9: Opening | G9: 45352 | H9: 10000 | I9: Social | J9: 45352 | K9: 60000 | L9: Shares | M9: 45355 | N9: 70000 | O9: Shares | BI9: =E9+H9+K9+N9+Q9+T9+W9+Z9+AC9+AF9+AI9+AO9+AL9+AR9+AU9+AX9+BA9+BG9 -> 141000 | BJ9: =E9+H9 -> 11000 | BL9: =K9+N9 -> 130000 | BM9: =BJ9+BL9+BK9 -> 141000 | BN9: =BM9=BI9 -> TRUE | BP9: 0 | BR9: 0 | BY9: 46111 | BZ9: 2000000 | CA9: 46128 | CB9: 550000 | CC9: 46148 | CD9: 250000 | CE9: 46175 | CF9: 282000 | CM9: =BP9+BR9+BT9+BV9+BX9+BZ9+CB9+CD9+CF9+CH9+CJ9+CL9 -> 3082000 | CN9: =BM9+CM9 -> 3223000 | CO9: =BM9/$BM$153*$BM$166 -> 2096.0954 | CP9: =BM9+BP9+BR9 -> 141000 | CQ9: =CP9/$CP$153*$DS$172 -> 1846.5778 | CR9: =CP9/$CP$153*$DS$173 -> 2816.3681 | CS9: =BM9+BP9+BR9+BT9+BV9 -> 141000 | CT9: =CS9/$CS$153*$DS$174 -> 2005.5691 | CU9: =CS9+BX9 -> 141000 | CV9: =CU9/$CU$153*$DS$175 -> 4787.3877 | CW9: =CU9+BZ9 -> 2141000 | CX9: =CW9/$CW$153*$DS$176 -> 20799.429 | CY9: =CW9+CB9 -> 2691000 | CZ9: =CY9/$CY$153*750000 -> 4158.2718 | DA9: =CY9/$CY$153*$DS$185 -> 10697.686 | DB9: =CY9+CD9 -> 2941000 | DC9: =DB9/$DB$153*$DC$154 -> 16574.49 | DD9: =DB9/$DB$153*$DD$154 -> 11222.504 | DE9: =DB9+CF9 -> 3223000 | DF9: =DE9/$DE$153*$DF$154 -> 8641.5996 | DG9: =DE9/$DE$153*$DG$154 -> 28854.235 | DH9: 3337500.2 | DI9: =DH9 -> 3337500.2 | DJ9: =DH9-DI9 -> 0 | DK9: =DH9/$DH$153*$DK$154 -> 34268.65 | DL9: =DH9/$DH$153*$DL$154 -> 9545.4227 | DS9: =CN9+CO9+CQ9+CR9+CT9+CV9+CX9+CZ9+DA9+DC9+DD9+DF9+DG9+DK9+DL9+DN9+DO9+DQ9+DR9 -> 3381314.3 | DT9: =DS9=CN9+CO9+CQ9+CR9+CT9+CV9+CX9+CZ9+DA9+DC9+DD9+DF9+DG9+DK9+DL9+DN9+DO9+DQ9+DR9 -> TRUE | DU9: =B9 -> Felix Daniel Kinabo | DV9: =DS9 -> 3381314.3 | DW9: =DS9-CN9 -> 158314.29 | DZ9: =BM9+BP9+BR9+BT9+CO9+CQ9+CR9+CT9 -> 149764.61 | EB9: =BM9+BP9+BR9+BT9+BV9+BX9+CO9+CQ9+CR9+CT9+CV9 -> 154552
A10: ILS24-F00009 | B10: Gideon Gabriel | C10: 0754046688 | D10: 45369 | E10: 80000 | F10: Social | G10: 45369 | H10: 90000 | I10: Shares | J10: 45683 | K10: 200000 | L10: Shares | M10: 45775 | N10: 200000 | O10: NMB | P10: 45884 | Q10: 200000 | R10: NMB | S10: 45895 | T10: 200000 | U10: NMB | V10: 45899 | W10: 200000 | X10: NMB | BI10: =E10+H10+K10+N10+Q10+T10+W10+Z10+AC10+AF10+AI10+AO10+AL10+AR10+AU10+AX10+BA10+BG10 -> 1170000 | BJ10: =E10 -> 80000 | BK10: =N10+Q10+T10+W10 -> 800000 | BL10: =H10+K10 -> 290000 | BM10: =BJ10+BL10+BK10 -> 1170000 | BN10: =BM10=BI10 -> TRUE | BO10: 45957 | BP10: 200000 | BR10: 0 | CE10: 46203 | CF10: 2000000 | CM10: =BP10+BR10+BT10+BV10+BX10+BZ10+CB10+CD10+CF10+CH10+CJ10+CL10 -> 2200000 | CN10: =BM10+CM10 -> 3370000 | CO10: =BM10/$BM$153*$BM$166 -> 17393.132 | CP10: =BM10+BP10+BR10 -> 1370000 | CQ10: =CP10/$CP$153*$DS$172 -> 17941.926 | CR10: =CP10/$CP$153*$DS$173 -> 27364.711 | CS10: =BM10+BP10+BR10+BT10+BV10 -> 1370000 | CT10: =CS10/$CS$153*$DS$174 -> 19486.735 | CU10: =CS10+BX10 -> 1370000 | CV10: =CU10/$CU$153*$DS$175 -> 46515.753 | CW10: =CU10+BZ10 -> 1370000 | CX10: =CW10/$CW$153*$DS$176 -> 13309.303 | CY10: =CW10+CB10 -> 1370000 | CZ10: =CY10/$CY$153*750000 -> 2116.9945 | DA10: =CY10/$CY$153*$DS$185 -> 5446.2392 | DB10: =CY10+CD10 -> 1370000 | DC10: =DB10/$DB$153*$DC$154 -> 7720.8606 | DD10: =DB10/$DB$153*$DD$154 -> 5227.7559 | DE10: =DB10+CF10 -> 3370000 | DF10: =DE10/$DE$153*$DF$154 -> 9035.7402 | DG10: =DE10/$DE$153*$DG$154 -> 30170.267 | DH10: 3571729.4 | DI10: =DH10 -> 3571729.4 | DJ10: =DH10-DI10 -> 0 | DK10: =DH10/$DH$153*$DK$154 -> 36673.659 | DL10: =DH10/$DH$153*$DL$154 -> 10215.33 | DS10: =CN10+CO10+CQ10+CR10+CT10+CV10+CX10+CZ10+DA10+DC10+DD10+DF10+DG10+DK10+DL10+DN10+DO10+DQ10+DR10 -> 3618618.4 | DT10: =DS10=CN10+CO10+CQ10+CR10+CT10+CV10+CX10+CZ10+DA10+DC10+DD10+DF10+DG10+DK10+DL10+DN10+DO10+DQ10+DR10 -> TRUE | DU10: =B10 -> Gideon Gabriel | DV10: =DS10 -> 3618618.4 | DW10: =DS10-CN10 -> 248618.41 | DZ10: =BM10+BP10+BR10+BT10+CO10+CQ10+CR10+CT10 -> 1452186.5 | EB10: =BM10+BP10+BR10+BT10+BV10+BX10+CO10+CQ10+CR10+CT10+CV10 -> 1498702.3
A11: ILS24-F00010 | B11: Mosses Makoko | C11: 0754710473 | D11: 45355 | E11: 170000 | F11: Social | G11: 45355 | H11: 170000 | I11: Shares | J11: 45530 | K11: 460000 | L11: Shares | M11: 45690 | N11: 200000 | O11: Shares | P11: 45912 | Q11: 1000000 | R11: NMB | BI11: =E11+H11+K11+N11+Q11+T11+W11+Z11+AC11+AF11+AI11+AO11+AL11+AR11+AU11+AX11+BA11+BG11 -> 2000000 | BJ11: =E11 -> 170000 | BK11: =Q11 -> 1000000 | BL11: =H11+K11+N11 -> 830000 | BM11: =BJ11+BL11+BK11 -> 2000000 | BN11: =BM11=BI11 -> TRUE | BO11: 45954 | BP11: 1000000 | BY11: 46084 | BZ11: =2000000+2000000+3000000 -> 7000000 | CA11: 46141 | CB11: =2000000+3000000 -> 5000000 | CC11: 46170 | CD11: =3000000+2000000 -> 5000000 | CE11: 46198 | CF11: =3000000+2000000 -> 5000000 | CG11: 46227 | CH11: =3000000+2000000 -> 5000000 | CM11: =BP11+BR11+BT11+BV11+BX11+BZ11+CB11+CD11+CF11+CH11+CJ11+CL11 -> 28000000 | CN11: =BM11+CM11 -> 30000000 | CO11: =BM11/$BM$153*$BM$166 -> 29731.85 | CP11: =BM11+BP11+BR11 -> 3000000 | CQ11: =CP11/$CP$153*$DS$172 -> 39288.889 | CR11: =CP11/$CP$153*$DS$173 -> 59922.725 | CS11: =BM11+BP11+BR11+BT11+BV11 -> 3000000 | CT11: =CS11/$CS$153*$DS$174 -> 42671.683 | CU11: =CS11+BX11 -> 3000000 | CV11: =CU11/$CU$153*$DS$175 -> 101859.31 | CW11: =CU11+BZ11 -> 10000000 | CX11: =CW11/$CW$153*$DS$176 -> 97148.196 | CY11: =CW11+CB11 -> 15000000 | CZ11: =CY11/$CY$153*750000 -> 23178.772 | DA11: =CY11/$CY$153*$DS$185 -> 59630.356 | DB11: =CY11+CD11 -> 20000000 | DC11: =DB11/$DB$153*$DC$154 -> 112713.29 | DD11: =DB11/$DB$153*$DD$154 -> 76317.605 | DE11: =DB11+CF11 -> 25000000 | DF11: =DE11/$DE$153*$DF$154 -> 67030.714 | DG11: =DE11/$DE$153*$DG$154 -> 223815.04 | DH11: 30933308 | DI11: =DH11 -> 30933308 | DJ11: =DH11-DI11 -> 0 | DK11: =DH11/$DH$153*$DK$154 -> 317615.77 | DL11: =DH11/$DH$153*$DL$154 -> 88470.858 | DS11: =CN11+CO11+CQ11+CR11+CT11+CV11+CX11+CZ11+DA11+DC11+DD11+DF11+DG11+DK11+DL11+DN11+DO11+DQ11+DR11 -> 31339395 | DT11: =DS11=CN11+CO11+CQ11+CR11+CT11+CV11+CX11+CZ11+DA11+DC11+DD11+DF11+DG11+DK11+DL11+DN11+DO11+DQ11+DR11 -> TRUE | DU11: =B11 -> Mosses Makoko | DV11: =DS11 -> 31339395 | DW11: =DS11-CN11 -> 1339395.1 | DZ11: =BM11+BP11+BR11+BT11+CO11+CQ11+CR11+CT11 -> 3171615.1 | EB11: =BM11+BP11+BR11+BT11+BV11+BX11+CO11+CQ11+CR11+CT11+CV11 -> 3273474.5
A12: ILS24-F00011 | B12: Jacob Shabani Mangu | C12: 0754499843 | D12: 45355 | E12: 100000 | F12: Shares | G12: 45359 | H12: 190000 | I12: Shares | J12: 45359 | K12: 110000 | L12: Social | M12: 45359 | N12: 60000 | O12: Social | P12: 45421 | Q12: 140000 | R12: Shares | S12: 45485 | T12: 140000 | U12: Shares | V12: 45504 | W12: 60000 | X12: Shares | Y12: 45649 | Z12: 200000 | AA12: Shares | AB12: 45702 | AC12: 300000 | AD12: Shares | AE12: 45712 | AF12: 300000 | AG12: Shares | AH12: 45740 | AI12: 200000 | AJ12: Shares | AK12: 45778 | AL12: 100000 | AM12: NMB | AN12: 45797 | AO12: 100000 | AP12: NMB | AQ12: 45833 | AR12: 100000 | AS12: Shares | AT12: 45869 | AU12: 100000 | AV12: NMB | AW12: 45895 | AX12: 100000 | AY12: NMB | AZ12: 45918 | BA12: 100000 | BB12: NMB | BI12: =E12+H12+K12+N12+Q12+T12+W12+Z12+AC12+AF12+AI12+AO12+AL12+AR12+AU12+AX12+BA12+BG12 -> 2400000 | BJ12: =K12+N12 -> 170000 | BK12: =AL12+AO12+AU12+AX12+BA12 -> 500000 | BL12: =E12+H12+Q12+T12+W12+Z12+AC12+AF12+AI12+AR12 -> 1730000 | BM12: =BJ12+BL12+BK12 -> 2400000 | BN12: =BM12=BI12 -> TRUE | BO12: 45955 | BP12: 300000 | BR12: 0 | BS12: 46011 | BT12: 100000 | BU12: 46034 | BV12: =400000+600000+600000 -> 1600000 | BW12: 46070 | BX12: =500000+912446 -> 1412446 | BY12: 46086 | BZ12: =1000000+1402650+500000 -> 2902650 | CA12: 46122 | CB12: =1100000+1015334+800000 -> 2915334 | CC12: 46149 | CD12: =635793+1500000+700000 -> 2835793 | CE12: 46177 | CF12: =559696+1003576+500000 -> 2063272 | CG12: 46216 | CH12: =807698+1300000+800000+200000+500000 -> 3607698 | CM12: =BP12+BR12+BT12+BV12+BX12+BZ12+CB12+CD12+CF12+CH12+CJ12+CL12 -> 17737193 | CN12: =BM12+CM12 -> 20137193 | CO12: =BM12/$BM$153*$BM$166 -> 35678.22 | CP12: =BM12+BP12+BR12 -> 2700000 | CQ12: =CP12/$CP$153*$DS$172 -> 35360 | CR12: =CP12/$CP$153*$DS$173 -> 53930.452 | CS12: =BM12+BP12+BR12+BT12+BV12 -> 4400000 | CT12: =CS12/$CS$153*$DS$174 -> 62585.135 | CU12: =CS12+BX12 -> 5812446 | CV12: =CU12/$CU$153*$DS$175 -> 197350.58 | CW12: =CU12+BZ12 -> 8715096 | CX12: =CW12/$CW$153*$DS$176 -> 84665.586 | CY12: =CW12+CB12 -> 11630430 | CZ12: =CY12/$CY$153*750000 -> 17971.939 | DA12: =CY12/$CY$153*$DS$185 -> 46235.112 | DB12: =CY12+CD12 -> 14466223 | DC12: =DB12/$DB$153*$DC$154 -> 81526.782 | DD12: =DB12/$DB$153*$DD$154 -> 55201.374 | DE12: =DB12+CF12 -> 16529495 | DF12: =DE12/$DE$153*$DF$154 -> 44319.354 | DG12: =DE12/$DE$153*$DG$154 -> 147981.98 | DH12: 21000000 | DI12: 21000000 | DJ12: =DH12-DI12 -> -0.47835456 | DK12: =DH12/$DH$153*$DK$154 -> 215622.95 | DL12: =DH12/$DH$153*$DL$154 -> 60061.082 | DS12: =CN12+CO12+CQ12+CR12+CT12+CV12+CX12+CZ12+DA12+DC12+DD12+DF12+DG12+DK12+DL12+DN12+DO12+DQ12+DR12 -> 21275684 | DT12: =DS12=CN12+CO12+CQ12+CR12+CT12+CV12+CX12+CZ12+DA12+DC12+DD12+DF12+DG12+DK12+DL12+DN12+DO12+DQ12+DR12 -> TRUE | DU12: =B12 -> Jacob Shabani Mangu | DV12: =DS12 -> 21275684 | DW12: =DS12-CN12 -> 1138490.5 | DZ12: =BM12+BP12+BR12+BT12+CO12+CQ12+CR12+CT12 -> 2987553.8 | EB12: =BM12+BP12+BR12+BT12+BV12+BX12+CO12+CQ12+CR12+CT12+CV12 -> 6197350.4
A13: ILS24-F00012 | B13: Mlindwa Kashindye | C13: 0784280224 | D13: 45369 | E13: 150000 | F13: Social | G13: 45370 | H13: 20000 | I13: Social | J13: 45370 | K13: 200000 | L13: Shares | M13: 45382 | N13: 130000 | O13: Shares | P13: 45525 | Q13: 300000 | R13: Shares | S13: 45635 | T13: 200000 | U13: Shares | V13: 45659 | W13: 250000 | X13: Shares | Y13: 45886 | Z13: 500000 | AA13: NMB | AB13: 45909 | AC13: 150000 | AD13: NMB | BI13: =E13+H13+K13+N13+Q13+T13+W13+Z13+AC13+AF13+AI13+AO13+AL13+AR13+AU13+AX13+BA13+BG13 -> 1900000 | BJ13: =E13+H13 -> 170000 | BK13: =Z13+AC13 -> 650000 | BL13: =K13+N13+Q13+T13+W13 -> 1080000 | BM13: =BJ13+BL13+BK13 -> 1900000 | BN13: =BM13=BI13 -> TRUE | BO13: 45951 | BP13: =600000+100000 -> 700000 | BQ13: 45990 | BR13: 150000 | BS13: 45998 | BT13: =200000+200000 -> 400000 | BU13: 46026 | BV13: =500000+500000+600000 -> 1600000 | BW13: 46058 | BX13: =300000+300000+600000 -> 1200000 | BY13: 46093 | BZ13: =300000+1361226+2000000+1000000 -> 4661226 | CA13: 46113 | CB13: =1000000+1100000+681857+115057+500000+500000 -> 3896914 | CC13: 46143 | CD13: =500000+919906 -> 1419906 | CE13: 46174 | CF13: =2500000+2000000+1349456+2500000 -> 8349456 | CG13: 46227 | CH13: 2717559 | CM13: =BP13+BR13+BT13+BV13+BX13+BZ13+CB13+CD13+CF13+CH13+CJ13+CL13 -> 25095061 | CN13: =BM13+CM13 -> 26995061 | CO13: =BM13/$BM$153*$BM$166 -> 28245.258 | CP13: =BM13+BP13+BR13 -> 2750000 | CQ13: =CP13/$CP$153*$DS$172 -> 36014.815 | CR13: =CP13/$CP$153*$DS$173 -> 54929.164 | CS13: =BM13+BP13+BR13+BT13+BV13 -> 4750000 | CT13: =CS13/$CS$153*$DS$174 -> 67563.498 | CU13: =CS13+BX13 -> 5950000 | CV13: =CU13/$CU$153*$DS$175 -> 202020.97 | CW13: =CU13+BZ13 -> 10611226 | CX13: =CW13/$CW$153*$DS$176 -> 103086.15 | CY13: =CW13+CB13 -> 14508140 | CZ13: =CY13/$CY$153*750000 -> 22418.725 | DA13: =CY13/$CY$153*$DS$185 -> 57675.037 | DB13: =CY13+CD13 -> 15928046 | DC13: =DB13/$DB$153*$DC$154 -> 89765.126 | DD13: =DB13/$DB$153*$DD$154 -> 60779.516 | DE13: =DB13+CF13 -> 24277502 | DF13: =DE13/$DE$153*$DF$154 -> 65093.532 | DG13: =DE13/$DE$153*$DG$154 -> 217346.8 | DH13: 28000000 | DI13: =DH13 -> 28000000 | DJ13: =DH13-DI13 -> 0 | DK13: =DH13/$DH$153*$DK$154 -> 287497.26 | DL13: =DH13/$DH$153*$DL$154 -> 80081.443 | DS13: =CN13+CO13+CQ13+CR13+CT13+CV13+CX13+CZ13+DA13+DC13+DD13+DF13+DG13+DK13+DL13+DN13+DO13+DQ13+DR13 -> 28367578 | DT13: =DS13=CN13+CO13+CQ13+CR13+CT13+CV13+CX13+CZ13+DA13+DC13+DD13+DF13+DG13+DK13+DL13+DN13+DO13+DQ13+DR13 -> TRUE | DU13: =B13 -> Mlindwa Kashindye | DV13: =DS13 -> 28367578 | DW13: =DS13-CN13 -> 1372517.3 | DZ13: =BM13+BP13+BR13+BT13+CO13+CQ13+CR13+CT13 -> 3336752.7 | EB13: =BM13+BP13+BR13+BT13+BV13+BX13+CO13+CQ13+CR13+CT13+CV13 -> 6338773.7
A14: ILS24-F00013 | B14: Emmanuel Matechi | C14: 0784333244 | D14: 45358 | E14: 50000 | F14: Social | G14: 45382 | H14: 50000 | I14: Shares | J14: 45652 | K14: 400000 | L14: Shares | M14: 45656 | N14: 450000 | O14: Shares | P14: 45657 | Q14: 50000 | R14: Shares | S14: 45913 | T14: 500000 | U14: NMB | BI14: =E14+H14+K14+N14+Q14+T14+W14+Z14+AC14+AF14+AI14+AO14+AL14+AR14+AU14+AX14+BA14+BG14 -> 1500000 | BJ14: =E14 -> 50000 | BK14: =T14 -> 500000 | BL14: =H14+K14+N14+Q14 -> 950000 | BM14: =BJ14+BL14+BK14 -> 1500000 | BN14: =BM14=BI14 -> TRUE | BO14: 45957 | BP14: 500000 | BQ14: 45967 | BR14: 500000 | BU14: 46052 | BV14: 200000 | BW14: 46081 | BX14: 100000 | BY14: 46092 | BZ14: 1000000 | CA14: 46131 | CB14: =1000000+1000000 -> 2000000 | CC14: 46173 | CD14: 2000000 | CE14: 46187 | CF14: =2000000+2000000 -> 4000000 | CG14: 46231 | CH14: 2000000 | CM14: =BP14+BR14+BT14+BV14+BX14+BZ14+CB14+CD14+CF14+CH14+CJ14+CL14 -> 12300000 | CN14: =BM14+CM14 -> 13800000 | CO14: =BM14/$BM$153*$BM$166 -> 22298.888 | CP14: =BM14+BP14+BR14 -> 2500000 | CQ14: =CP14/$CP$153*$DS$172 -> 32740.741 | CR14: =CP14/$CP$153*$DS$173 -> 49935.604 | CS14: =BM14+BP14+BR14+BT14+BV14 -> 2700000 | CT14: =CS14/$CS$153*$DS$174 -> 38404.515 | CU14: =CS14+BX14 -> 2800000 | CV14: =CU14/$CU$153*$DS$175 -> 95068.691 | CW14: =CU14+BZ14 -> 3800000 | CX14: =CW14/$CW$153*$DS$176 -> 36916.315 | CY14: =CW14+CB14 -> 5800000 | CZ14: =CY14/$CY$153*750000 -> 8962.4586 | DA14: =CY14/$CY$153*$DS$185 -> 23057.071 | DB14: =CY14+CD14 -> 7800000 | DC14: =DB14/$DB$153*$DC$154 -> 43958.184 | DD14: =DB14/$DB$153*$DD$154 -> 29763.866 | DE14: =DB14+CF14 -> 11800000 | DF14: =DE14/$DE$153*$DF$154 -> 31638.497 | DG14: =DE14/$DE$153*$DG$154 -> 105640.7 | DH14: 14318386 | DI14: =DH14 -> 14318386 | DJ14: =DH14-DI14 -> 0 | DK14: =DH14/$DH$153*$DK$154 -> 147017.74 | DL14: =DH14/$DH$153*$DL$154 -> 40951.321 | DS14: =CN14+CO14+CQ14+CR14+CT14+CV14+CX14+CZ14+DA14+DC14+DD14+DF14+DG14+DK14+DL14+DN14+DO14+DQ14+DR14 -> 14506355 | DT14: =DS14=CN14+CO14+CQ14+CR14+CT14+CV14+CX14+CZ14+DA14+DC14+DD14+DF14+DG14+DK14+DL14+DN14+DO14+DQ14+DR14 -> TRUE | DU14: =B14 -> Emmanuel Matechi | DV14: =DS14 -> 14506355 | DW14: =DS14-CN14 -> 706354.59 | DZ14: =BM14+BP14+BR14+BT14+CO14+CQ14+CR14+CT14 -> 2643379.7 | EB14: =BM14+BP14+BR14+BT14+BV14+BX14+CO14+CQ14+CR14+CT14+CV14 -> 3038448.4
A15: ILS24-F00014 | B15: Kanuti Simba | C15: 0754659313 | D15: 45354 | E15: 120000 | F15: Social | G15: 45354 | H15: 500000 | I15: Shares | J15: 45363 | K15: 100000 | L15: Shares | M15: 45529 | N15: 80000 | O15: Shares | P15: 45652 | Q15: 200000 | R15: Shares | S15: 9/112/2025 | T15: 1000000 | U15: NMB | BI15: =E15+H15+K15+N15+Q15+T15+W15+Z15+AC15+AF15+AI15+AO15+AL15+AR15+AU15+AX15+BA15+BG15 -> 2000000 | BJ15: =E15 -> 120000 | BK15: =T15 -> 1000000 | BL15: =H15+K15+N15+Q15 -> 880000 | BM15: =BJ15+BL15+BK15 -> 2000000 | BN15: =BM15=BI15 -> TRUE | BO15: 45951 | BP15: 500000 | BQ15: 45990 | BR15: 1000000 | BY15: 46087 | BZ15: 125000 | CM15: =BP15+BR15+BT15+BV15+BX15+BZ15+CB15+CD15+CF15+CH15+CJ15+CL15 -> 1625000 | CN15: =BM15+CM15 -> 3625000 | CO15: =BM15/$BM$153*$BM$166 -> 29731.85 | CP15: =BM15+BP15+BR15 -> 3500000 | CQ15: =CP15/$CP$153*$DS$172 -> 45837.037 | CR15: =CP15/$CP$153*$DS$173 -> 69909.846 | CS15: =BM15+BP15+BR15+BT15+BV15 -> 3500000 | CT15: =CS15/$CS$153*$DS$174 -> 49783.63 | CU15: =CS15+BX15 -> 3500000 | CV15: =CU15/$CU$153*$DS$175 -> 118835.86 | CW15: =CU15+BZ15 -> 3625000 | CX15: =CW15/$CW$153*$DS$176 -> 35216.221 | CY15: =CW15+CB15 -> 3625000 | CZ15: =CY15/$CY$153*750000 -> 5601.5366 | DA15: =CY15/$CY$153*$DS$185 -> 14410.669 | DB15: =CY15+CD15 -> 3625000 | DC15: =DB15/$DB$153*$DC$154 -> 20429.284 | DD15: =DB15/$DB$153*$DD$154 -> 13832.566 | DE15: =DB15+CF15 -> 3625000 | DF15: =DE15/$DE$153*$DF$154 -> 9719.4535 | DG15: =DE15/$DE$153*$DG$154 -> 32453.181 | DH15: 4070761.1 | DI15: =DH15 -> 4070761.1 | DJ15: =DH15-DI15 -> 0 | DK15: =DH15/$DH$153*$DK$154 -> 41797.597 | DL15: =DH15/$DH$153*$DL$154 -> 11642.587 | DS15: =CN15+CO15+CQ15+CR15+CT15+CV15+CX15+CZ15+DA15+DC15+DD15+DF15+DG15+DK15+DL15+DN15+DO15+DQ15+DR15 -> 4124201.3 | DT15: =DS15=CN15+CO15+CQ15+CR15+CT15+CV15+CX15+CZ15+DA15+DC15+DD15+DF15+DG15+DK15+DL15+DN15+DO15+DQ15+DR15 -> TRUE | DU15: =B15 -> Kanuti Simba | DV15: =DS15 -> 4124201.3 | DW15: =DS15-CN15 -> 499201.32 | DZ15: =BM15+BP15+BR15+BT15+CO15+CQ15+CR15+CT15 -> 3695262.4 | EB15: =BM15+BP15+BR15+BT15+BV15+BX15+CO15+CQ15+CR15+CT15+CV15 -> 3814098.2
A16: ILS24-F00015 | B16: Mohamed Khalfan Mohamed | C16: 0784740381 | D16: 45352 | E16: 50000 | F16: Shares | G16: 45362 | H16: 120000 | I16: Shares | J16: 45529 | K16: 630000 | L16: Shares | M16: 45654 | N16: 200000 | O16: Shares | P16: 45885 | Q16: 300000 | R16: NMB | S16: 45927 | T16: 300000 | U16: NMB | BI16: =E16+H16+K16+N16+Q16+T16+W16+Z16+AC16+AF16+AI16+AO16+AL16+AR16+AU16+AX16+BA16+BG16 -> 1600000 | BK16: =Q16+T16 -> 600000 | BL16: =E16+H16+K16+N16 -> 1000000 | BM16: =BJ16+BL16+BK16 -> 1600000 | BN16: =BM16=BI16 -> TRUE | BO16: 45955 | BP16: 400000 | BQ16: 45985 | BR16: 200000 | BS16: 46014 | BT16: =100000+700000 -> 800000 | BW16: 46077 | BX16: =200000+300000 -> 500000 | BY16: 46087 | BZ16: =125000+500000 -> 625000 | CC16: 46154 | CD16: 300000 | CE16: 46186 | CF16: 312000 | CG16: 46229 | CH16: 500000 | CM16: =BP16+BR16+BT16+BV16+BX16+BZ16+CB16+CD16+CF16+CH16+CJ16+CL16 -> 3637000 | CN16: =BM16+CM16 -> 5237000 | CO16: =BM16/$BM$153*$BM$166 -> 23785.48 | CP16: =BM16+BP16+BR16 -> 2200000 | CQ16: =CP16/$CP$153*$DS$172 -> 28811.852 | CR16: =CP16/$CP$153*$DS$173 -> 43943.332 | CS16: =BM16+BP16+BR16+BT16+BV16 -> 3000000 | CT16: =CS16/$CS$153*$DS$174 -> 42671.683 | CU16: =CS16+BX16 -> 3500000 | CV16: =CU16/$CU$153*$DS$175 -> 118835.86 | CW16: =CU16+BZ16 -> 4125000 | CX16: =CW16/$CW$153*$DS$176 -> 40073.631 | CY16: =CW16+CB16 -> 4125000 | CZ16: =CY16/$CY$153*750000 -> 6374.1624 | DA16: =CY16/$CY$153*$DS$185 -> 16398.348 | DB16: =CY16+CD16 -> 4425000 | DC16: =DB16/$DB$153*$DC$154 -> 24937.816 | DD16: =DB16/$DB$153*$DD$154 -> 16885.27 | DE16: =DB16+CF16 -> 4737000 | DF16: =DE16/$DE$153*$DF$154 -> 12700.98 | DG16: =DE16/$DE$153*$DG$154 -> 42408.474 | DH16: 5654826.9 | DI16: =DH16 -> 5654826.9 | DJ16: =DH16-DI16 -> 0 | DK16: =DH16/$DH$153*$DK$154 -> 58062.403 | DL16: =DH16/$DH$153*$DL$154 -> 16173.097 | DS16: =CN16+CO16+CQ16+CR16+CT16+CV16+CX16+CZ16+DA16+DC16+DD16+DF16+DG16+DK16+DL16+DN16+DO16+DQ16+DR16 -> 5729062.4 | DT16: =DS16=CN16+CO16+CQ16+CR16+CT16+CV16+CX16+CZ16+DA16+DC16+DD16+DF16+DG16+DK16+DL16+DN16+DO16+DQ16+DR16 -> TRUE | DU16: =B16 -> Mohamed Khalfan Mohamed | DV16: =DS16 -> 5729062.4 | DW16: =DS16-CN16 -> 492062.39 | DZ16: =BM16+BP16+BR16+BT16+CO16+CQ16+CR16+CT16 -> 3139212.3 | EB16: =BM16+BP16+BR16+BT16+BV16+BX16+CO16+CQ16+CR16+CT16+CV16 -> 3758048.2
A17: ILS24-F00016 | B17: Walter Salema | C17: 0754001144 | D17: 45360 | E17: 60000 | F17: Social | G17: 45360 | H17: 90000 | I17: Shares | J17: 45526 | K17: 650000 | L17: Shares | M17: 45875 | N17: 200000 | O17: NMB | BI17: =E17+H17+K17+N17+Q17+T17+W17+Z17+AC17+AF17+AI17+AO17+AL17+AR17+AU17+AX17+BA17+BG17 -> 1000000 | BJ17: =E17 -> 60000 | BK17: =N17 -> 200000 | BL17: =H17+K17 -> 740000 | BM17: =BJ17+BL17+BK17 -> 1000000 | BN17: =BM17=BI17 -> TRUE | BO17: 45951 | BP17: =1000000+500000 -> 1500000 | BQ17: 45990 | BR17: 100000 | BS17: 46004 | BT17: 200000 | BU17: 46026 | BV17: 1200000 | CA17: 46141 | CB17: 25000000 | CG17: 46214 | CH17: =3000000+2000000+10000000 -> 15000000 | CM17: =BP17+BR17+BT17+BV17+BX17+BZ17+CB17+CD17+CF17+CH17+CJ17+CL17 -> 43000000 | CN17: =BM17+CM17 -> 44000000 | CO17: =BM17/$BM$153*$BM$166 -> 14865.925 | CP17: =BM17+BP17+BR17 -> 2600000 | CQ17: =CP17/$CP$153*$DS$172 -> 34050.371 | CR17: =CP17/$CP$153*$DS$173 -> 51933.028 | CS17: =BM17+BP17+BR17+BT17+BV17 -> 4000000 | CT17: =CS17/$CS$153*$DS$174 -> 56895.577 | CU17: =CS17+BX17 -> 4000000 | CV17: =CU17/$CU$153*$DS$175 -> 135812.42 | CW17: =CU17+BZ17 -> 4000000 | CX17: =CW17/$CW$153*$DS$176 -> 38859.278 | CY17: =CW17+CB17 -> 29000000 | CZ17: =CY17/$CY$153*750000 -> 44812.293 | DA17: =CY17/$CY$153*$DS$185 -> 115285.36 | DB17: =CY17+CD17 -> 29000000 | DC17: =DB17/$DB$153*$DC$154 -> 163434.27 | DD17: =DB17/$DB$153*$DD$154 -> 110660.53 | DE17: =DB17+CF17 -> 29000000 | DF17: =DE17/$DE$153*$DF$154 -> 77755.628 | DG17: =DE17/$DE$153*$DG$154 -> 259625.45 | DH17: 45103990 | DI17: ='[1]Member Positions'!$F$19 -> 45103990 | DJ17: =DH17-DI17 -> -0.020005636 | DK17: =DH17/$DH$153*$DK$154 -> 463116.93 | DL17: =DH17/$DH$153*$DL$154 -> 128999.74 | DS17: =CN17+CO17+CQ17+CR17+CT17+CV17+CX17+CZ17+DA17+DC17+DD17+DF17+DG17+DK17+DL17+DN17+DO17+DQ17+DR17 -> 45696107 | DT17: =DS17=CN17+CO17+CQ17+CR17+CT17+CV17+CX17+CZ17+DA17+DC17+DD17+DF17+DG17+DK17+DL17+DN17+DO17+DQ17+DR17 -> TRUE | DU17: =B17 -> Walter Salema | DV17: =DS17 -> 45696107 | DW17: =DS17-CN17 -> 1696106.8 | DZ17: =BM17+BP17+BR17+BT17+CO17+CQ17+CR17+CT17 -> 2957744.9 | EB17: =BM17+BP17+BR17+BT17+BV17+BX17+CO17+CQ17+CR17+CT17+CV17 -> 4293557.3
A18: ILS24-F00017 | B18: Emmanuel Mmari | C18: 0754740047 | D18: 45506 | E18: 900000 | F18: Shares | G18: 45685 | H18: 100000 | I18: Shares | J18: 45775 | K18: 100000 | L18: Shares | M18: 45742 | N18: 200000 | O18: Shares | P18: 45775 | Q18: 100000 | R18: Shares | S18: 45799 | T18: 200000 | U18: Shares | V18: 45833 | W18: 200000 | X18: Shares | BI18: =E18+H18+K18+N18+Q18+T18+W18+Z18+AC18+AF18+AI18+AO18+AL18+AR18+AU18+AX18+BA18+BG18 -> 1800000 | BL18: =E18+H18+K18+N18+Q18+T18+W18 -> 1800000 | BM18: =BJ18+BL18+BK18 -> 1800000 | BN18: =BM18=BI18 -> TRUE | BP18: 0 | BQ18: 45975 | BR18: 500000 | BS18: 46014 | BT18: 500000 | BU18: 46043 | BV18: 500000 | CG18: 46230 | CH18: 200000 | CM18: =BP18+BR18+BT18+BV18+BX18+BZ18+CB18+CD18+CF18+CH18+CJ18+CL18 -> 1700000 | CN18: =BM18+CM18 -> 3500000 | CO18: =BM18/$BM$153*$BM$166 -> 26758.665 | CP18: =BM18+BP18+BR18 -> 2300000 | CQ18: =CP18/$CP$153*$DS$172 -> 30121.482 | CR18: =CP18/$CP$153*$DS$173 -> 45940.756 | CS18: =BM18+BP18+BR18+BT18+BV18 -> 3300000 | CT18: =CS18/$CS$153*$DS$174 -> 46938.851 | CU18: =CS18+BX18 -> 3300000 | CV18: =CU18/$CU$153*$DS$175 -> 112045.24 | CW18: =CU18+BZ18 -> 3300000 | CX18: =CW18/$CW$153*$DS$176 -> 32058.905 | CY18: =CW18+CB18 -> 3300000 | CZ18: =CY18/$CY$153*750000 -> 5099.3299 | DA18: =CY18/$CY$153*$DS$185 -> 13118.678 | DB18: =CY18+CD18 -> 3300000 | DC18: =DB18/$DB$153*$DC$154 -> 18597.693 | DD18: =DB18/$DB$153*$DD$154 -> 12592.405 | DE18: =DB18+CF18 -> 3300000 | DF18: =DE18/$DE$153*$DF$154 -> 8848.0542 | DG18: =DE18/$DE$153*$DG$154 -> 29543.585 | DH18: 3881663.6 | DI18: ='[1]Member Positions'!$F$20 -> 3881663.6 | DJ18: =DH18-DI18 -> 0.007700495 | DK18: =DH18/$DH$153*$DK$154 -> 39855.989 | DL18: =DH18/$DH$153*$DL$154 -> 11101.758 | DS18: =CN18+CO18+CQ18+CR18+CT18+CV18+CX18+CZ18+DA18+DC18+DD18+DF18+DG18+DK18+DL18+DN18+DO18+DQ18+DR18 -> 3932621.4 | DT18: =DS18=CN18+CO18+CQ18+CR18+CT18+CV18+CX18+CZ18+DA18+DC18+DD18+DF18+DG18+DK18+DL18+DN18+DO18+DQ18+DR18 -> TRUE | DU18: =B18 -> Emmanuel Mmari | DV18: =DS18 -> 3932621.4 | DW18: =DS18-CN18 -> 432621.39 | DZ18: =BM18+BP18+BR18+BT18+CO18+CQ18+CR18+CT18 -> 2949759.8 | EB18: =BM18+BP18+BR18+BT18+BV18+BX18+CO18+CQ18+CR18+CT18+CV18 -> 3561805
A19: ILS24-F00018 | B19: Alban Robert Kimario | C19: 0784859978 | D19: 45380 | E19: 170000 | F19: Social | G19: 45380 | H19: 530000 | I19: Shares | J19: 45530 | K19: 100000 | L19: Shares | M19: 45657 | N19: 200000 | O19: Shares | BI19: =E19+H19+K19+N19+Q19+T19+W19+Z19+AC19+AF19+AI19+AO19+AL19+AR19+AU19+AX19+BA19+BG19 -> 1000000 | BJ19: =E19 -> 170000 | BL19: =H19+K19+N19 -> 830000 | BM19: =BJ19+BL19+BK19 -> 1000000 | BN19: =BM19=BI19 -> TRUE | BP19: 0 | BQ19: 45990 | BR19: 500000 | BS19: 46002 | BT19: 1200000 | BU19: 46047 | BV19: 200000 | BW19: 46081 | BX19: 300000 | CA19: 46113 | CB19: =500000+2249930+204889 -> 2954819 | CC19: 46171 | CD19: 5565744 | CE19: 46187 | CF19: =1000000+3000000+16000000 -> 20000000 | CG19: 46219 | CH19: 500000 | CM19: =BP19+BR19+BT19+BV19+BX19+BZ19+CB19+CD19+CF19+CH19+CJ19+CL19 -> 31220563 | CN19: =BM19+CM19 -> 32220563 | CO19: =BM19/$BM$153*$BM$166 -> 14865.925 | CP19: =BM19+BP19+BR19 -> 1500000 | CQ19: =CP19/$CP$153*$DS$172 -> 19644.445 | CR19: =CP19/$CP$153*$DS$173 -> 29961.362 | CS19: =BM19+BP19+BR19+BT19+BV19 -> 2900000 | CT19: =CS19/$CS$153*$DS$174 -> 41249.294 | CU19: =CS19+BX19 -> 3200000 | CV19: =CU19/$CU$153*$DS$175 -> 108649.93 | CW19: =CU19+BZ19 -> 3200000 | CX19: =CW19/$CW$153*$DS$176 -> 31087.423 | CY19: =CW19+CB19 -> 6154819 | CZ19: =CY19/$CY$153*750000 -> 9510.7432 | DA19: =CY19/$CY$153*$DS$185 -> 24467.603 | DB19: =CY19+CD19 -> 11720563 | DC19: =DB19/$DB$153*$DC$154 -> 66053.163 | DD19: =DB19/$DB$153*$DD$154 -> 44724.265 | DE19: =DB19+CF19 -> 31720563 | DF19: =DE19/$DE$153*$DF$154 -> 85050.079 | DG19: =DE19/$DE$153*$DG$154 -> 283981.56 | DH19: 32979809 | DI19: ='Member position mfumo and excel'!F21 -> 32979809 | DJ19: =DH19-DI19 -> 0.026504885 | DK19: =DH19/$DH$153*$DK$154 -> 338628.75 | DL19: =DH19/$DH$153*$DL$154 -> 94323.954 | DS19: =CN19+CO19+CQ19+CR19+CT19+CV19+CX19+CZ19+DA19+DC19+DD19+DF19+DG19+DK19+DL19+DN19+DO19+DQ19+DR19 -> 33412761 | DT19: =DS19=CN19+CO19+CQ19+CR19+CT19+CV19+CX19+CZ19+DA19+DC19+DD19+DF19+DG19+DK19+DL19+DN19+DO19+DQ19+DR19 -> TRUE | DU19: =B19 -> Alban Robert Kimario | DV19: =DS19 -> 33412761 | DW19: =DS19-CN19 -> 1192198.5 | DZ19: =BM19+BP19+BR19+BT19+CO19+CQ19+CR19+CT19 -> 2805721 | EB19: =BM19+BP19+BR19+BT19+BV19+BX19+CO19+CQ19+CR19+CT19+CV19 -> 3414371
A20: ILS24-F00019 | B20: Laurian Gidoyi | C20: 0757080851 | D20: 45374 | E20: 170000 | F20: Shares | G20: 45374 | H20: 80000 | I20: Social | J20: 45448 | K20: 50000 | L20: Social | M20: 45636 | N20: 300000 | O20: Shares | P20: 45637 | Q20: 200000 | R20: Shares | S20: 45659 | T20: 200000 | U20: Shares | V20: 45911 | W20: 500000 | X20: NMB | BI20: =E20+H20+K20+N20+Q20+T20+W20+Z20+AC20+AF20+AI20+AO20+AL20+AR20+AU20+AX20+BA20+BG20 -> 1500000 | BJ20: =H20+K20+Z20 -> 130000 | BK20: =W20 -> 500000 | BL20: =E20+N20+Q20+T20 -> 870000 | BM20: =BJ20+BL20+BK20 -> 1500000 | BN20: =BM20=BI20 -> TRUE | BO20: 45931 | BP20: =400000+300000 -> 700000 | BQ20: 45975 | BR20: 300000 | BS20: 45998 | BT20: 100000 | BU20: 46045 | BV20: 300000 | BW20: 46079 | BX20: 200000 | BY20: 46082 | BZ20: =200000+200000 -> 400000 | CA20: 46114 | CB20: =500000+500000 -> 1000000 | CC20: 46143 | CD20: =700000+2000000 -> 2700000 | CE20: 46189 | CF20: =700000+1000000+1000000 -> 2700000 | CG20: 46227 | CH20: 2000000 | CM20: =BP20+BR20+BT20+BV20+BX20+BZ20+CB20+CD20+CF20+CH20+CJ20+CL20 -> 10400000 | CN20: =BM20+CM20 -> 11900000 | CO20: =BM20/$BM$153*$BM$166 -> 22298.888 | CP20: =BM20+BP20+BR20 -> 2500000 | CQ20: =CP20/$CP$153*$DS$172 -> 32740.741 | CR20: =CP20/$CP$153*$DS$173 -> 49935.604 | CS20: =BM20+BP20+BR20+BT20+BV20 -> 2900000 | CT20: =CS20/$CS$153*$DS$174 -> 41249.294 | CU20: =CS20+BX20 -> 3100000 | CV20: =CU20/$CU$153*$DS$175 -> 105254.62 | CW20: =CU20+BZ20 -> 3500000 | CX20: =CW20/$CW$153*$DS$176 -> 34001.869 | CY20: =CW20+CB20 -> 4500000 | CZ20: =CY20/$CY$153*750000 -> 6953.6317 | DA20: =CY20/$CY$153*$DS$185 -> 17889.107 | DB20: =CY20+CD20 -> 7200000 | DC20: =DB20/$DB$153*$DC$154 -> 40576.785 | DD20: =DB20/$DB$153*$DD$154 -> 27474.338 | DE20: =DB20+CF20 -> 9900000 | DF20: =DE20/$DE$153*$DF$154 -> 26544.163 | DG20: =DE20/$DE$153*$DG$154 -> 88630.756 | DH20: 12393550 | DI20: ='Member position mfumo and excel'!F22 -> 12393550 | DJ20: =DH20-DI20 -> -0.0026826933 | DK20: =DH20/$DH$153*$DK$154 -> 127253.99 | DL20: =DH20/$DH$153*$DL$154 -> 35446.192 | DS20: =CN20+CO20+CQ20+CR20+CT20+CV20+CX20+CZ20+DA20+DC20+DD20+DF20+DG20+DK20+DL20+DN20+DO20+DQ20+DR20 -> 12556250 | DT20: =DS20=CN20+CO20+CQ20+CR20+CT20+CV20+CX20+CZ20+DA20+DC20+DD20+DF20+DG20+DK20+DL20+DN20+DO20+DQ20+DR20 -> TRUE | DU20: =B20 -> Laurian Gidoyi | DV20: =DS20 -> 12556250 | DW20: =DS20-CN20 -> 656249.98 | DZ20: =BM20+BP20+BR20+BT20+CO20+CQ20+CR20+CT20 -> 2746224.5 | EB20: =BM20+BP20+BR20+BT20+BV20+BX20+CO20+CQ20+CR20+CT20+CV20 -> 3351479.1
A21: ILS24-F00020 | B21: John Arbogast Massawe | C21: 0712345926 | D21: 45370 | E21: 50000 | F21: Social | G21: 45370 | H21: 90000 | I21: Shares | J21: 45527 | K21: 660000 | L21: Shares | M21: 45655 | N21: 200000 | O21: Shares | P21: 45799 | Q21: 400000 | R21: Shares | S21: 45916 | T21: 500000 | U21: NMB | BI21: =E21+H21+K21+N21+Q21+T21+W21+Z21+AC21+AF21+AI21+AO21+AL21+AR21+AU21+AX21+BA21+BG21 -> 1900000 | BJ21: =E21 -> 50000 | BK21: =T21 -> 500000 | BL21: =H21+K21+N21+Q21 -> 1350000 | BM21: =BJ21+BL21+BK21 -> 1900000 | BN21: =BM21=BI21 -> TRUE | BP21: 0 | BQ21: 45990 | BR21: 200000 | BS21: 46022 | BT21: 500000 | BY21: 46095 | BZ21: =1200000+2000000 -> 3200000 | CA21: 46128 | CB21: =1920700+1000000 -> 2920700 | CC21: 46159 | CD21: =2000000+2500000 -> 4500000 | CE21: 46185 | CF21: 2500000 | CG21: 46221 | CH21: =2000000+2000000 -> 4000000 | CM21: =BP21+BR21+BT21+BV21+BX21+BZ21+CB21+CD21+CF21+CH21+CJ21+CL21 -> 17820700 | CN21: =BM21+CM21 -> 19720700 | CO21: =BM21/$BM$153*$BM$166 -> 28245.258 | CP21: =BM21+BP21+BR21 -> 2100000 | CQ21: =CP21/$CP$153*$DS$172 -> 27502.222 | CR21: =CP21/$CP$153*$DS$173 -> 41945.907 | CS21: =BM21+BP21+BR21+BT21+BV21 -> 2600000 | CT21: =CS21/$CS$153*$DS$174 -> 36982.125 | CU21: =CS21+BX21 -> 2600000 | CV21: =CU21/$CU$153*$DS$175 -> 88278.07 | CW21: =CU21+BZ21 -> 5800000 | CX21: =CW21/$CW$153*$DS$176 -> 56345.954 | CY21: =CW21+CB21 -> 8720700 | CZ21: =CY21/$CY$153*750000 -> 13475.675 | DA21: =CY21/$CY$153*$DS$185 -> 34667.897 | DB21: =CY21+CD21 -> 13220700 | DC21: =DB21/$DB$153*$DC$154 -> 74507.432 | DD21: =DB21/$DB$153*$DD$154 -> 50448.608 | DE21: =DB21+CF21 -> 15720700 | DF21: =DE21/$DE$153*$DF$154 -> 42150.79 | DG21: =DE21/$DE$153*$DG$154 -> 140741.16 | DH21: 20355991 | DI21: ='Member position mfumo and excel'!F23 -> 20355991 | DJ21: =DH21-DI21 -> 0.00084353611 | DK21: =DH21/$DH$153*$DK$154 -> 209010.42 | DL21: =DH21/$DH$153*$DL$154 -> 58219.184 | DS21: =CN21+CO21+CQ21+CR21+CT21+CV21+CX21+CZ21+DA21+DC21+DD21+DF21+DG21+DK21+DL21+DN21+DO21+DQ21+DR21 -> 20623221 | DT21: =DS21=CN21+CO21+CQ21+CR21+CT21+CV21+CX21+CZ21+DA21+DC21+DD21+DF21+DG21+DK21+DL21+DN21+DO21+DQ21+DR21 -> TRUE | DU21: =B21 -> John Arbogast Massawe | DV21: =DS21 -> 20623221 | DW21: =DS21-CN21 -> 902520.71 | DZ21: =BM21+BP21+BR21+BT21+CO21+CQ21+CR21+CT21 -> 2734675.5 | EB21: =BM21+BP21+BR21+BT21+BV21+BX21+CO21+CQ21+CR21+CT21+CV21 -> 2822953.6
A22: ILS24-F00021 | B22: Masale Rajabu Masale | C22: 0756148078 | D22: 45361 | E22: 100000 | F22: Social | G22: 45361 | H22: 250000 | I22: Shares | J22: 45637 | K22: 450000 | L22: Shares | M22: 45650 | N22: 200000 | O22: Shares | P22: 45911 | Q22: 900000 | R22: Shares | BI22: =E22+H22+K22+N22+Q22+T22+W22+Z22+AC22+AF22+AI22+AO22+AL22+AR22+AU22+AX22+BA22+BG22 -> 1900000 | BJ22: =E22 -> 100000 | BL22: =H22+K22+N22+Q22 -> 1800000 | BM22: =BJ22+BL22+BK22 -> 1900000 | BN22: =BM22=BI22 -> TRUE | BO22: 45951 | BP22: 600000 | BS22: 46003 | BT22: 1200000 | CA22: 46127 | CB22: 3000000 | CE22: 46200 | CF22: 3000000 | CG22: 46211 | CH22: 3000000 | CM22: =BP22+BR22+BT22+BV22+BX22+BZ22+CB22+CD22+CF22+CH22+CJ22+CL22 -> 10800000 | CN22: =BM22+CM22 -> 12700000 | CO22: =BM22/$BM$153*$BM$166 -> 28245.258 | CP22: =BM22+BP22+BR22 -> 2500000 | CQ22: =CP22/$CP$153*$DS$172 -> 32740.741 | CR22: =CP22/$CP$153*$DS$173 -> 49935.604 | CS22: =BM22+BP22+BR22+BT22+BV22 -> 3700000 | CT22: =CS22/$CS$153*$DS$174 -> 52628.409 | CU22: =CS22+BX22 -> 3700000 | CV22: =CU22/$CU$153*$DS$175 -> 125626.48 | CW22: =CU22+BZ22 -> 3700000 | CX22: =CW22/$CW$153*$DS$176 -> 35944.833 | CY22: =CW22+CB22 -> 6700000 | CZ22: =CY22/$CY$153*750000 -> 10353.185 | DA22: =CY22/$CY$153*$DS$185 -> 26634.893 | DB22: =CY22+CD22 -> 6700000 | DC22: =DB22/$DB$153*$DC$154 -> 37758.953 | DD22: =DB22/$DB$153*$DD$154 -> 25566.398 | DE22: =DB22+CF22 -> 9700000 | DF22: =DE22/$DE$153*$DF$154 -> 26007.917 | DG22: =DE22/$DE$153*$DG$154 -> 86840.235 | DH22: 13238283 | DI22: ='Member position mfumo and excel'!F24 -> 13238283 | DJ22: =DH22-DI22 -> 0.0095804594 | DK22: =DH22/$DH$153*$DK$154 -> 135927.51 | DL22: =DH22/$DH$153*$DL$154 -> 37862.172 | DS22: =CN22+CO22+CQ22+CR22+CT22+CV22+CX22+CZ22+DA22+DC22+DD22+DF22+DG22+DK22+DL22+DN22+DO22+DQ22+DR22 -> 13412073 | DT22: =DS22=CN22+CO22+CQ22+CR22+CT22+CV22+CX22+CZ22+DA22+DC22+DD22+DF22+DG22+DK22+DL22+DN22+DO22+DQ22+DR22 -> TRUE | DU22: =B22 -> Masale Rajabu Masale | DV22: =DS22 -> 13412073 | DW22: =DS22-CN22 -> 712072.59 | DZ22: =BM22+BP22+BR22+BT22+CO22+CQ22+CR22+CT22 -> 3863550 | EB22: =BM22+BP22+BR22+BT22+BV22+BX22+CO22+CQ22+CR22+CT22+CV22 -> 3989176.5
A23: ILS24-F00022 | B23: Innocent Mosha | C23: 0713123540 | D23: 45650 | E23: 800000 | F23: Shares | G23: 45653 | H23: 200000 | I23: Shares | J23: 45795 | K23: 400000 | L23: Shares | M23: 45807 | N23: 100000 | O23: Shares | BI23: =E23+H23+K23+N23+Q23+T23+W23+Z23+AC23+AF23+AI23+AO23+AL23+AR23+AU23+AX23+BA23+BG23 -> 1500000 | BL23: =E23+H23+K23+N23 -> 1500000 | BM23: =BJ23+BL23+BK23 -> 1500000 | BN23: =BM23=BI23 -> TRUE | BP23: 0 | BR23: 0 | BU23: 46053 | BV23: 3200000 | CM23: =BP23+BR23+BT23+BV23+BX23+BZ23+CB23+CD23+CF23+CH23+CJ23+CL23 -> 3200000 | CN23: =BM23+CM23 -> 4700000 | CO23: =BM23/$BM$153*$BM$166 -> 22298.888 | CP23: =BM23+BP23+BR23 -> 1500000 | CQ23: =CP23/$CP$153*$DS$172 -> 19644.445 | CR23: =CP23/$CP$153*$DS$173 -> 29961.362 | CS23: =BM23+BP23+BR23+BT23+BV23 -> 4700000 | CT23: =CS23/$CS$153*$DS$174 -> 66852.304 | CU23: =CS23+BX23 -> 4700000 | CV23: =CU23/$CU$153*$DS$175 -> 159579.59 | CW23: =CU23+BZ23 -> 4700000 | CX23: =CW23/$CW$153*$DS$176 -> 45659.652 | CY23: =CW23+CB23 -> 4700000 | CZ23: =CY23/$CY$153*750000 -> 7262.682 | DA23: =CY23/$CY$153*$DS$185 -> 18684.178 | DB23: =CY23+CD23 -> 4700000 | DC23: =DB23/$DB$153*$DC$154 -> 26487.624 | DD23: =DB23/$DB$153*$DD$154 -> 17934.637 | DE23: =DB23+CF23 -> 4700000 | DF23: =DE23/$DE$153*$DF$154 -> 12601.774 | DG23: =DE23/$DE$153*$DG$154 -> 42077.227 | DH23: 5169044.4 | DI23: ='Member position mfumo and excel'!F25 -> 5169044.3 | DJ23: =DH23-DI23 -> 0.012052548 | DK23: =DH23/$DH$153*$DK$154 -> 53074.505 | DL23: =DH23/$DH$153*$DL$154 -> 14783.733 | DS23: =CN23+CO23+CQ23+CR23+CT23+CV23+CX23+CZ23+DA23+DC23+DD23+DF23+DG23+DK23+DL23+DN23+DO23+DQ23+DR23 -> 5236902.6 | DT23: =DS23=CN23+CO23+CQ23+CR23+CT23+CV23+CX23+CZ23+DA23+DC23+DD23+DF23+DG23+DK23+DL23+DN23+DO23+DQ23+DR23 -> TRUE | DU23: =B23 -> Innocent Mosha | DV23: =DS23 -> 5236902.6 | DW23: =DS23-CN23 -> 536902.6 | DZ23: =BM23+BP23+BR23+BT23+CO23+CQ23+CR23+CT23 -> 1638757 | EB23: =BM23+BP23+BR23+BT23+BV23+BX23+CO23+CQ23+CR23+CT23+CV23 -> 4998336.6
A24: ILS24-F00023 | B24: Amos Nungu | C24: 0787716778 | D24: 45369 | E24: 220000 | F24: Shares | G24: 45369 | H24: 80000 | I24: Social | J24: 45524 | K24: 550000 | L24: Shares | M24: 45683 | N24: 150000 | O24: Shares | P24: 45778 | Q24: 600000 | R24: NMB | S24: 45875 | T24: 500000 | U24: NMB | BI24: =E24+H24+K24+N24+Q24+T24+W24+Z24+AC24+AF24+AI24+AO24+AL24+AR24+AU24+AX24+BA24+BG24 -> 2100000 | BJ24: =H24 -> 80000 | BK24: =Q24+T24 -> 1100000 | BL24: =E24+K24+N24 -> 920000 | BM24: =BJ24+BL24+BK24 -> 2100000 | BN24: =BM24=BI24 -> TRUE | BO24: 45951 | BP24: 500000 | BR24: 0 | BS24: 45999 | BT24: 1000000 | BW24: 46079 | BX24: =2000000+1000000 -> 3000000 | BY24: 46095 | BZ24: 2000000 | CA24: 46114 | CB24: =1000000+2000000 -> 3000000 | CC24: 46143 | CD24: 1000000 | CE24: 46200 | CF24: =2000000+1000000 -> 3000000 | CG24: 46218 | CH24: =3000000+3000000 -> 6000000 | CM24: =BP24+BR24+BT24+BV24+BX24+BZ24+CB24+CD24+CF24+CH24+CJ24+CL24 -> 19500000 | CN24: =BM24+CM24 -> 21600000 | CO24: =BM24/$BM$153*$BM$166 -> 31218.443 | CP24: =BM24+BP24+BR24 -> 2600000 | CQ24: =CP24/$CP$153*$DS$172 -> 34050.371 | CR24: =CP24/$CP$153*$DS$173 -> 51933.028 | CS24: =BM24+BP24+BR24+BT24+BV24 -> 3600000 | CT24: =CS24/$CS$153*$DS$174 -> 51206.02 | CU24: =CS24+BX24 -> 6600000 | CV24: =CU24/$CU$153*$DS$175 -> 224090.49 | CW24: =CU24+BZ24 -> 8600000 | CX24: =CW24/$CW$153*$DS$176 -> 83547.449 | CY24: =CW24+CB24 -> 11600000 | CZ24: =CY24/$CY$153*750000 -> 17924.917 | DA24: =CY24/$CY$153*$DS$185 -> 46114.142 | DB24: =CY24+CD24 -> 12600000 | DC24: =DB24/$DB$153*$DC$154 -> 71009.375 | DD24: =DB24/$DB$153*$DD$154 -> 48080.091 | DE24: =DB24+CF24 -> 15600000 | DF24: =DE24/$DE$153*$DF$154 -> 41827.165 | DG24: =DE24/$DE$153*$DG$154 -> 139660.58 | DH24: 22440662 | DI24: ='Member position mfumo and excel'!F26 -> 22440662 | DJ24: =DH24-DI24 -> 0.0013783053 | DK24: =DH24/$DH$153*$DK$154 -> 230415.32 | DL24: =DH24/$DH$153*$DL$154 -> 64181.451 | DS24: =CN24+CO24+CQ24+CR24+CT24+CV24+CX24+CZ24+DA24+DC24+DD24+DF24+DG24+DK24+DL24+DN24+DO24+DQ24+DR24 -> 22735259 | DT24: =DS24=CN24+CO24+CQ24+CR24+CT24+CV24+CX24+CZ24+DA24+DC24+DD24+DF24+DG24+DK24+DL24+DN24+DO24+DQ24+DR24 -> TRUE | DU24: =B24 -> Amos Nungu | DV24: =DS24 -> 22735259 | DW24: =DS24-CN24 -> 1135258.8 | DZ24: =BM24+BP24+BR24+BT24+CO24+CQ24+CR24+CT24 -> 3768407.9 | EB24: =BM24+BP24+BR24+BT24+BV24+BX24+CO24+CQ24+CR24+CT24+CV24 -> 6992498.3
A25: ILS24-F00024 | B25: Athumani Mwasha | C25: 0715470615 | D25: 45363 | E25: 170000 | F25: Social | G25: 45363 | H25: 130000 | I25: Shares | J25: 45524 | K25: 220000 | L25: Shares | M25: 45530 | N25: 280000 | O25: Shares | P25: 45659 | Q25: 200000 | R25: Shares | S25: 45801 | T25: 400000 | U25: NMB | V25: 45835 | W25: 100000 | X25: NMB | Y25: 45894 | Z25: 200000 | AA25: NMB | AB25: 45911 | AC25: 300000 | AD25: NMB | BI25: =E25+H25+K25+N25+Q25+T25+W25+Z25+AC25+AF25+AI25+AO25+AL25+AR25+AU25+AX25+BA25+BG25 -> 2000000 | BJ25: =E25 -> 170000 | BK25: =T25+W25+Z25+AC25 -> 1000000 | BL25: =H25+K25+N25+Q25 -> 830000 | BM25: =BJ25+BL25+BK25 -> 2000000 | BN25: =BM25=BI25 -> TRUE | BP25: 0 | BQ25: 45966 | BR25: =200000+200000+100000 -> 500000 | BS25: 45997 | BT25: =100000+100000 -> 200000 | BU25: 46052 | BV25: 400000 | BY25: 46084 | BZ25: =500000+540000+155000+644000+1000000+150000 -> 2989000 | CA25: 46123 | CB25: =300000+300000 -> 600000 | CC25: 46171 | CD25: 550000 | CE25: 46174 | CF25: =350000+300000+300000+400000+500000 -> 1850000 | CG25: 46204 | CH25: =500000+100000+127000+300000+220000+162000+365000+500000 -> 2274000 | CM25: =BP25+BR25+BT25+BV25+BX25+BZ25+CB25+CD25+CF25+CH25+CJ25+CL25 -> 9363000 | CN25: =BM25+CM25 -> 11363000 | CO25: =BM25/$BM$153*$BM$166 -> 29731.85 | CP25: =BM25+BP25+BR25 -> 2500000 | CQ25: =CP25/$CP$153*$DS$172 -> 32740.741 | CR25: =CP25/$CP$153*$DS$173 -> 49935.604 | CS25: =BM25+BP25+BR25+BT25+BV25 -> 3100000 | CT25: =CS25/$CS$153*$DS$174 -> 44094.073 | CU25: =CS25+BX25 -> 3100000 | CV25: =CU25/$CU$153*$DS$175 -> 105254.62 | CW25: =CU25+BZ25 -> 6089000 | CX25: =CW25/$CW$153*$DS$176 -> 59153.537 | CY25: =CW25+CB25 -> 6689000 | CZ25: =CY25/$CY$153*750000 -> 10336.187 | DA25: =CY25/$CY$153*$DS$185 -> 26591.164 | DB25: =CY25+CD25 -> 7239000 | DC25: =DB25/$DB$153*$DC$154 -> 40796.576 | DD25: =DB25/$DB$153*$DD$154 -> 27623.157 | DE25: =DB25+CF25 -> 9089000 | DF25: =DE25/$DE$153*$DF$154 -> 24369.686 | DG25: =DE25/$DE$153*$DG$154 -> 81370.196 | DH25: 11894997 | DI25: ='Member position mfumo and excel'!F27 -> 11894997 | DJ25: =DH25-DI25 -> -0.0070940219 | DK25: =DH25/$DH$153*$DK$154 -> 122134.97 | DL25: =DH25/$DH$153*$DL$154 -> 34020.306 | DS25: =CN25+CO25+CQ25+CR25+CT25+CV25+CX25+CZ25+DA25+DC25+DD25+DF25+DG25+DK25+DL25+DN25+DO25+DQ25+DR25 -> 12051153 | DT25: =DS25=CN25+CO25+CQ25+CR25+CT25+CV25+CX25+CZ25+DA25+DC25+DD25+DF25+DG25+DK25+DL25+DN25+DO25+DQ25+DR25 -> TRUE | DU25: =B25 -> Athumani Mwasha | DV25: =DS25 -> 12051153 | DW25: =DS25-CN25 -> 688152.67 | DZ25: =BM25+BP25+BR25+BT25+CO25+CQ25+CR25+CT25 -> 2856502.3 | EB25: =BM25+BP25+BR25+BT25+BV25+BX25+CO25+CQ25+CR25+CT25+CV25 -> 3361756.9
A26: ILS24-F00025 | B26: Hassan Matata | C26: 0746000600 | D26: 45384 | E26: 30000 | F26: Social | G26: 45384 | H26: 170000 | I26: Social | J26: 45657 | K26: 800000 | L26: Shares | BI26: =E26+H26+K26+N26+Q26+T26+W26+Z26+AC26+AF26+AI26+AO26+AL26+AR26+AU26+AX26+BA26+BG26 -> 1000000 | BJ26: =E26+H26 -> 200000 | BL26: =K26 -> 800000 | BM26: =BJ26+BL26+BK26 -> 1000000 | BN26: =BM26=BI26 -> TRUE | BO26: 45946 | BP26: 500000 | BR26: 0 | CE26: 46202 | CF26: 1700000 | CG26: 46204 | CH26: 200000 | CM26: =BP26+BR26+BT26+BV26+BX26+BZ26+CB26+CD26+CF26+CH26+CJ26+CL26 -> 2400000 | CN26: =BM26+CM26 -> 3400000 | CO26: =BM26/$BM$153*$BM$166 -> 14865.925 | CP26: =BM26+BP26+BR26 -> 1500000 | CQ26: =CP26/$CP$153*$DS$172 -> 19644.445 | CR26: =CP26/$CP$153*$DS$173 -> 29961.362 | CS26: =BM26+BP26+BR26+BT26+BV26 -> 1500000 | CT26: =CS26/$CS$153*$DS$174 -> 21335.842 | CU26: =CS26+BX26 -> 1500000 | CV26: =CU26/$CU$153*$DS$175 -> 50929.656 | CW26: =CU26+BZ26 -> 1500000 | CX26: =CW26/$CW$153*$DS$176 -> 14572.229 | CY26: =CW26+CB26 -> 1500000 | CZ26: =CY26/$CY$153*750000 -> 2317.8772 | DA26: =CY26/$CY$153*$DS$185 -> 5963.0356 | DB26: =CY26+CD26 -> 1500000 | DC26: =DB26/$DB$153*$DC$154 -> 8453.497 | DD26: =DB26/$DB$153*$DD$154 -> 5723.8204 | DE26: =DB26+CF26 -> 3200000 | DF26: =DE26/$DE$153*$DF$154 -> 8579.9314 | DG26: =DE26/$DE$153*$DG$154 -> 28648.325 | DH26: 3610995.9 | DI26: ='Member position mfumo and excel'!F28 -> 3610996 | DJ26: =DH26-DI26 -> -0.014385206 | DK26: =DH26/$DH$153*$DK$154 -> 37076.838 | DL26: =DH26/$DH$153*$DL$154 -> 10327.635 | DS26: =CN26+CO26+CQ26+CR26+CT26+CV26+CX26+CZ26+DA26+DC26+DD26+DF26+DG26+DK26+DL26+DN26+DO26+DQ26+DR26 -> 3658400.4 | DT26: =DS26=CN26+CO26+CQ26+CR26+CT26+CV26+CX26+CZ26+DA26+DC26+DD26+DF26+DG26+DK26+DL26+DN26+DO26+DQ26+DR26 -> TRUE | DU26: =B26 -> Hassan Matata | DV26: =DS26 -> 3658400.4 | DW26: =DS26-CN26 -> 258400.42 | DZ26: =BM26+BP26+BR26+BT26+CO26+CQ26+CR26+CT26 -> 1585807.6 | EB26: =BM26+BP26+BR26+BT26+BV26+BX26+CO26+CQ26+CR26+CT26+CV26 -> 1636737.2
A27: ILS24-F00026 | B27: Plasduce Mkeli Mbossa | C27: 0755008144 | D27: 45928 | E27: 1000000 | F27: NMB | G27: 45928 | H27: 900000 | I27: NMB | BI27: =E27+H27+K27+N27+Q27+T27+W27+Z27+AC27+AF27+AI27+AO27+AL27+AR27+AU27+AX27+BA27+BG27 -> 1900000 | BK27: =E27+H27 -> 1900000 | BM27: =BJ27+BL27+BK27 -> 1900000 | BN27: =BM27=BI27 -> TRUE | BP27: 0 | BR27: 0 | CG27: 46212 | CH27: 10000000 | CM27: =BP27+BR27+BT27+BV27+BX27+BZ27+CB27+CD27+CF27+CH27+CJ27+CL27 -> 10000000 | CN27: =BM27+CM27 -> 11900000 | CO27: =BM27/$BM$153*$BM$166 -> 28245.258 | CP27: =BM27+BP27+BR27 -> 1900000 | CQ27: =CP27/$CP$153*$DS$172 -> 24882.963 | CR27: =CP27/$CP$153*$DS$173 -> 37951.059 | CS27: =BM27+BP27+BR27+BT27+BV27 -> 1900000 | CT27: =CS27/$CS$153*$DS$174 -> 27025.399 | CU27: =CS27+BX27 -> 1900000 | CV27: =CU27/$CU$153*$DS$175 -> 64510.898 | CW27: =CU27+BZ27 -> 1900000 | CX27: =CW27/$CW$153*$DS$176 -> 18458.157 | CY27: =CW27+CB27 -> 1900000 | CZ27: =CY27/$CY$153*750000 -> 2935.9778 | DA27: =CY27/$CY$153*$DS$185 -> 7553.1785 | DB27: =CY27+CD27 -> 1900000 | DC27: =DB27/$DB$153*$DC$154 -> 10707.763 | DD27: =DB27/$DB$153*$DD$154 -> 7250.1725 | DE27: =DB27+CF27 -> 1900000 | DF27: =DE27/$DE$153*$DF$154 -> 5094.3343 | DG27: =DE27/$DE$153*$DG$154 -> 17009.943 | DH27: 12151625 | DI27: ='Member position mfumo and excel'!F29 -> 12151625 | DJ27: =DH27-DI27 -> 0.0027528759 | DK27: =DH27/$DH$153*$DK$154 -> 124769.96 | DL27: =DH27/$DH$153*$DL$154 -> 34754.275 | DS27: =CN27+CO27+CQ27+CR27+CT27+CV27+CX27+CZ27+DA27+DC27+DD27+DF27+DG27+DK27+DL27+DN27+DO27+DQ27+DR27 -> 12311149 | DT27: =DS27=CN27+CO27+CQ27+CR27+CT27+CV27+CX27+CZ27+DA27+DC27+DD27+DF27+DG27+DK27+DL27+DN27+DO27+DQ27+DR27 -> TRUE | DU27: =B27 -> Plasduce Mkeli Mbossa | DV27: =DS27 -> 12311149 | DW27: =DS27-CN27 -> 411149.34 | DZ27: =BM27+BP27+BR27+BT27+CO27+CQ27+CR27+CT27 -> 2018104.7 | EB27: =BM27+BP27+BR27+BT27+BV27+BX27+CO27+CQ27+CR27+CT27+CV27 -> 2082615.6
A28: ILS24-F00027 | B28: Saidi Ramadhani Mdee | C28: 0754548239 | D28: 45662 | E28: 1000000 | F28: Shares | BI28: =E28+H28+K28+N28+Q28+T28+W28+Z28+AC28+AF28+AI28+AO28+AL28+AR28+AU28+AX28+BA28+BG28 -> 1000000 | BL28: =E28 -> 1000000 | BM28: =BJ28+BL28+BK28 -> 1000000 | BN28: =BM28=BI28 -> TRUE | BP28: 0 | BQ28: 45990 | BR28: 1000000 | CG28: 46204 | CH28: 2000000 | CM28: =BP28+BR28+BT28+BV28+BX28+BZ28+CB28+CD28+CF28+CH28+CJ28+CL28 -> 3000000 | CN28: =BM28+CM28 -> 4000000 | CO28: =BM28/$BM$153*$BM$166 -> 14865.925 | CP28: =BM28+BP28+BR28 -> 2000000 | CQ28: =CP28/$CP$153*$DS$172 -> 26192.593 | CR28: =CP28/$CP$153*$DS$173 -> 39948.483 | CS28: =BM28+BP28+BR28+BT28+BV28 -> 2000000 | CT28: =CS28/$CS$153*$DS$174 -> 28447.789 | CU28: =CS28+BX28 -> 2000000 | CV28: =CU28/$CU$153*$DS$175 -> 67906.208 | CW28: =CU28+BZ28 -> 2000000 | CX28: =CW28/$CW$153*$DS$176 -> 19429.639 | CY28: =CW28+CB28 -> 2000000 | CZ28: =CY28/$CY$153*750000 -> 3090.503 | DA28: =CY28/$CY$153*$DS$185 -> 7950.7142 | DB28: =CY28+CD28 -> 2000000 | DC28: =DB28/$DB$153*$DC$154 -> 11271.329 | DD28: =DB28/$DB$153*$DD$154 -> 7631.7605 | DE28: =DB28+CF28 -> 2000000 | DF28: =DE28/$DE$153*$DF$154 -> 5362.4571 | DG28: =DE28/$DE$153*$DG$154 -> 17905.203 | DH28: 4250002.6 | DI28: ='Member position mfumo and excel'!F30 -> 4250002.6 | DJ28: =DH28-DI28 -> 0.0042093825 | DK28: =DH28/$DH$153*$DK$154 -> 43638.005 | DL28: =DH28/$DH$153*$DL$154 -> 12155.227 | DS28: =CN28+CO28+CQ28+CR28+CT28+CV28+CX28+CZ28+DA28+DC28+DD28+DF28+DG28+DK28+DL28+DN28+DO28+DQ28+DR28 -> 4305795.8 | DT28: =DS28=CN28+CO28+CQ28+CR28+CT28+CV28+CX28+CZ28+DA28+DC28+DD28+DF28+DG28+DK28+DL28+DN28+DO28+DQ28+DR28 -> TRUE | DU28: =B28 -> Saidi Ramadhani Mdee | DV28: =DS28 -> 4305795.8 | DW28: =DS28-CN28 -> 305795.84 | DZ28: =BM28+BP28+BR28+BT28+CO28+CQ28+CR28+CT28 -> 2109454.8 | EB28: =BM28+BP28+BR28+BT28+BV28+BX28+CO28+CQ28+CR28+CT28+CV28 -> 2177361
A29: ILS24-F00028 | B29: Evance Mori | C29: 0754379191 | D29: 45354 | E29: 100000 | F29: Shares | G29: 45361 | H29: 100000 | I29: Shares | J29: 45411 | K29: 50000 | L29: Social | M29: 45496 | N29: 100000 | O29: Social | P29: 45521 | Q29: 650000 | R29: Shares | S29: 45742 | T29: 200000 | U29: Shares | V29: 45928 | W29: 500000 | X29: NMB | BI29: =E29+H29+K29+N29+Q29+T29+W29+Z29+AC29+AF29+AI29+AO29+AL29+AR29+AU29+AX29+BA29+BG29 -> 1700000 | BJ29: =K29+N29 -> 150000 | BK29: =W29 -> 500000 | BL29: =E29+H29+Q29+T29 -> 1050000 | BM29: =BJ29+BL29+BK29 -> 1700000 | BN29: =BM29=BI29 -> TRUE | BP29: 0 | BR29: 0 | BY29: 46083 | BZ29: =1500000+640000 -> 2140000 | CA29: 46137 | CB29: 1000000 | CC29: 46164 | CD29: 1500000 | CE29: 46198 | CF29: =3500000+2000000 -> 5500000 | CM29: =BP29+BR29+BT29+BV29+BX29+BZ29+CB29+CD29+CF29+CH29+CJ29+CL29 -> 10140000 | CN29: =BM29+CM29 -> 11840000 | CO29: =BM29/$BM$153*$BM$166 -> 25272.073 | CP29: =BM29+BP29+BR29 -> 1700000 | CQ29: =CP29/$CP$153*$DS$172 -> 22263.704 | CR29: =CP29/$CP$153*$DS$173 -> 33956.211 | CS29: =BM29+BP29+BR29+BT29+BV29 -> 1700000 | CT29: =CS29/$CS$153*$DS$174 -> 24180.62 | CU29: =CS29+BX29 -> 1700000 | CV29: =CU29/$CU$153*$DS$175 -> 57720.277 | CW29: =CU29+BZ29 -> 3840000 | CX29: =CW29/$CW$153*$DS$176 -> 37304.907 | CY29: =CW29+CB29 -> 4840000 | CZ29: =CY29/$CY$153*750000 -> 7479.0172 | DA29: =CY29/$CY$153*$DS$185 -> 19240.728 | DB29: =CY29+CD29 -> 6340000 | DC29: =DB29/$DB$153*$DC$154 -> 35730.114 | DD29: =DB29/$DB$153*$DD$154 -> 24192.681 | DE29: =DB29+CF29 -> 11840000 | DF29: =DE29/$DE$153*$DF$154 -> 31745.746 | DG29: =DE29/$DE$153*$DG$154 -> 105998.8 | DH29: 12265085 | DI29: ='Member position mfumo and excel'!F31 -> 12265085 | DJ29: =DH29-DI29 -> 0.00046645664 | DK29: =DH29/$DH$153*$DK$154 -> 125934.94 | DL29: =DH29/$DH$153*$DL$154 -> 35078.775 | DS29: =CN29+CO29+CQ29+CR29+CT29+CV29+CX29+CZ29+DA29+DC29+DD29+DF29+DG29+DK29+DL29+DN29+DO29+DQ29+DR29 -> 12426099 | DT29: =DS29=CN29+CO29+CQ29+CR29+CT29+CV29+CX29+CZ29+DA29+DC29+DD29+DF29+DG29+DK29+DL29+DN29+DO29+DQ29+DR29 -> TRUE | DU29: =B29 -> Evance Mori | DV29: =DS29 -> 12426099 | DW29: =DS29-CN29 -> 586098.6 | DZ29: =BM29+BP29+BR29+BT29+CO29+CQ29+CR29+CT29 -> 1805672.6 | EB29: =BM29+BP29+BR29+BT29+BV29+BX29+CO29+CQ29+CR29+CT29+CV29 -> 1863392.9
A30: ILS24-F00029 | B30: Emanuel Ezekiah Moshi | C30: 0754679533 | D30: 45649 | E30: 800000 | F30: Shares | G30: 45655 | H30: 200000 | I30: Shares | J30: 45687 | K30: 200000 | L30: Shares | M30: 45816 | N30: 200000 | O30: NMB | BI30: =E30+H30+K30+N30+Q30+T30+W30+Z30+AC30+AF30+AI30+AO30+AL30+AR30+AU30+AX30+BA30+BG30 -> 1400000 | BK30: =N30 -> 200000 | BL30: =E30+H30+K30 -> 1200000 | BM30: =BJ30+BL30+BK30 -> 1400000 | BN30: =BM30=BI30 -> TRUE | BO30: 45946 | BP30: 500000 | BR30: 0 | BS30: 45995 | BT30: =500000+500000 -> 1000000 | BW30: 46059 | BX30: =200000+200000 -> 400000 | BY30: 46084 | BZ30: =400000+400000+300000 -> 1100000 | CC30: 46150 | CD30: =5000000+350000+700000 -> 6050000 | CE30: 46203 | CF30: 300000 | CG30: 46234 | CH30: 1000000 | CM30: =BP30+BR30+BT30+BV30+BX30+BZ30+CB30+CD30+CF30+CH30+CJ30+CL30 -> 10350000 | CN30: =BM30+CM30 -> 11750000 | CO30: =BM30/$BM$153*$BM$166 -> 20812.295 | CP30: =BM30+BP30+BR30 -> 1900000 | CQ30: =CP30/$CP$153*$DS$172 -> 24882.963 | CR30: =CP30/$CP$153*$DS$173 -> 37951.059 | CS30: =BM30+BP30+BR30+BT30+BV30 -> 2900000 | CT30: =CS30/$CS$153*$DS$174 -> 41249.294 | CU30: =CS30+BX30 -> 3300000 | CV30: =CU30/$CU$153*$DS$175 -> 112045.24 | CW30: =CU30+BZ30 -> 4400000 | CX30: =CW30/$CW$153*$DS$176 -> 42745.206 | CY30: =CW30+CB30 -> 4400000 | CZ30: =CY30/$CY$153*750000 -> 6799.1065 | DA30: =CY30/$CY$153*$DS$185 -> 17491.571 | DB30: =CY30+CD30 -> 10450000 | DC30: =DB30/$DB$153*$DC$154 -> 58892.696 | DD30: =DB30/$DB$153*$DD$154 -> 39875.948 | DE30: =DB30+CF30 -> 10750000 | DF30: =DE30/$DE$153*$DF$154 -> 28823.207 | DG30: =DE30/$DE$153*$DG$154 -> 96240.467 | DH30: 12277809 | DI30: ='Member position mfumo and excel'!F32 -> 12277809 | DJ30: =DH30-DI30 -> -0.013905419 | DK30: =DH30/$DH$153*$DK$154 -> 126065.59 | DL30: =DH30/$DH$153*$DL$154 -> 35115.167 | DS30: =CN30+CO30+CQ30+CR30+CT30+CV30+CX30+CZ30+DA30+DC30+DD30+DF30+DG30+DK30+DL30+DN30+DO30+DQ30+DR30 -> 12438990 | DT30: =DS30=CN30+CO30+CQ30+CR30+CT30+CV30+CX30+CZ30+DA30+DC30+DD30+DF30+DG30+DK30+DL30+DN30+DO30+DQ30+DR30 -> TRUE | DU30: =B30 -> Emanuel Ezekiah Moshi | DV30: =DS30 -> 12438990 | DW30: =DS30-CN30 -> 688989.81 | DZ30: =BM30+BP30+BR30+BT30+CO30+CQ30+CR30+CT30 -> 3024895.6 | EB30: =BM30+BP30+BR30+BT30+BV30+BX30+CO30+CQ30+CR30+CT30+CV30 -> 3536940.9
A31: ILS24-F00030 | B31: Patrick Salum Kiani | C31: 0757800235 | D31: 45669 | E31: 1000000 | F31: Shares | G31: 45728 | H31: 200000 | I31: Shares | J31: 45919 | K31: 100000 | L31: Shares | M31: 45919 | N31: 200000 | O31: NMB | BI31: =E31+H31+K31+N31+Q31+T31+W31+Z31+AC31+AF31+AI31+AO31+AL31+AR31+AU31+AX31+BA31+BG31 -> 1500000 | BK31: =N31 -> 200000 | BL31: =E31+H31+K31 -> 1300000 | BM31: =BJ31+BL31+BK31 -> 1500000 | BN31: =BM31=BI31 -> TRUE | BO31: 45932 | BP31: 200000 | BQ31: 45985 | BR31: 200000 | BS31: 45997 | BT31: =200000+200000 -> 400000 | BU31: 46042 | BV31: =200000+250000 -> 450000 | BW31: 46059 | BX31: =300000+200000 -> 500000 | BY31: 46100 | BZ31: =200000+100000+200000 -> 500000 | CA31: 46113 | CB31: =200000+200000+200000+500000+200000+200000+1000000 -> 2500000 | CC31: 46144 | CD31: =3000000+500000 -> 3500000 | CE31: 46175 | CF31: =800000+200000+1000000+1000000 -> 3000000 | CM31: =BP31+BR31+BT31+BV31+BX31+BZ31+CB31+CD31+CF31+CH31+CJ31+CL31 -> 11250000 | CN31: =BM31+CM31 -> 12750000 | CO31: =BM31/$BM$153*$BM$166 -> 22298.888 | CP31: =BM31+BP31+BR31 -> 1900000 | CQ31: =CP31/$CP$153*$DS$172 -> 24882.963 | CR31: =CP31/$CP$153*$DS$173 -> 37951.059 | CS31: =BM31+BP31+BR31+BT31+BV31 -> 2750000 | CT31: =CS31/$CS$153*$DS$174 -> 39115.709 | CU31: =CS31+BX31 -> 3250000 | CV31: =CU31/$CU$153*$DS$175 -> 110347.59 | CW31: =CU31+BZ31 -> 3750000 | CX31: =CW31/$CW$153*$DS$176 -> 36430.574 | CY31: =CW31+CB31 -> 6250000 | CZ31: =CY31/$CY$153*750000 -> 9657.8218 | DA31: =CY31/$CY$153*$DS$185 -> 24845.982 | DB31: =CY31+CD31 -> 9750000 | DC31: =DB31/$DB$153*$DC$154 -> 54947.73 | DD31: =DB31/$DB$153*$DD$154 -> 37204.832 | DE31: =DB31+CF31 -> 12750000 | DF31: =DE31/$DE$153*$DF$154 -> 34185.664 | DG31: =DE31/$DE$153*$DG$154 -> 114145.67 | DH31: 13296014 | DI31: ='Member position mfumo and excel'!F33 -> 13296014 | DJ31: =DH31-DI31 -> 0.01119902 | DK31: =DH31/$DH$153*$DK$154 -> 136520.28 | DL31: =DH31/$DH$153*$DL$154 -> 38027.287 | DS31: =CN31+CO31+CQ31+CR31+CT31+CV31+CX31+CZ31+DA31+DC31+DD31+DF31+DG31+DK31+DL31+DN31+DO31+DQ31+DR31 -> 13470562 | DT31: =DS31=CN31+CO31+CQ31+CR31+CT31+CV31+CX31+CZ31+DA31+DC31+DD31+DF31+DG31+DK31+DL31+DN31+DO31+DQ31+DR31 -> TRUE | DU31: =B31 -> Patrick Salum Kiani | DV31: =DS31 -> 13470562 | DW31: =DS31-CN31 -> 720562.05 | DZ31: =BM31+BP31+BR31+BT31+CO31+CQ31+CR31+CT31 -> 2424248.6 | EB31: =BM31+BP31+BR31+BT31+BV31+BX31+CO31+CQ31+CR31+CT31+CV31 -> 3484596.2
A32: ILS24-F00031 | B32: Stephen Nkurlu | C32: 0759178459 | D32: 45355 | E32: 50000 | F32: Social | G32: 45355 | H32: 50000 | I32: Shares | J32: 45358 | K32: 120000 | L32: Shares | M32: 45650 | N32: 800000 | O32: Shares | BI32: =E32+H32+K32+N32+Q32+T32+W32+Z32+AC32+AF32+AI32+AO32+AL32+AR32+AU32+AX32+BA32+BG32 -> 1020000 | BJ32: =E32 -> 50000 | BL32: =H32+K32+N32 -> 970000 | BM32: =BJ32+BL32+BK32 -> 1020000 | BN32: =BM32=BI32 -> TRUE | BP32: 0 | BR32: 0 | BW32: 46071 | BX32: 200000 | BY32: 46108 | BZ32: 250000 | CA32: 46113 | CB32: =250000+500000+860893 -> 1610893 | CE32: 46188 | CF32: =500000+500000 -> 1000000 | CM32: =BP32+BR32+BT32+BV32+BX32+BZ32+CB32+CD32+CF32+CH32+CJ32+CL32 -> 3060893 | CN32: =BM32+CM32 -> 4080893 | CO32: =BM32/$BM$153*$BM$166 -> 15163.244 | CP32: =BM32+BP32+BR32 -> 1020000 | CQ32: =CP32/$CP$153*$DS$172 -> 13358.222 | CR32: =CP32/$CP$153*$DS$173 -> 20373.726 | CS32: =BM32+BP32+BR32+BT32+BV32 -> 1020000 | CT32: =CS32/$CS$153*$DS$174 -> 14508.372 | CU32: =CS32+BX32 -> 1220000 | CV32: =CU32/$CU$153*$DS$175 -> 41422.787 | CW32: =CU32+BZ32 -> 1470000 | CX32: =CW32/$CW$153*$DS$176 -> 14280.785 | CY32: =CW32+CB32 -> 3080893 | CZ32: =CY32/$CY$153*750000 -> 4760.7545 | DA32: =CY32/$CY$153*$DS$185 -> 12247.65 | DB32: =CY32+CD32 -> 3080893 | DC32: =DB32/$DB$153*$DC$154 -> 17362.88 | DD32: =DB32/$DB$153*$DD$154 -> 11756.319 | DE32: =DB32+CF32 -> 4080893 | DF32: =DE32/$DE$153*$DF$154 -> 10941.807 | DG32: =DE32/$DE$153*$DG$154 -> 36534.609 | DH32: 4293604.2 | DI32: ='Member position mfumo and excel'!F34 -> 4293604.2 | DJ32: =DH32-DI32 -> 0.0049967859 | DK32: =DH32/$DH$153*$DK$154 -> 44085.695 | DL32: =DH32/$DH$153*$DL$154 -> 12279.929 | DS32: =CN32+CO32+CQ32+CR32+CT32+CV32+CX32+CZ32+DA32+DC32+DD32+DF32+DG32+DK32+DL32+DN32+DO32+DQ32+DR32 -> 4349969.8 | DT32: =DS32=CN32+CO32+CQ32+CR32+CT32+CV32+CX32+CZ32+DA32+DC32+DD32+DF32+DG32+DK32+DL32+DN32+DO32+DQ32+DR32 -> TRUE | DU32: =B32 -> Stephen Nkurlu | DV32: =DS32 -> 4349969.8 | DW32: =DS32-CN32 -> 269076.78 | DZ32: =BM32+BP32+BR32+BT32+CO32+CQ32+CR32+CT32 -> 1083403.6 | EB32: =BM32+BP32+BR32+BT32+BV32+BX32+CO32+CQ32+CR32+CT32+CV32 -> 1324826.4
A33: ILS24-F00032 | B33: Shabani Salim | C33: 0784561767 | D33: 45652 | E33: 1000000 | F33: Shares | G33: 45729 | H33: 200000 | I33: Shares | BI33: =E33+H33+K33+N33+Q33+T33+W33+Z33+AC33+AF33+AI33+AO33+AL33+AR33+AU33+AX33+BA33+BG33 -> 1200000 | BL33: =E33+H33 -> 1200000 | BM33: =BJ33+BL33+BK33 -> 1200000 | BN33: =BM33=BI33 -> TRUE | BP33: 0 | BR33: 0 | CC33: 46155 | CD33: 2100000 | CM33: =BP33+BR33+BT33+BV33+BX33+BZ33+CB33+CD33+CF33+CH33+CJ33+CL33 -> 2100000 | CN33: =BM33+CM33 -> 3300000 | CO33: =BM33/$BM$153*$BM$166 -> 17839.11 | CP33: =BM33+BP33+BR33 -> 1200000 | CQ33: =CP33/$CP$153*$DS$172 -> 15715.556 | CR33: =CP33/$CP$153*$DS$173 -> 23969.09 | CS33: =BM33+BP33+BR33+BT33+BV33 -> 1200000 | CT33: =CS33/$CS$153*$DS$174 -> 17068.673 | CU33: =CS33+BX33 -> 1200000 | CV33: =CU33/$CU$153*$DS$175 -> 40743.725 | CW33: =CU33+BZ33 -> 1200000 | CX33: =CW33/$CW$153*$DS$176 -> 11657.784 | CY33: =CW33+CB33 -> 1200000 | CZ33: =CY33/$CY$153*750000 -> 1854.3018 | DA33: =CY33/$CY$153*$DS$185 -> 4770.4285 | DB33: =CY33+CD33 -> 3300000 | DC33: =DB33/$DB$153*$DC$154 -> 18597.693 | DD33: =DB33/$DB$153*$DD$154 -> 12592.405 | DE33: =DB33+CF33 -> 3300000 | DF33: =DE33/$DE$153*$DF$154 -> 8848.0542 | DG33: =DE33/$DE$153*$DG$154 -> 29543.585 | DH33: 3503200.4 | DI33: ='Member position mfumo and excel'!F35 -> 3503200.4 | DJ33: =DH33-DI33 -> 0.015035473 | DK33: =DH33/$DH$153*$DK$154 -> 35970.019 | DL33: =DH33/$DH$153*$DL$154 -> 10019.334 | DS33: =CN33+CO33+CQ33+CR33+CT33+CV33+CX33+CZ33+DA33+DC33+DD33+DF33+DG33+DK33+DL33+DN33+DO33+DQ33+DR33 -> 3549189.8 | DT33: =DS33=CN33+CO33+CQ33+CR33+CT33+CV33+CX33+CZ33+DA33+DC33+DD33+DF33+DG33+DK33+DL33+DN33+DO33+DQ33+DR33 -> TRUE | DU33: =B33 -> Shabani Salim | DV33: =DS33 -> 3549189.8 | DW33: =DS33-CN33 -> 249189.76 | DZ33: =BM33+BP33+BR33+BT33+CO33+CQ33+CR33+CT33 -> 1274592.4 | EB33: =BM33+BP33+BR33+BT33+BV33+BX33+CO33+CQ33+CR33+CT33+CV33 -> 1315336.2
A34: ILS24-F00033 | B34: Frederick Peter Ndossi | C34: 0783661006 | D34: 45381 | E34: 50000 | F34: Shares | G34: 45383 | H34: 10000 | I34: Social | J34: 45408 | K34: 10000 | L34: Social | M34: 45529 | N34: 150000 | O34: Social | P34: 45631 | Q34: 580000 | R34: Shares | S34: 45652 | T34: 200000 | U34: Shares | BI34: =E34+H34+K34+N34+Q34+T34+W34+Z34+AC34+AF34+AI34+AO34+AL34+AR34+AU34+AX34+BA34+BG34 -> 1000000 | BJ34: =H34+K34+N34 -> 170000 | BL34: =E34+Q34+T34 -> 830000 | BM34: =BJ34+BL34+BK34 -> 1000000 | BN34: =BM34=BI34 -> TRUE | BO34: 45957 | BP34: 500000 | BR34: 0 | BU34: 46052 | BV34: 100000 | BY34: 46107 | BZ34: =500000+800000 -> 1300000 | CA34: 46140 | CB34: 300000 | CE34: 46182 | CF34: =100000+200000 -> 300000 | CG34: 46228 | CH34: 500000 | CM34: =BP34+BR34+BT34+BV34+BX34+BZ34+CB34+CD34+CF34+CH34+CJ34+CL34 -> 3000000 | CN34: =BM34+CM34 -> 4000000 | CO34: =BM34/$BM$153*$BM$166 -> 14865.925 | CP34: =BM34+BP34+BR34 -> 1500000 | CQ34: =CP34/$CP$153*$DS$172 -> 19644.445 | CR34: =CP34/$CP$153*$DS$173 -> 29961.362 | CS34: =BM34+BP34+BR34+BT34+BV34 -> 1600000 | CT34: =CS34/$CS$153*$DS$174 -> 22758.231 | CU34: =CS34+BX34 -> 1600000 | CV34: =CU34/$CU$153*$DS$175 -> 54324.966 | CW34: =CU34+BZ34 -> 2900000 | CX34: =CW34/$CW$153*$DS$176 -> 28172.977 | CY34: =CW34+CB34 -> 3200000 | CZ34: =CY34/$CY$153*750000 -> 4944.8048 | DA34: =CY34/$CY$153*$DS$185 -> 12721.143 | DB34: =CY34+CD34 -> 3200000 | DC34: =DB34/$DB$153*$DC$154 -> 18034.127 | DD34: =DB34/$DB$153*$DD$154 -> 12210.817 | DE34: =DB34+CF34 -> 3500000 | DF34: =DE34/$DE$153*$DF$154 -> 9384.2999 | DG34: =DE34/$DE$153*$DG$154 -> 31334.105 | DH34: 4258357.2 | DI34: ='Member position mfumo and excel'!F36 -> 4258357.2 | DJ34: =DH34-DI34 -> -0.0071441131 | DK34: =DH34/$DH$153*$DK$154 -> 43723.788 | DL34: =DH34/$DH$153*$DL$154 -> 12179.121 | DS34: =CN34+CO34+CQ34+CR34+CT34+CV34+CX34+CZ34+DA34+DC34+DD34+DF34+DG34+DK34+DL34+DN34+DO34+DQ34+DR34 -> 4314260.1 | DT34: =DS34=CN34+CO34+CQ34+CR34+CT34+CV34+CX34+CZ34+DA34+DC34+DD34+DF34+DG34+DK34+DL34+DN34+DO34+DQ34+DR34 -> TRUE | DU34: =B34 -> Frederick Peter Ndossi | DV34: =DS34 -> 4314260.1 | DW34: =DS34-CN34 -> 314260.11 | DZ34: =BM34+BP34+BR34+BT34+CO34+CQ34+CR34+CT34 -> 1587230 | EB34: =BM34+BP34+BR34+BT34+BV34+BX34+CO34+CQ34+CR34+CT34+CV34 -> 1741554.9
A35: ILS24-F00034 | B35: Abraham Alex Assenga | C35: 0764568979 | D35: 45360 | E35: 90000 | F35: Shares | G35: 45360 | H35: 60000 | I35: Social | J35: 45530 | K35: 600000 | L35: Shares | M35: 45530 | N35: 200000 | O35: Shares | P35: 45657 | Q35: 50000 | R35: Shares | BI35: =E35+H35+K35+N35+Q35+T35+W35+Z35+AC35+AF35+AI35+AO35+AL35+AR35+AU35+AX35+BA35+BG35 -> 1000000 | BJ35: =H35 -> 60000 | BL35: =E35+K35+N35+Q35 -> 940000 | BM35: =BJ35+BL35+BK35 -> 1000000 | BN35: =BM35=BI35 -> TRUE | BP35: 0 | BR35: 0 | CA35: 46137 | CB35: 1000000 | CC35: 46172 | CD35: 1200000 | CG35: 46204 | CH35: 200000 | CM35: =BP35+BR35+BT35+BV35+BX35+BZ35+CB35+CD35+CF35+CH35+CJ35+CL35 -> 2400000 | CN35: =BM35+CM35 -> 3400000 | CO35: =BM35/$BM$153*$BM$166 -> 14865.925 | CP35: =BM35+BP35+BR35 -> 1000000 | CQ35: =CP35/$CP$153*$DS$172 -> 13096.296 | CR35: =CP35/$CP$153*$DS$173 -> 19974.242 | CS35: =BM35+BP35+BR35+BT35+BV35 -> 1000000 | CT35: =CS35/$CS$153*$DS$174 -> 14223.894 | CU35: =CS35+BX35 -> 1000000 | CV35: =CU35/$CU$153*$DS$175 -> 33953.104 | CW35: =CU35+BZ35 -> 1000000 | CX35: =CW35/$CW$153*$DS$176 -> 9714.8196 | CY35: =CW35+CB35 -> 2000000 | CZ35: =CY35/$CY$153*750000 -> 3090.503 | DA35: =CY35/$CY$153*$DS$185 -> 7950.7142 | DB35: =CY35+CD35 -> 3200000 | DC35: =DB35/$DB$153*$DC$154 -> 18034.127 | DD35: =DB35/$DB$153*$DD$154 -> 12210.817 | DE35: =DB35+CF35 -> 3200000 | DF35: =DE35/$DE$153*$DF$154 -> 8579.9314 | DG35: =DE35/$DE$153*$DG$154 -> 28648.325 | DH35: 3584342.7 | DI35: ='Member position mfumo and excel'!F37 -> 3584342.7 | DJ35: =DH35-DI35 -> -0.0017980835 | DK35: =DH35/$DH$153*$DK$154 -> 36803.169 | DL35: =DH35/$DH$153*$DL$154 -> 10251.405 | DS35: =CN35+CO35+CQ35+CR35+CT35+CV35+CX35+CZ35+DA35+DC35+DD35+DF35+DG35+DK35+DL35+DN35+DO35+DQ35+DR35 -> 3631397.3 | DT35: =DS35=CN35+CO35+CQ35+CR35+CT35+CV35+CX35+CZ35+DA35+DC35+DD35+DF35+DG35+DK35+DL35+DN35+DO35+DQ35+DR35 -> TRUE | DU35: =B35 -> Abraham Alex Assenga | DV35: =DS35 -> 3631397.3 | DW35: =DS35-CN35 -> 231397.27 | DZ35: =BM35+BP35+BR35+BT35+CO35+CQ35+CR35+CT35 -> 1062160.4 | EB35: =BM35+BP35+BR35+BT35+BV35+BX35+CO35+CQ35+CR35+CT35+CV35 -> 1096113.5
A36: ILS24-F00035 | B36: Best Magoma | C36: 0754621046 | D36: 45363 | E36: 50000 | F36: Social | G36: 45382 | H36: 100000 | I36: Shares | J36: 45487 | K36: 100000 | L36: Shares | M36: 45652 | N36: 200000 | O36: Shares | P36: 45656 | Q36: 550000 | R36: Shares | BI36: =E36+H36+K36+N36+Q36+T36+W36+Z36+AC36+AF36+AI36+AO36+AL36+AR36+AU36+AX36+BA36+BG36 -> 1000000 | BJ36: =E36 -> 50000 | BL36: =H36+K36+N36+Q36 -> 950000 | BM36: =BJ36+BL36+BK36 -> 1000000 | BN36: =BM36=BI36 -> TRUE | BP36: 0 | BR36: 0 | BU36: 46038 | BV36: =500000+300000 -> 800000 | BY36: 46089 | BZ36: =1070000+200000 -> 1270000 | CE36: 46182 | CF36: 200000 | CM36: =BP36+BR36+BT36+BV36+BX36+BZ36+CB36+CD36+CF36+CH36+CJ36+CL36 -> 2270000 | CN36: =BM36+CM36 -> 3270000 | CO36: =BM36/$BM$153*$BM$166 -> 14865.925 | CP36: =BM36+BP36+BR36 -> 1000000 | CQ36: =CP36/$CP$153*$DS$172 -> 13096.296 | CR36: =CP36/$CP$153*$DS$173 -> 19974.242 | CS36: =BM36+BP36+BR36+BT36+BV36 -> 1800000 | CT36: =CS36/$CS$153*$DS$174 -> 25603.01 | CU36: =CS36+BX36 -> 1800000 | CV36: =CU36/$CU$153*$DS$175 -> 61115.587 | CW36: =CU36+BZ36 -> 3070000 | CX36: =CW36/$CW$153*$DS$176 -> 29824.496 | CY36: =CW36+CB36 -> 3070000 | CZ36: =CY36/$CY$153*750000 -> 4743.9221 | DA36: =CY36/$CY$153*$DS$185 -> 12204.346 | DB36: =CY36+CD36 -> 3070000 | DC36: =DB36/$DB$153*$DC$154 -> 17301.49 | DD36: =DB36/$DB$153*$DD$154 -> 11714.752 | DE36: =DB36+CF36 -> 3270000 | DF36: =DE36/$DE$153*$DF$154 -> 8767.6174 | DG36: =DE36/$DE$153*$DG$154 -> 29275.007 | DH36: 3518486.7 | DI36: ='Member position mfumo and excel'!F38 -> 3518486.7 | DJ36: =DH36-DI36 -> -0.018006271 | DK36: =DH36/$DH$153*$DK$154 -> 36126.975 | DL36: =DH36/$DH$153*$DL$154 -> 10063.053 | DS36: =CN36+CO36+CQ36+CR36+CT36+CV36+CX36+CZ36+DA36+DC36+DD36+DF36+DG36+DK36+DL36+DN36+DO36+DQ36+DR36 -> 3564676.7 | DT36: =DS36=CN36+CO36+CQ36+CR36+CT36+CV36+CX36+CZ36+DA36+DC36+DD36+DF36+DG36+DK36+DL36+DN36+DO36+DQ36+DR36 -> TRUE | DU36: =B36 -> Best Magoma | DV36: =DS36 -> 3564676.7 | DW36: =DS36-CN36 -> 294676.72 | DZ36: =BM36+BP36+BR36+BT36+CO36+CQ36+CR36+CT36 -> 1073539.5 | EB36: =BM36+BP36+BR36+BT36+BV36+BX36+CO36+CQ36+CR36+CT36+CV36 -> 1934655.1
A37: ILS24-F00036 | B37: Bakari Mchila Hemedi | C37: 0768297082 | D37: 45361 | E37: 50000 | F37: Shares | G37: 45361 | H37: 50000 | I37: Social | J37: 45669 | K37: 1000000 | L37: Shares | BI37: =E37+H37+K37+N37+Q37+T37+W37+Z37+AC37+AF37+AI37+AO37+AL37+AR37+AU37+AX37+BA37+BG37 -> 1100000 | BJ37: =H37 -> 50000 | BL37: =E37+K37 -> 1050000 | BM37: =BJ37+BL37+BK37 -> 1100000 | BN37: =BM37=BI37 -> TRUE | BP37: 0 | BR37: 0 | CA37: 46128 | CB37: =1800000+100000 -> 1900000 | CC37: 46154 | CD37: 500000 | CM37: =BP37+BR37+BT37+BV37+BX37+BZ37+CB37+CD37+CF37+CH37+CJ37+CL37 -> 2400000 | CN37: =BM37+CM37 -> 3500000 | CO37: =BM37/$BM$153*$BM$166 -> 16352.518 | CP37: =BM37+BP37+BR37 -> 1100000 | CQ37: =CP37/$CP$153*$DS$172 -> 14405.926 | CR37: =CP37/$CP$153*$DS$173 -> 21971.666 | CS37: =BM37+BP37+BR37+BT37+BV37 -> 1100000 | CT37: =CS37/$CS$153*$DS$174 -> 15646.284 | CU37: =CS37+BX37 -> 1100000 | CV37: =CU37/$CU$153*$DS$175 -> 37348.414 | CW37: =CU37+BZ37 -> 1100000 | CX37: =CW37/$CW$153*$DS$176 -> 10686.302 | CY37: =CW37+CB37 -> 3000000 | CZ37: =CY37/$CY$153*750000 -> 4635.7545 | DA37: =CY37/$CY$153*$DS$185 -> 11926.071 | DB37: =CY37+CD37 -> 3500000 | DC37: =DB37/$DB$153*$DC$154 -> 19724.826 | DD37: =DB37/$DB$153*$DD$154 -> 13355.581 | DE37: =DB37+CF37 -> 3500000 | DF37: =DE37/$DE$153*$DF$154 -> 9384.2999 | DG37: =DE37/$DE$153*$DG$154 -> 31334.105 | DH37: 3706771.7 | DI37: ='Member position mfumo and excel'!F39 -> 3706771.8 | DJ37: =DH37-DI37 -> -0.0026080017 | DK37: =DH37/$DH$153*$DK$154 -> 38060.241 | DL37: =DH37/$DH$153*$DL$154 -> 10601.558 | DS37: =CN37+CO37+CQ37+CR37+CT37+CV37+CX37+CZ37+DA37+DC37+DD37+DF37+DG37+DK37+DL37+DN37+DO37+DQ37+DR37 -> 3755433.5 | DT37: =DS37=CN37+CO37+CQ37+CR37+CT37+CV37+CX37+CZ37+DA37+DC37+DD37+DF37+DG37+DK37+DL37+DN37+DO37+DQ37+DR37 -> TRUE | DU37: =B37 -> Bakari Mchila Hemedi | DV37: =DS37 -> 3755433.5 | DW37: =DS37-CN37 -> 255433.55 | DZ37: =BM37+BP37+BR37+BT37+CO37+CQ37+CR37+CT37 -> 1168376.4 | EB37: =BM37+BP37+BR37+BT37+BV37+BX37+CO37+CQ37+CR37+CT37+CV37 -> 1205724.8
A38: ILS24-F00037 | B38: Elibariki Mkumbo | C38: 0787014096 | D38: 45357 | E38: 250000 | F38: Shares | G38: 45365 | H38: 100000 | I38: Social | J38: 45530 | K38: 230000 | L38: Shares | M38: 45687 | N38: 420000 | O38: Shares | BI38: =E38+H38+K38+N38+Q38+T38+W38+Z38+AC38+AF38+AI38+AO38+AL38+AR38+AU38+AX38+BA38+BG38 -> 1000000 | BJ38: =H38 -> 100000 | BL38: =E38+K38+N38 -> 900000 | BM38: =BJ38+BL38+BK38 -> 1000000 | BN38: =BM38=BI38 -> TRUE | BP38: 0 | BQ38: 45989 | BR38: 200000 | BS38: 46001 | BT38: 400000 | BU38: 46053 | BV38: 500000 | BW38: 46058 | BX38: 1000000 | BY38: 46090 | BZ38: 2000000 | CA38: 46123 | CB38: 1000000 | CE38: 46192 | CF38: =6000000+4000000+2000000 -> 12000000 | CM38: =BP38+BR38+BT38+BV38+BX38+BZ38+CB38+CD38+CF38+CH38+CJ38+CL38 -> 17100000 | CN38: =BM38+CM38 -> 18100000 | CO38: =BM38/$BM$153*$BM$166 -> 14865.925 | CP38: =BM38+BP38+BR38 -> 1200000 | CQ38: =CP38/$CP$153*$DS$172 -> 15715.556 | CR38: =CP38/$CP$153*$DS$173 -> 23969.09 | CS38: =BM38+BP38+BR38+BT38+BV38 -> 2100000 | CT38: =CS38/$CS$153*$DS$174 -> 29870.178 | CU38: =CS38+BX38 -> 3100000 | CV38: =CU38/$CU$153*$DS$175 -> 105254.62 | CW38: =CU38+BZ38 -> 5100000 | CX38: =CW38/$CW$153*$DS$176 -> 49545.58 | CY38: =CW38+CB38 -> 6100000 | CZ38: =CY38/$CY$153*750000 -> 9426.0341 | DA38: =CY38/$CY$153*$DS$185 -> 24249.678 | DB38: =CY38+CD38 -> 6100000 | DC38: =DB38/$DB$153*$DC$154 -> 34377.554 | DD38: =DB38/$DB$153*$DD$154 -> 23276.869 | DE38: =DB38+CF38 -> 18100000 | DF38: =DE38/$DE$153*$DF$154 -> 48530.237 | DG38: =DE38/$DE$153*$DG$154 -> 162042.09 | DH38: 18641123 | DI38: ='Member position mfumo and excel'!F40 -> 18641123 | DJ38: =DH38-DI38 -> -0.007311061 | DK38: =DH38/$DH$153*$DK$154 -> 191402.57 | DL38: =DH38/$DH$153*$DL$154 -> 53314.574 | DS38: =CN38+CO38+CQ38+CR38+CT38+CV38+CX38+CZ38+DA38+DC38+DD38+DF38+DG38+DK38+DL38+DN38+DO38+DQ38+DR38 -> 18885841 | DT38: =DS38=CN38+CO38+CQ38+CR38+CT38+CV38+CX38+CZ38+DA38+DC38+DD38+DF38+DG38+DK38+DL38+DN38+DO38+DQ38+DR38 -> TRUE | DU38: =B38 -> Elibariki Mkumbo | DV38: =DS38 -> 18885841 | DW38: =DS38-CN38 -> 785840.56 | DZ38: =BM38+BP38+BR38+BT38+CO38+CQ38+CR38+CT38 -> 1684420.7 | EB38: =BM38+BP38+BR38+BT38+BV38+BX38+CO38+CQ38+CR38+CT38+CV38 -> 3289675.4
A39: ILS24-F00038 | B39: Charles Suka Jangu | C39: 0752505062 | D39: 45382 | E39: 100000 | F39: Social | G39: 45382 | H39: 100000 | I39: Shares | J39: 45693 | K39: 500000 | L39: Shares | M39: 45881 | N39: 300000 | O39: NMB | BI39: =E39+H39+K39+N39+Q39+T39+W39+Z39+AC39+AF39+AI39+AO39+AL39+AR39+AU39+AX39+BA39+BG39 -> 1000000 | BJ39: =E39 -> 100000 | BK39: 300000 | BL39: =H39+K39 -> 600000 | BM39: =BJ39+BL39+BK39 -> 1000000 | BN39: =BM39=BI39 -> TRUE | BP39: 0 | BR39: 0 | BU39: 46045 | BV39: 752064 | BY39: 46082 | BZ39: =500000+650000+1000000 -> 2150000 | CA39: 46113 | CB39: =608288+538582 -> 1146870 | CE39: 46174 | CF39: =1200000 -> 1200000 | CG39: 46204 | CH39: 1752610 | CM39: =BP39+BR39+BT39+BV39+BX39+BZ39+CB39+CD39+CF39+CH39+CJ39+CL39 -> 7001544 | CN39: =BM39+CM39 -> 8001544 | CO39: =BM39/$BM$153*$BM$166 -> 14865.925 | CP39: =BM39+BP39+BR39 -> 1000000 | CQ39: =CP39/$CP$153*$DS$172 -> 13096.296 | CR39: =CP39/$CP$153*$DS$173 -> 19974.242 | CS39: =BM39+BP39+BR39+BT39+BV39 -> 1752064 | CT39: =CS39/$CS$153*$DS$174 -> 24921.173 | CU39: =CS39+BX39 -> 1752064 | CV39: =CU39/$CU$153*$DS$175 -> 59488.011 | CW39: =CU39+BZ39 -> 3902064 | CX39: =CW39/$CW$153*$DS$176 -> 37907.848 | CY39: =CW39+CB39 -> 5048934 | CZ39: =CY39/$CY$153*750000 -> 7801.8728 | DA39: =CY39/$CY$153*$DS$185 -> 20071.316 | DB39: =CY39+CD39 -> 5048934 | DC39: =DB39/$DB$153*$DC$154 -> 28454.099 | DD39: =DB39/$DB$153*$DD$154 -> 19266.127 | DE39: =DB39+CF39 -> 6248934 | DF39: =DE39/$DE$153*$DF$154 -> 16754.82 | DG39: =DE39/$DE$153*$DG$154 -> 55944.216 | DH39: 8320089.9 | DI39: ='Member position mfumo and excel'!F41 -> 8320090 | DJ39: =DH39-DI39 -> -0.013276526 | DK39: =DH39/$DH$153*$DK$154 -> 85428.683 | DL39: =DH39/$DH$153*$DL$154 -> 23795.886 | DS39: =CN39+CO39+CQ39+CR39+CT39+CV39+CX39+CZ39+DA39+DC39+DD39+DF39+DG39+DK39+DL39+DN39+DO39+DQ39+DR39 -> 8429314.5 | DT39: =DS39=CN39+CO39+CQ39+CR39+CT39+CV39+CX39+CZ39+DA39+DC39+DD39+DF39+DG39+DK39+DL39+DN39+DO39+DQ39+DR39 -> TRUE | DU39: =B39 -> Charles Suka Jangu | DV39: =DS39 -> 8429314.5 | DW39: =DS39-CN39 -> 427770.52 | DZ39: =BM39+BP39+BR39+BT39+CO39+CQ39+CR39+CT39 -> 1072857.6 | EB39: =BM39+BP39+BR39+BT39+BV39+BX39+CO39+CQ39+CR39+CT39+CV39 -> 1884409.6
A40: ILS24-F00039 | B40: Abdillahi Moshi | C40: 0754263187 | D40: 45372 | E40: 80000 | F40: Social | G40: 45372 | H40: 100000 | I40: Shares | J40: 45661 | K40: 820000 | L40: Shares | BI40: =E40+H40+K40+N40+Q40+T40+W40+Z40+AC40+AF40+AI40+AO40+AL40+AR40+AU40+AX40+BA40+BG40 -> 1000000 | BJ40: =E40+K40 -> 900000 | BL40: =H40 -> 100000 | BM40: =BJ40+BL40+BK40 -> 1000000 | BN40: =BM40=BI40 -> TRUE | BP40: 0 | BR40: 0 | BS40: 46003 | BT40: 500000 | BU40: 46049 | BV40: 100000 | CC40: 46146 | CD40: 260000 | CG40: 46204 | CH40: =500000+1000000 -> 1500000 | CM40: =BP40+BR40+BT40+BV40+BX40+BZ40+CB40+CD40+CF40+CH40+CJ40+CL40 -> 2360000 | CN40: =BM40+CM40 -> 3360000 | CO40: =BM40/$BM$153*$BM$166 -> 14865.925 | CP40: =BM40+BP40+BR40 -> 1000000 | CQ40: =CP40/$CP$153*$DS$172 -> 13096.296 | CR40: =CP40/$CP$153*$DS$173 -> 19974.242 | CS40: =BM40+BP40+BR40+BT40+BV40 -> 1600000 | CT40: =CS40/$CS$153*$DS$174 -> 22758.231 | CU40: =CS40+BX40 -> 1600000 | CV40: =CU40/$CU$153*$DS$175 -> 54324.966 | CW40: =CU40+BZ40 -> 1600000 | CX40: =CW40/$CW$153*$DS$176 -> 15543.711 | CY40: =CW40+CB40 -> 1600000 | CZ40: =CY40/$CY$153*750000 -> 2472.4024 | DA40: =CY40/$CY$153*$DS$185 -> 6360.5714 | DB40: =CY40+CD40 -> 1860000 | DC40: =DB40/$DB$153*$DC$154 -> 10482.336 | DD40: =DB40/$DB$153*$DD$154 -> 7097.5372 | DE40: =DB40+CF40 -> 1860000 | DF40: =DE40/$DE$153*$DF$154 -> 4987.0851 | DG40: =DE40/$DE$153*$DG$154 -> 16651.839 | DH40: 3548615.1 | DI40: ='Member position mfumo and excel'!F42 -> 3548615.2 | DJ40: =DH40-DI40 -> -0.016928118 | DK40: =DH40/$DH$153*$DK$154 -> 36436.327 | DL40: =DH40/$DH$153*$DL$154 -> 10149.222 | DS40: =CN40+CO40+CQ40+CR40+CT40+CV40+CX40+CZ40+DA40+DC40+DD40+DF40+DG40+DK40+DL40+DN40+DO40+DQ40+DR40 -> 3595200.7 | DT40: =DS40=CN40+CO40+CQ40+CR40+CT40+CV40+CX40+CZ40+DA40+DC40+DD40+DF40+DG40+DK40+DL40+DN40+DO40+DQ40+DR40 -> TRUE | DU40: =B40 -> Abdillahi Moshi | DV40: =DS40 -> 3595200.7 | DW40: =DS40-CN40 -> 235200.69 | DZ40: =BM40+BP40+BR40+BT40+CO40+CQ40+CR40+CT40 -> 1570694.7 | EB40: =BM40+BP40+BR40+BT40+BV40+BX40+CO40+CQ40+CR40+CT40+CV40 -> 1725019.7
A41: ILS24-F00040 | B41: Ahmad Yahya | C41: 0713508199 | D41: 45356 | E41: 50000 | F41: Shares | G41: 45359 | H41: 40000 | I41: Social | J41: 45373 | K41: 50000 | L41: Social | M41: 45373 | N41: 120000 | O41: Shares | P41: 45663 | Q41: 780000 | R41: Shares | BI41: =E41+H41+K41+N41+Q41+T41+W41+Z41+AC41+AF41+AI41+AO41+AL41+AR41+AU41+AX41+BA41+BG41 -> 1040000 | BJ41: =H41+K41 -> 90000 | BL41: =E41+N41+Q41 -> 950000 | BM41: =BJ41+BL41+BK41 -> 1040000 | BN41: =BM41=BI41 -> TRUE | BO41: 45953 | BP41: 500000 | BQ41: 45972 | BR41: 800000 | BS41: 45994 | BT41: =200000+300000 -> 500000 | BU41: 46026 | BV41: 200000 | BY41: 46085 | BZ41: 500000 | CA41: 46121 | CB41: =400000+86306 -> 486306 | CC41: 46145 | CD41: 400000 | CE41: 46201 | CF41: 400000 | CG41: 46216 | CH41: =400000+400000+4000000 -> 4800000 | CM41: =BP41+BR41+BT41+BV41+BX41+BZ41+CB41+CD41+CF41+CH41+CJ41+CL41 -> 8586306 | CN41: =BM41+CM41 -> 9626306 | CO41: =BM41/$BM$153*$BM$166 -> 15460.562 | CP41: =BM41+BP41+BR41 -> 2340000 | CQ41: =CP41/$CP$153*$DS$172 -> 30645.334 | CR41: =CP41/$CP$153*$DS$173 -> 46739.725 | CS41: =BM41+BP41+BR41+BT41+BV41 -> 3040000 | CT41: =CS41/$CS$153*$DS$174 -> 43240.639 | CU41: =CS41+BX41 -> 3040000 | CV41: =CU41/$CU$153*$DS$175 -> 103217.44 | CW41: =CU41+BZ41 -> 3540000 | CX41: =CW41/$CW$153*$DS$176 -> 34390.461 | CY41: =CW41+CB41 -> 4026306 | CZ41: =CY41/$CY$153*750000 -> 6221.6553 | DA41: =CY41/$CY$153*$DS$185 -> 16006.004 | DB41: =CY41+CD41 -> 4426306 | DC41: =DB41/$DB$153*$DC$154 -> 24945.176 | DD41: =DB41/$DB$153*$DD$154 -> 16890.254 | DE41: =DB41+CF41 -> 4826306 | DF41: =DE41/$DE$153*$DF$154 -> 12940.429 | DG41: =DE41/$DE$153*$DG$154 -> 43207.995 | DH41: 10020212 | DI41: ='Member position mfumo and excel'!F43 -> 10020212 | DJ41: =DH41-DI41 -> 0.00091067702 | DK41: =DH41/$DH$153*$DK$154 -> 102885.12 | DL41: =DH41/$DH$153*$DL$154 -> 28658.322 | DS41: =CN41+CO41+CQ41+CR41+CT41+CV41+CX41+CZ41+DA41+DC41+DD41+DF41+DG41+DK41+DL41+DN41+DO41+DQ41+DR41 -> 10151755 | DT41: =DS41=CN41+CO41+CQ41+CR41+CT41+CV41+CX41+CZ41+DA41+DC41+DD41+DF41+DG41+DK41+DL41+DN41+DO41+DQ41+DR41 -> TRUE | DU41: =B41 -> Ahmad Yahya | DV41: =DS41 -> 10151755 | DW41: =DS41-CN41 -> 525449.12 | DZ41: =BM41+BP41+BR41+BT41+CO41+CQ41+CR41+CT41 -> 2976086.3 | EB41: =BM41+BP41+BR41+BT41+BV41+BX41+CO41+CQ41+CR41+CT41+CV41 -> 3279303.7
A42: ILS24-F00041 | B42: Edgar Shumbusho | D42: 45359 | E42: 100000 | F42: Social | G42: 45359 | H42: 130000 | I42: Shares | J42: 45383 | K42: 70000 | L42: Social | M42: 45383 | N42: 120000 | O42: Shares | P42: 45910 | Q42: 1500000 | R42: NMB | BI42: =E42+H42+K42+N42+Q42+T42+W42+Z42+AC42+AF42+AI42+AO42+AL42+AR42+AU42+AX42+BA42+BG42 -> 1920000 | BJ42: =E42+K42 -> 170000 | BK42: =Q42 -> 1500000 | BL42: =H42+N42 -> 250000 | BM42: =BJ42+BL42+BK42 -> 1920000 | BN42: =BM42=BI42 -> TRUE | BO42: 45957 | BP42: 734958 | BR42: 0 | CG42: 46223 | CH42: =1000000+230000+255000+520000+200000+1050000+300000+1000000+450000+1000000 -> 6005000 | CM42: =BP42+BR42+BT42+BV42+BX42+BZ42+CB42+CD42+CF42+CH42+CJ42+CL42 -> 6739958 | CN42: =BM42+CM42 -> 8659958 | CO42: =BM42/$BM$153*$BM$166 -> 28542.576 | CP42: =BM42+BP42+BR42 -> 2654958 | CQ42: =CP42/$CP$153*$DS$172 -> 34770.117 | CR42: =CP42/$CP$153*$DS$173 -> 53030.773 | CS42: =BM42+BP42+BR42+BT42+BV42 -> 2654958 | CT42: =CS42/$CS$153*$DS$174 -> 37763.842 | CU42: =CS42+BX42 -> 2654958 | CV42: =CU42/$CU$153*$DS$175 -> 90144.065 | CW42: =CU42+BZ42 -> 2654958 | CX42: =CW42/$CW$153*$DS$176 -> 25792.438 | CY42: =CW42+CB42 -> 2654958 | CZ42: =CY42/$CY$153*750000 -> 4102.5778 | DA42: =CY42/$CY$153*$DS$185 -> 10554.406 | DB42: =CY42+CD42 -> 2654958 | DC42: =DB42/$DB$153*$DC$154 -> 14962.453 | DD42: =DB42/$DB$153*$DD$154 -> 10131.002 | DE42: =DB42+CF42 -> 2654958 | DF42: =DE42/$DE$153*$DF$154 -> 7118.5492 | DG42: =DE42/$DE$153*$DG$154 -> 23768.781 | DH42: 9000639.6 | DI42: ='Member position mfumo and excel'!F44 -> 9000639.6 | DJ42: =DH42-DI42 -> -0.010217339 | DK42: =DH42/$DH$153*$DK$154 -> 92416.403 | DL42: =DH42/$DH$153*$DL$154 -> 25742.293 | DS42: =CN42+CO42+CQ42+CR42+CT42+CV42+CX42+CZ42+DA42+DC42+DD42+DF42+DG42+DK42+DL42+DN42+DO42+DQ42+DR42 -> 9118798.3 | DT42: =DS42=CN42+CO42+CQ42+CR42+CT42+CV42+CX42+CZ42+DA42+DC42+DD42+DF42+DG42+DK42+DL42+DN42+DO42+DQ42+DR42 -> TRUE | DU42: =B42 -> Edgar Shumbusho | DV42: =DS42 -> 9118798.3 | DW42: =DS42-CN42 -> 458840.28 | DZ42: =BM42+BP42+BR42+BT42+CO42+CQ42+CR42+CT42 -> 2809065.3 | EB42: =BM42+BP42+BR42+BT42+BV42+BX42+CO42+CQ42+CR42+CT42+CV42 -> 2899209.4
A43: ILS24-F00042 | B43: Adamu Urassa | C43: 0754710685 | D43: 45409 | E43: 250000 | F43: Shares | G43: 45393 | H43: 100000 | I43: Social | J43: 45530 | K43: 450000 | L43: Shares | M43: 45657 | N43: 200000 | O43: Shares | BI43: =E43+H43+K43+N43+Q43+T43+W43+Z43+AC43+AF43+AI43+AO43+AL43+AR43+AU43+AX43+BA43+BG43 -> 1000000 | BJ43: =H43 -> 100000 | BL43: =E43+K43+N43 -> 900000 | BM43: =BJ43+BL43+BK43 -> 1000000 | BN43: =BM43=BI43 -> TRUE | BP43: 0 | BR43: 0 | BU43: 46037 | BV43: 2000000 | CA43: 46137 | CB43: 10000000 | CM43: =BP43+BR43+BT43+BV43+BX43+BZ43+CB43+CD43+CF43+CH43+CJ43+CL43 -> 12000000 | CN43: =BM43+CM43 -> 13000000 | CO43: =BM43/$BM$153*$BM$166 -> 14865.925 | CP43: =BM43+BP43+BR43 -> 1000000 | CQ43: =CP43/$CP$153*$DS$172 -> 13096.296 | CR43: =CP43/$CP$153*$DS$173 -> 19974.242 | CS43: =BM43+BP43+BR43+BT43+BV43 -> 3000000 | CT43: =CS43/$CS$153*$DS$174 -> 42671.683 | CU43: =CS43+BX43 -> 3000000 | CV43: =CU43/$CU$153*$DS$175 -> 101859.31 | CW43: =CU43+BZ43 -> 3000000 | CX43: =CW43/$CW$153*$DS$176 -> 29144.459 | CY43: =CW43+CB43 -> 13000000 | CZ43: =CY43/$CY$153*750000 -> 20088.269 | DA43: =CY43/$CY$153*$DS$185 -> 51679.642 | DB43: =CY43+CD43 -> 13000000 | DC43: =DB43/$DB$153*$DC$154 -> 73263.64 | DD43: =DB43/$DB$153*$DD$154 -> 49606.443 | DE43: =DB43+CF43 -> 13000000 | DF43: =DE43/$DE$153*$DF$154 -> 34855.971 | DG43: =DE43/$DE$153*$DG$154 -> 116383.82 | DH43: 13567490 | DI43: ='Member position mfumo and excel'!F45 -> 13567490 | DJ43: =DH43-DI43 -> 0.0037302244 | DK43: =DH43/$DH$153*$DK$154 -> 139307.72 | DL43: =DH43/$DH$153*$DL$154 -> 38803.72 | DS43: =CN43+CO43+CQ43+CR43+CT43+CV43+CX43+CZ43+DA43+DC43+DD43+DF43+DG43+DK43+DL43+DN43+DO43+DQ43+DR43 -> 13745601 | DT43: =DS43=CN43+CO43+CQ43+CR43+CT43+CV43+CX43+CZ43+DA43+DC43+DD43+DF43+DG43+DK43+DL43+DN43+DO43+DQ43+DR43 -> TRUE | DU43: =B43 -> Adamu Urassa | DV43: =DS43 -> 13745601 | DW43: =DS43-CN43 -> 745601.15 | DZ43: =BM43+BP43+BR43+BT43+CO43+CQ43+CR43+CT43 -> 1090608.1 | EB43: =BM43+BP43+BR43+BT43+BV43+BX43+CO43+CQ43+CR43+CT43+CV43 -> 3192467.5
A44: ILS24-F00043 | B44: Innocent R. Kasigwa | C44: 0756666600 | D44: 45357 | E44: 50000 | F44: Shares | G44: 45381 | H44: 150000 | I44: Shares | J44: 45649 | K44: 300000 | L44: Shares | M44: 45659 | N44: 500000 | O44: NMB | BI44: =E44+H44+K44+N44+Q44+T44+W44+Z44+AC44+AF44+AI44+AO44+AL44+AR44+AU44+AX44+BA44+BG44 -> 1000000 | BL44: =E44+H44+K44+N44 -> 1000000 | BM44: =BJ44+BL44+BK44 -> 1000000 | BN44: =BM44=BI44 -> TRUE | BP44: 0 | BR44: 0 | BS44: 46022 | BT44: =200000+300000 -> 500000 | BW44: 46078 | BX44: 500000 | BY44: 46099 | BZ44: 1000000 | CE44: 46176 | CF44: 500000 | CM44: =BP44+BR44+BT44+BV44+BX44+BZ44+CB44+CD44+CF44+CH44+CJ44+CL44 -> 2500000 | CN44: =BM44+CM44 -> 3500000 | CO44: =BM44/$BM$153*$BM$166 -> 14865.925 | CP44: =BM44+BP44+BR44 -> 1000000 | CQ44: =CP44/$CP$153*$DS$172 -> 13096.296 | CR44: =CP44/$CP$153*$DS$173 -> 19974.242 | CS44: =BM44+BP44+BR44+BT44+BV44 -> 1500000 | CT44: =CS44/$CS$153*$DS$174 -> 21335.842 | CU44: =CS44+BX44 -> 2000000 | CV44: =CU44/$CU$153*$DS$175 -> 67906.208 | CW44: =CU44+BZ44 -> 3000000 | CX44: =CW44/$CW$153*$DS$176 -> 29144.459 | CY44: =CW44+CB44 -> 3000000 | CZ44: =CY44/$CY$153*750000 -> 4635.7545 | DA44: =CY44/$CY$153*$DS$185 -> 11926.071 | DB44: =CY44+CD44 -> 3000000 | DC44: =DB44/$DB$153*$DC$154 -> 16906.994 | DD44: =DB44/$DB$153*$DD$154 -> 11447.641 | DE44: =DB44+CF44 -> 3500000 | DF44: =DE44/$DE$153*$DF$154 -> 9384.2999 | DG44: =DE44/$DE$153*$DG$154 -> 31334.105 | DH44: 3751957.8 | DI44: ='Member position mfumo and excel'!F46 -> 3751957.8 | DJ44: =DH44-DI44 -> -0.0026963092 | DK44: =DH44/$DH$153*$DK$154 -> 38524.201 | DL44: =DH44/$DH$153*$DL$154 -> 10730.793 | DS44: =CN44+CO44+CQ44+CR44+CT44+CV44+CX44+CZ44+DA44+DC44+DD44+DF44+DG44+DK44+DL44+DN44+DO44+DQ44+DR44 -> 3801212.8 | DT44: =DS44=CN44+CO44+CQ44+CR44+CT44+CV44+CX44+CZ44+DA44+DC44+DD44+DF44+DG44+DK44+DL44+DN44+DO44+DQ44+DR44 -> TRUE | DU44: =B44 -> Innocent R. Kasigwa | DV44: =DS44 -> 3801212.8 | DW44: =DS44-CN44 -> 301212.83 | DZ44: =BM44+BP44+BR44+BT44+CO44+CQ44+CR44+CT44 -> 1569272.3 | EB44: =BM44+BP44+BR44+BT44+BV44+BX44+CO44+CQ44+CR44+CT44+CV44 -> 2137178.5
A45: ILS24-F00044 | B45: Abduel Kitururu | C45: 0784707170 | D45: 45361 | E45: 280000 | F45: Shares | G45: 45361 | H45: 70000 | I45: Social | J45: 45361 | K45: 280000 | L45: Shares | BI45: =E45+H45+K45+N45+Q45+T45+W45+Z45+AC45+AF45+AI45+AO45+AL45+AR45+AU45+AX45+BA45+BG45 -> 630000 | BJ45: =H45 -> 70000 | BL45: =E45+K45 -> 560000 | BM45: =BJ45+BL45+BK45 -> 630000 | BN45: =BM45=BI45 -> TRUE | BP45: 0 | BR45: 0 | BW45: 46063 | BX45: 2000000 | CA45: 46137 | CB45: =1000000+500000 -> 1500000 | CC45: 46150 | CD45: =1000000+1500000+2200000+1000000+500000+500000 -> 6700000 | CE45: 46174 | CF45: =3000000+2000000+1000000+1500000+4000000+5000000 -> 16500000 | CM45: =BP45+BR45+BT45+BV45+BX45+BZ45+CB45+CD45+CF45+CH45+CJ45+CL45 -> 26700000 | CN45: =BM45+CM45 -> 27330000 | CO45: =BM45/$BM$153*$BM$166 -> 9365.5328 | CP45: =BM45+BP45+BR45 -> 630000 | CQ45: =CP45/$CP$153*$DS$172 -> 8250.6667 | CR45: =CP45/$CP$153*$DS$173 -> 12583.772 | CS45: =BM45+BP45+BR45+BT45+BV45 -> 630000 | CT45: =CS45/$CS$153*$DS$174 -> 8961.0534 | CU45: =CS45+BX45 -> 2630000 | CV45: =CU45/$CU$153*$DS$175 -> 89296.664 | CW45: =CU45+BZ45 -> 2630000 | CX45: =CW45/$CW$153*$DS$176 -> 25549.976 | CY45: =CW45+CB45 -> 4130000 | CZ45: =CY45/$CY$153*750000 -> 6381.8886 | DA45: =CY45/$CY$153*$DS$185 -> 16418.225 | DB45: =CY45+CD45 -> 10830000 | DC45: =DB45/$DB$153*$DC$154 -> 61034.248 | DD45: =DB45/$DB$153*$DD$154 -> 41325.983 | DE45: =DB45+CF45 -> 27330000 | DF45: =DE45/$DE$153*$DF$154 -> 73277.976 | DG45: =DE45/$DE$153*$DG$154 -> 244674.6 | DH45: 27927121 | DI45: ='Member position mfumo and excel'!F47 -> 27927121 | DJ45: =DH45-DI45 -> 0.006107863 | DK45: =DH45/$DH$153*$DK$154 -> 286748.96 | DL45: =DH45/$DH$153*$DL$154 -> 79873.005 | DS45: =CN45+CO45+CQ45+CR45+CT45+CV45+CX45+CZ45+DA45+DC45+DD45+DF45+DG45+DK45+DL45+DN45+DO45+DQ45+DR45 -> 28293743 | DT45: =DS45=CN45+CO45+CQ45+CR45+CT45+CV45+CX45+CZ45+DA45+DC45+DD45+DF45+DG45+DK45+DL45+DN45+DO45+DQ45+DR45 -> TRUE | DU45: =B45 -> Abduel Kitururu | DV45: =DS45 -> 28293743 | DW45: =DS45-CN45 -> 963742.55 | DZ45: =BM45+BP45+BR45+BT45+CO45+CQ45+CR45+CT45 -> 669161.03 | EB45: =BM45+BP45+BR45+BT45+BV45+BX45+CO45+CQ45+CR45+CT45+CV45 -> 2758457.7
A46: ILS24-F00045 | B46: Ernest Phelician Shirima | C46: 0713123480 | D46: 45360 | E46: 290000 | F46: Shares | G46: 45360 | H46: 110000 | I46: Social | J46: 45523 | K46: 340000 | L46: Shares | M46: 45523 | N46: 60000 | O46: Social | BI46: =E46+H46+K46+N46+Q46+T46+W46+Z46+AC46+AF46+AI46+AO46+AL46+AR46+AU46+AX46+BA46+BG46 -> 800000 | BJ46: =H46+N46 -> 170000 | BL46: =E46+K46 -> 630000 | BM46: =BJ46+BL46+BK46 -> 800000 | BN46: =BM46=BI46 -> TRUE | BP46: 0 | BR46: 0 | CA46: 46119 | CB46: 2500000 | CM46: =BP46+BR46+BT46+BV46+BX46+BZ46+CB46+CD46+CF46+CH46+CJ46+CL46 -> 2500000 | CN46: =BM46+CM46 -> 3300000 | CO46: =BM46/$BM$153*$BM$166 -> 11892.74 | CP46: =BM46+BP46+BR46 -> 800000 | CQ46: =CP46/$CP$153*$DS$172 -> 10477.037 | CR46: =CP46/$CP$153*$DS$173 -> 15979.393 | CS46: =BM46+BP46+BR46+BT46+BV46 -> 800000 | CT46: =CS46/$CS$153*$DS$174 -> 11379.115 | CU46: =CS46+BX46 -> 800000 | CV46: =CU46/$CU$153*$DS$175 -> 27162.483 | CW46: =CU46+BZ46 -> 800000 | CX46: =CW46/$CW$153*$DS$176 -> 7771.8557 | CY46: =CW46+CB46 -> 3300000 | CZ46: =CY46/$CY$153*750000 -> 5099.3299 | DA46: =CY46/$CY$153*$DS$185 -> 13118.678 | DB46: =CY46+CD46 -> 3300000 | DC46: =DB46/$DB$153*$DC$154 -> 18597.693 | DD46: =DB46/$DB$153*$DD$154 -> 12592.405 | DE46: =DB46+CF46 -> 3300000 | DF46: =DE46/$DE$153*$DF$154 -> 8848.0542 | DG46: =DE46/$DE$153*$DG$154 -> 29543.585 | DH46: 3472462.4 | DI46: ='Member position mfumo and excel'!F48 -> 3472462.4 | DJ46: =DH46-DI46 -> 0.00066278595 | DK46: =DH46/$DH$153*$DK$154 -> 35654.409 | DL46: =DH46/$DH$153*$DL$154 -> 9931.4215 | DS46: =CN46+CO46+CQ46+CR46+CT46+CV46+CX46+CZ46+DA46+DC46+DD46+DF46+DG46+DK46+DL46+DN46+DO46+DQ46+DR46 -> 3518048.2 | DT46: =DS46=CN46+CO46+CQ46+CR46+CT46+CV46+CX46+CZ46+DA46+DC46+DD46+DF46+DG46+DK46+DL46+DN46+DO46+DQ46+DR46 -> TRUE | DU46: =B46 -> Ernest Phelician Shirima | DV46: =DS46 -> 3518048.2 | DW46: =DS46-CN46 -> 218048.2 | DZ46: =BM46+BP46+BR46+BT46+CO46+CQ46+CR46+CT46 -> 849728.29 | EB46: =BM46+BP46+BR46+BT46+BV46+BX46+CO46+CQ46+CR46+CT46+CV46 -> 876890.77
A47: ILS24-F00046 | B47: Adolph William Ndeabura | C47: 0764812183 | D47: 45660 | E47: 1000000 | F47: Shares | BI47: =E47+H47+K47+N47+Q47+T47+W47+Z47+AC47+AF47+AI47+AO47+AL47+AR47+AU47+AX47+BA47+BG47 -> 1000000 | BL47: =E47 -> 1000000 | BM47: =BJ47+BL47+BK47 -> 1000000 | BN47: =BM47=BI47 -> TRUE | BP47: 0 | BR47: 0 | BY47: 46096 | BZ47: =350000+1600000 -> 1950000 | CA47: 46132 | CB47: 200000 | CE47: 46185 | CF47: =2500000+3500000 -> 6000000 | CG47: 46206 | CH47: =700000+500000 -> 1200000 | CM47: =BP47+BR47+BT47+BV47+BX47+BZ47+CB47+CD47+CF47+CH47+CJ47+CL47 -> 9350000 | CN47: =BM47+CM47 -> 10350000 | CO47: =BM47/$BM$153*$BM$166 -> 14865.925 | CP47: =BM47+BP47+BR47 -> 1000000 | CQ47: =CP47/$CP$153*$DS$172 -> 13096.296 | CR47: =CP47/$CP$153*$DS$173 -> 19974.242 | CS47: =BM47+BP47+BR47+BT47+BV47 -> 1000000 | CT47: =CS47/$CS$153*$DS$174 -> 14223.894 | CU47: =CS47+BX47 -> 1000000 | CV47: =CU47/$CU$153*$DS$175 -> 33953.104 | CW47: =CU47+BZ47 -> 2950000 | CX47: =CW47/$CW$153*$DS$176 -> 28658.718 | CY47: =CW47+CB47 -> 3150000 | CZ47: =CY47/$CY$153*750000 -> 4867.5422 | DA47: =CY47/$CY$153*$DS$185 -> 12522.375 | DB47: =CY47+CD47 -> 3150000 | DC47: =DB47/$DB$153*$DC$154 -> 17752.344 | DD47: =DB47/$DB$153*$DD$154 -> 12020.023 | DE47: =DB47+CF47 -> 9150000 | DF47: =DE47/$DE$153*$DF$154 -> 24533.241 | DG47: =DE47/$DE$153*$DG$154 -> 81916.304 | DH47: 10628384 | DI47: ='Member position mfumo and excel'!F49 -> 10628384 | DJ47: =DH47-DI47 -> 0.018314565 | DK47: =DH47/$DH$153*$DK$154 -> 109129.69 | DL47: =DH47/$DH$153*$DL$154 -> 30397.726 | DS47: =CN47+CO47+CQ47+CR47+CT47+CV47+CX47+CZ47+DA47+DC47+DD47+DF47+DG47+DK47+DL47+DN47+DO47+DQ47+DR47 -> 10767911 | DT47: =DS47=CN47+CO47+CQ47+CR47+CT47+CV47+CX47+CZ47+DA47+DC47+DD47+DF47+DG47+DK47+DL47+DN47+DO47+DQ47+DR47 -> TRUE | DU47: =B47 -> Adolph William Ndeabura | DV47: =DS47 -> 10767911 | DW47: =DS47-CN47 -> 417911.43 | DZ47: =BM47+BP47+BR47+BT47+CO47+CQ47+CR47+CT47 -> 1062160.4 | EB47: =BM47+BP47+BR47+BT47+BV47+BX47+CO47+CQ47+CR47+CT47+CV47 -> 1096113.5
